<?xml version="1.0" encoding="Windows-1252"?>
<SolarModel xmlns:xsi="http://www.w3.org/2001/XMLSchema-instance" xmlns:xsd="http://www.w3.org/2001/XMLSchema">
  <Id>2843ae3f-05fc-484c-a841-57a066efac95</Id>
  <name>Bueturn 149</name>
  <isActive>false</isActive>
  <galacticPosition>
    <x>-1724.2944653488953</x>
    <y>1257.1420723697129</y>
  </galacticPosition>
  <color>
    <r>0</r>
    <g>0</g>
    <b>0</b>
    <a>0</a>
  </color>
  <solar>
    <name>Bueturn 149 MainSequence</name>
    <orbit>
      <sma>0</sma>
      <ecc>0</ecc>
      <inc>0</inc>
      <lpe>0</lpe>
      <lan>0</lan>
      <mna>0</mna>
      <eph>0</eph>
    </orbit>
    <groundStructures />
    <spaceStructures />
    <color>
      <r>1</r>
      <g>0.9784954</g>
      <b>0.9507819</b>
      <a>1</a>
    </color>
    <satelites>
      <SolarBody>
        <name>Bueturn 149 Planet 1</name>
        <orbit>
          <sma>20096561152</sma>
          <ecc>0.00077136512845754623</ecc>
          <inc>0</inc>
          <lpe>1.1280233860015869</lpe>
          <lan>0</lan>
          <mna>1.1280233860015869</mna>
          <eph>0</eph>
        </orbit>
        <groundStructures />
        <spaceStructures />
        <color>
          <r>0.5</r>
          <g>0.5</g>
          <b>0.5</b>
          <a>1</a>
        </color>
        <satelites />
        <totalPopulation>0</totalPopulation>
        <solarType>Planet</solarType>
        <solarSubType>Rocky</solarSubType>
        <mass>9.3373012542724608E+23</mass>
        <bodyRadius>3348.3901384967448</bodyRadius>
        <lastKnownPosition>
          <x>0</x>
          <y>0</y>
        </lastKnownPosition>
        <surfaceTemp>51.712283648357115</surfaceTemp>
        <surfacePressure>7.9328107833862305</surfacePressure>
        <luminosity>0</luminosity>
        <bondAlebo>0.873490571975708</bondAlebo>
        <greenhouse>1.6465850073335604</greenhouse>
        <surfaceGravity>0.566247228079177</surfaceGravity>
        <planetTiles>
          <PlanetTile>
            <planetTileType>Rocky</planetTileType>
            <count>7</count>
          </PlanetTile>
          <PlanetTile>
            <planetTileType>Desert</planetTileType>
            <count>1</count>
          </PlanetTile>
        </planetTiles>
        <rawResources>
          <RawResource>
            <name>Armoroid</name>
            <id>1</id>
            <amount>953416</amount>
            <accessibility>0.90931832790374756</accessibility>
          </RawResource>
          <RawResource>
            <name>Coppode</name>
            <id>2</id>
            <amount>25411</amount>
            <accessibility>0.066562175750732422</accessibility>
          </RawResource>
          <RawResource>
            <name>Warium</name>
            <id>4</id>
            <amount>38199</amount>
            <accessibility>0.12700521945953369</accessibility>
          </RawResource>
          <RawResource>
            <name>Glassitum</name>
            <id>6</id>
            <amount>496178</amount>
            <accessibility>0.95038580894470215</accessibility>
          </RawResource>
        </rawResources>
        <population>0</population>
        <solarIndex>
          <int>148</int>
          <int>0</int>
        </solarIndex>
      </SolarBody>
    </satelites>
    <totalPopulation>0</totalPopulation>
    <solarType>Star</solarType>
    <solarSubType>MainSequence</solarSubType>
    <mass>9.20417967224121E+31</mass>
    <bodyRadius>25035175.701399554</bodyRadius>
    <lastKnownPosition>
      <x>0</x>
      <y>0</y>
    </lastKnownPosition>
    <surfaceTemp>6206.6444423974854</surfaceTemp>
    <surfacePressure>1</surfacePressure>
    <luminosity>3.9458811797357062E+28</luminosity>
    <bondAlebo>0.5</bondAlebo>
    <greenhouse>0.1123595</greenhouse>
    <surfaceGravity>0.9984828894269675</surfaceGravity>
    <planetTiles />
    <rawResources />
    <population>0</population>
    <solarIndex>
      <int>148</int>
    </solarIndex>
  </solar>
  <nearStars>
    <Id>cc2377ad-1ad3-441f-9bc3-083137c52502</Id>
    <Id>be39f9b5-ee43-4da4-8020-5307915aae39</Id>
    <Id>dc666200-36b8-4b8f-a7d3-70286aa4abdf</Id>
  </nearStars>
  <government />
  <governmentInfluence>0</governmentInfluence>
  <isCapital>false</isCapital>
  <index>148</index>
</SolarModel>