<?xml version="1.0" encoding="Windows-1252"?>
<SolarModel xmlns:xsi="http://www.w3.org/2001/XMLSchema-instance" xmlns:xsd="http://www.w3.org/2001/XMLSchema">
  <Id>2dbbc518-565b-4f9b-8147-6948afc5b0ec</Id>
  <name>Blara 8 185</name>
  <isActive>false</isActive>
  <galacticPosition>
    <x>-671.9745901221645</x>
    <y>618.95428773197227</y>
  </galacticPosition>
  <color>
    <r>0.5</r>
    <g>0.5</g>
    <b>0.5</b>
    <a>1</a>
  </color>
  <solar>
    <name>Blara 8 185 WhiteDwarf</name>
    <orbit>
      <sma>0</sma>
      <ecc>0</ecc>
      <inc>0</inc>
      <lpe>0</lpe>
      <lan>0</lan>
      <mna>0</mna>
      <eph>0</eph>
    </orbit>
    <population>0</population>
    <color>
      <r>0.874874234</r>
      <g>0.905463636</g>
      <b>1</b>
      <a>1</a>
    </color>
    <satelites>
      <SolarBody>
        <name>Blara 8 185 Planet 1</name>
        <orbit>
          <sma>514158690304</sma>
          <ecc>0.0081201661378145218</ecc>
          <inc>0</inc>
          <lpe>5.817164421081543</lpe>
          <lan>0</lan>
          <mna>5.817164421081543</mna>
          <eph>0</eph>
        </orbit>
        <planetTiles>
          <PlanetTile>
            <planetTileType>Rocky</planetTileType>
            <rawResources>
              <RawResource>
                <rawResourceType>Horizorium</rawResourceType>
                <amount>587310</amount>
                <accesibility>0.51290386915206909</accesibility>
              </RawResource>
            </rawResources>
          </PlanetTile>
          <PlanetTile>
            <planetTileType>Ice</planetTileType>
            <rawResources>
              <RawResource>
                <rawResourceType>Doronimum</rawResourceType>
                <amount>3051</amount>
                <accesibility>0.39595848321914673</accesibility>
              </RawResource>
            </rawResources>
          </PlanetTile>
          <PlanetTile>
            <planetTileType>Desert</planetTileType>
            <rawResources>
              <RawResource>
                <rawResourceType>Astodium</rawResourceType>
                <amount>29236</amount>
                <accesibility>0.83025062084198</accesibility>
              </RawResource>
              <RawResource>
                <rawResourceType>Galiditum</rawResourceType>
                <amount>986169</amount>
                <accesibility>0.34114137291908264</accesibility>
              </RawResource>
            </rawResources>
          </PlanetTile>
          <PlanetTile>
            <planetTileType>Rocky</planetTileType>
            <rawResources>
              <RawResource>
                <rawResourceType>Horizorium</rawResourceType>
                <amount>3497645</amount>
                <accesibility>0.1848924309015274</accesibility>
              </RawResource>
              <RawResource>
                <rawResourceType>Dodite</rawResourceType>
                <amount>335282</amount>
                <accesibility>0.98708093166351318</accesibility>
              </RawResource>
            </rawResources>
          </PlanetTile>
          <PlanetTile>
            <planetTileType>Desert</planetTileType>
            <rawResources>
              <RawResource>
                <rawResourceType>Horizorium</rawResourceType>
                <amount>5131828</amount>
                <accesibility>0.54843729734420776</accesibility>
              </RawResource>
              <RawResource>
                <rawResourceType>Galiditum</rawResourceType>
                <amount>407051</amount>
                <accesibility>0.8269343376159668</accesibility>
              </RawResource>
            </rawResources>
          </PlanetTile>
          <PlanetTile>
            <planetTileType>Rocky</planetTileType>
            <rawResources>
              <RawResource>
                <rawResourceType>Horizorium</rawResourceType>
                <amount>6273482</amount>
                <accesibility>0.62422782182693481</accesibility>
              </RawResource>
              <RawResource>
                <rawResourceType>Dodite</rawResourceType>
                <amount>726309</amount>
                <accesibility>0.073732264339923859</accesibility>
              </RawResource>
            </rawResources>
          </PlanetTile>
          <PlanetTile>
            <planetTileType>Ice</planetTileType>
            <rawResources />
          </PlanetTile>
          <PlanetTile>
            <planetTileType>Rocky</planetTileType>
            <rawResources>
              <RawResource>
                <rawResourceType>Horizorium</rawResourceType>
                <amount>3854823</amount>
                <accesibility>0.24441114068031311</accesibility>
              </RawResource>
            </rawResources>
          </PlanetTile>
          <PlanetTile>
            <planetTileType>Rocky</planetTileType>
            <rawResources>
              <RawResource>
                <rawResourceType>Goldium</rawResourceType>
                <amount>93511</amount>
                <accesibility>0.6870080828666687</accesibility>
              </RawResource>
              <RawResource>
                <rawResourceType>Horizorium</rawResourceType>
                <amount>8279485</amount>
                <accesibility>0.023211957886815071</accesibility>
              </RawResource>
            </rawResources>
          </PlanetTile>
          <PlanetTile>
            <planetTileType>Rocky</planetTileType>
            <rawResources>
              <RawResource>
                <rawResourceType>Horizorium</rawResourceType>
                <amount>187893</amount>
                <accesibility>0.41418689489364624</accesibility>
              </RawResource>
              <RawResource>
                <rawResourceType>Dodite</rawResourceType>
                <amount>89465</amount>
                <accesibility>0.49843376874923706</accesibility>
              </RawResource>
            </rawResources>
          </PlanetTile>
          <PlanetTile>
            <planetTileType>Rocky</planetTileType>
            <rawResources>
              <RawResource>
                <rawResourceType>Horizorium</rawResourceType>
                <amount>5366874</amount>
                <accesibility>0.95658612251281738</accesibility>
              </RawResource>
              <RawResource>
                <rawResourceType>Dodite</rawResourceType>
                <amount>359234</amount>
                <accesibility>0.6996883749961853</accesibility>
              </RawResource>
            </rawResources>
          </PlanetTile>
          <PlanetTile>
            <planetTileType>Rocky</planetTileType>
            <rawResources>
              <RawResource>
                <rawResourceType>Horizorium</rawResourceType>
                <amount>5068720</amount>
                <accesibility>0.22681513428688049</accesibility>
              </RawResource>
              <RawResource>
                <rawResourceType>Dodite</rawResourceType>
                <amount>923312</amount>
                <accesibility>0.93101298809051514</accesibility>
              </RawResource>
            </rawResources>
          </PlanetTile>
          <PlanetTile>
            <planetTileType>Rocky</planetTileType>
            <rawResources>
              <RawResource>
                <rawResourceType>Dodite</rawResourceType>
                <amount>963848</amount>
                <accesibility>0.78186881542205811</accesibility>
              </RawResource>
            </rawResources>
          </PlanetTile>
          <PlanetTile>
            <planetTileType>Volcanic</planetTileType>
            <rawResources>
              <RawResource>
                <rawResourceType>Doronimum</rawResourceType>
                <amount>73313</amount>
                <accesibility>0.20871761441230774</accesibility>
              </RawResource>
              <RawResource>
                <rawResourceType>Astodium</rawResourceType>
                <amount>294147</amount>
                <accesibility>0.42741960287094116</accesibility>
              </RawResource>
              <RawResource>
                <rawResourceType>Galiditum</rawResourceType>
                <amount>707689</amount>
                <accesibility>0.597532331943512</accesibility>
              </RawResource>
            </rawResources>
          </PlanetTile>
          <PlanetTile>
            <planetTileType>Rocky</planetTileType>
            <rawResources>
              <RawResource>
                <rawResourceType>Horizorium</rawResourceType>
                <amount>440733</amount>
                <accesibility>0.70014208555221558</accesibility>
              </RawResource>
              <RawResource>
                <rawResourceType>Uronimum</rawResourceType>
                <amount>2823</amount>
                <accesibility>0.46955209970474243</accesibility>
              </RawResource>
              <RawResource>
                <rawResourceType>Galiditum</rawResourceType>
                <amount>45223</amount>
                <accesibility>0.942345380783081</accesibility>
              </RawResource>
            </rawResources>
          </PlanetTile>
          <PlanetTile>
            <planetTileType>Desert</planetTileType>
            <rawResources>
              <RawResource>
                <rawResourceType>Horizorium</rawResourceType>
                <amount>4518366</amount>
                <accesibility>0.5196947455406189</accesibility>
              </RawResource>
              <RawResource>
                <rawResourceType>Galiditum</rawResourceType>
                <amount>253338</amount>
                <accesibility>0.96832823753356934</accesibility>
              </RawResource>
            </rawResources>
          </PlanetTile>
        </planetTiles>
        <population>0</population>
        <color>
          <r>0.5</r>
          <g>0.5</g>
          <b>0.5</b>
          <a>1</a>
        </color>
        <satelites>
          <SolarBody>
            <name>Blara 8 185Moon 1</name>
            <orbit>
              <sma>1054508608</sma>
              <ecc>0.0032712290994822979</ecc>
              <inc>0</inc>
              <lpe>4.6971173286437988</lpe>
              <lan>0</lan>
              <mna>4.6971173286437988</mna>
              <eph>0</eph>
            </orbit>
            <planetTiles>
              <PlanetTile>
                <planetTileType>Rocky</planetTileType>
                <rawResources>
                  <RawResource>
                    <rawResourceType>Goldium</rawResourceType>
                    <amount>869952</amount>
                    <accesibility>0.29925873875617981</accesibility>
                  </RawResource>
                  <RawResource>
                    <rawResourceType>Horizorium</rawResourceType>
                    <amount>7903580</amount>
                    <accesibility>0.293888121843338</accesibility>
                  </RawResource>
                  <RawResource>
                    <rawResourceType>Dodite</rawResourceType>
                    <amount>578766</amount>
                    <accesibility>0.76919782161712646</accesibility>
                  </RawResource>
                </rawResources>
              </PlanetTile>
              <PlanetTile>
                <planetTileType>Rocky</planetTileType>
                <rawResources>
                  <RawResource>
                    <rawResourceType>Horizorium</rawResourceType>
                    <amount>6506119</amount>
                    <accesibility>0.029532436281442642</accesibility>
                  </RawResource>
                  <RawResource>
                    <rawResourceType>Dodite</rawResourceType>
                    <amount>756579</amount>
                    <accesibility>0.17581845819950104</accesibility>
                  </RawResource>
                </rawResources>
              </PlanetTile>
              <PlanetTile>
                <planetTileType>Ice</planetTileType>
                <rawResources />
              </PlanetTile>
              <PlanetTile>
                <planetTileType>Rocky</planetTileType>
                <rawResources>
                  <RawResource>
                    <rawResourceType>Horizorium</rawResourceType>
                    <amount>5735128</amount>
                    <accesibility>0.19390466809272766</accesibility>
                  </RawResource>
                  <RawResource>
                    <rawResourceType>Dodite</rawResourceType>
                    <amount>180840</amount>
                    <accesibility>0.36899736523628235</accesibility>
                  </RawResource>
                </rawResources>
              </PlanetTile>
              <PlanetTile>
                <planetTileType>Rocky</planetTileType>
                <rawResources>
                  <RawResource>
                    <rawResourceType>Silvite</rawResourceType>
                    <amount>677485</amount>
                    <accesibility>0.5994833111763</accesibility>
                  </RawResource>
                  <RawResource>
                    <rawResourceType>Horizorium</rawResourceType>
                    <amount>950550</amount>
                    <accesibility>0.26950624585151672</accesibility>
                  </RawResource>
                </rawResources>
              </PlanetTile>
              <PlanetTile>
                <planetTileType>Rocky</planetTileType>
                <rawResources>
                  <RawResource>
                    <rawResourceType>Horizorium</rawResourceType>
                    <amount>8865994</amount>
                    <accesibility>0.3371303379535675</accesibility>
                  </RawResource>
                  <RawResource>
                    <rawResourceType>Dodite</rawResourceType>
                    <amount>213471</amount>
                    <accesibility>0.81307125091552734</accesibility>
                  </RawResource>
                  <RawResource>
                    <rawResourceType>Galiditum</rawResourceType>
                    <amount>101658</amount>
                    <accesibility>0.48413985967636108</accesibility>
                  </RawResource>
                </rawResources>
              </PlanetTile>
              <PlanetTile>
                <planetTileType>Rocky</planetTileType>
                <rawResources>
                  <RawResource>
                    <rawResourceType>Horizorium</rawResourceType>
                    <amount>3780644</amount>
                    <accesibility>0.45362955331802368</accesibility>
                  </RawResource>
                </rawResources>
              </PlanetTile>
            </planetTiles>
            <population>0</population>
            <color>
              <r>0.5</r>
              <g>0.5</g>
              <b>0.5</b>
              <a>1</a>
            </color>
            <satelites />
            <solarType>Moon</solarType>
            <solarSubType>Rocky</solarSubType>
            <mass>4.5245452880859378E+23</mass>
            <bodyRadius>2957953.9579925709</bodyRadius>
            <lastKnownPosition>
              <x>0</x>
              <y>0</y>
            </lastKnownPosition>
            <surfaceTemp>10452.294894354638</surfaceTemp>
            <surfacePressure>0.039688523858785629</surfacePressure>
            <luminosity>0</luminosity>
            <bondAlebo>0.32894864678382874</bondAlebo>
            <greenhouse>0.0039359797532194929</greenhouse>
            <surfaceGravity>0.35160006503433333</surfaceGravity>
            <solarIndex>
              <int>184</int>
              <int>0</int>
              <int>0</int>
            </solarIndex>
          </SolarBody>
        </satelites>
        <solarType>Planet</solarType>
        <solarSubType>Rocky</solarSubType>
        <mass>7.4884635925292965E+24</mass>
        <bodyRadius>6729081.5545507791</bodyRadius>
        <lastKnownPosition>
          <x>0</x>
          <y>0</y>
        </lastKnownPosition>
        <surfaceTemp>11284.378505836619</surfaceTemp>
        <surfacePressure>0.013277927413582802</surfacePressure>
        <luminosity>0</luminosity>
        <bondAlebo>0.091156966984272</bondAlebo>
        <greenhouse>0.001311979302373982</greenhouse>
        <surfaceGravity>1.1244443471645431</surfaceGravity>
        <solarIndex>
          <int>184</int>
          <int>0</int>
        </solarIndex>
      </SolarBody>
      <SolarBody>
        <name>Blara 8 185 Comet 2</name>
        <orbit>
          <sma>2631470940160</sma>
          <ecc>0.94845843315124512</ecc>
          <inc>0</inc>
          <lpe>2.3921685218811035</lpe>
          <lan>0</lan>
          <mna>2.3921685218811035</mna>
          <eph>0</eph>
        </orbit>
        <planetTiles>
          <PlanetTile>
            <planetTileType>Rocky</planetTileType>
            <rawResources>
              <RawResource>
                <rawResourceType>Uronimum</rawResourceType>
                <amount>8091</amount>
                <accesibility>0.22794583439826965</accesibility>
              </RawResource>
              <RawResource>
                <rawResourceType>Galiditum</rawResourceType>
                <amount>899722</amount>
                <accesibility>0.66402870416641235</accesibility>
              </RawResource>
            </rawResources>
          </PlanetTile>
        </planetTiles>
        <population>0</population>
        <color>
          <r>0.5</r>
          <g>0.5</g>
          <b>0.5</b>
          <a>1</a>
        </color>
        <satelites />
        <solarType>Comet</solarType>
        <solarSubType>Rocky</solarSubType>
        <mass>990000000000000</mass>
        <bodyRadius>3525.0340862535486</bodyRadius>
        <lastKnownPosition>
          <x>0</x>
          <y>0</y>
        </lastKnownPosition>
        <surfaceTemp>0</surfaceTemp>
        <surfacePressure>0</surfacePressure>
        <luminosity>0</luminosity>
        <bondAlebo>0.39982539415359497</bondAlebo>
        <greenhouse>0</greenhouse>
        <surfaceGravity>0.00054170816221064207</surfaceGravity>
        <solarIndex>
          <int>184</int>
          <int>1</int>
        </solarIndex>
      </SolarBody>
      <SolarBody>
        <name>Blara 8 185 DwarfPlanet 3</name>
        <orbit>
          <sma>2785299660800</sma>
          <ecc>0.050184741616249084</ecc>
          <inc>0</inc>
          <lpe>1.5705251693725586</lpe>
          <lan>0</lan>
          <mna>1.5705251693725586</mna>
          <eph>0</eph>
        </orbit>
        <planetTiles>
          <PlanetTile>
            <planetTileType>Rocky</planetTileType>
            <rawResources>
              <RawResource>
                <rawResourceType>Horizorium</rawResourceType>
                <amount>8343780</amount>
                <accesibility>0.66334825754165649</accesibility>
              </RawResource>
            </rawResources>
          </PlanetTile>
          <PlanetTile>
            <planetTileType>Rocky</planetTileType>
            <rawResources>
              <RawResource>
                <rawResourceType>Silvite</rawResourceType>
                <amount>669299</amount>
                <accesibility>0.92015600204467773</accesibility>
              </RawResource>
              <RawResource>
                <rawResourceType>Horizorium</rawResourceType>
                <amount>4929792</amount>
                <accesibility>0.98905253410339355</accesibility>
              </RawResource>
            </rawResources>
          </PlanetTile>
          <PlanetTile>
            <planetTileType>Rocky</planetTileType>
            <rawResources>
              <RawResource>
                <rawResourceType>Horizorium</rawResourceType>
                <amount>9781522</amount>
                <accesibility>0.37103787064552307</accesibility>
              </RawResource>
            </rawResources>
          </PlanetTile>
        </planetTiles>
        <population>0</population>
        <color>
          <r>0.5</r>
          <g>0.5</g>
          <b>0.5</b>
          <a>1</a>
        </color>
        <satelites />
        <solarType>DwarfPlanet</solarType>
        <solarSubType>Rocky</solarSubType>
        <mass>3.3E+22</mass>
        <bodyRadius>1086260.1164563813</bodyRadius>
        <lastKnownPosition>
          <x>0</x>
          <y>0</y>
        </lastKnownPosition>
        <surfaceTemp>4125.0543547522648</surfaceTemp>
        <surfacePressure>0.018588347360491753</surfacePressure>
        <luminosity>0</luminosity>
        <bondAlebo>0.523836076259613</bondAlebo>
        <greenhouse>0.0018380524071024229</greenhouse>
        <surfaceGravity>0.1901529634997059</surfaceGravity>
        <solarIndex>
          <int>184</int>
          <int>2</int>
        </solarIndex>
      </SolarBody>
      <SolarBody>
        <name>Blara 8 185 DwarfPlanet 4</name>
        <orbit>
          <sma>894089887744</sma>
          <ecc>0.29634881019592285</ecc>
          <inc>0</inc>
          <lpe>2.2272918224334717</lpe>
          <lan>0</lan>
          <mna>2.2272918224334717</mna>
          <eph>0</eph>
        </orbit>
        <planetTiles>
          <PlanetTile>
            <planetTileType>Rocky</planetTileType>
            <rawResources>
              <RawResource>
                <rawResourceType>Silvite</rawResourceType>
                <amount>472626</amount>
                <accesibility>0.88095653057098389</accesibility>
              </RawResource>
              <RawResource>
                <rawResourceType>Horizorium</rawResourceType>
                <amount>4797015</amount>
                <accesibility>0.19720473885536194</accesibility>
              </RawResource>
              <RawResource>
                <rawResourceType>Astodium</rawResourceType>
                <amount>79087</amount>
                <accesibility>0.16502656042575836</accesibility>
              </RawResource>
            </rawResources>
          </PlanetTile>
          <PlanetTile>
            <planetTileType>Rocky</planetTileType>
            <rawResources>
              <RawResource>
                <rawResourceType>Goldium</rawResourceType>
                <amount>556984</amount>
                <accesibility>0.95228159427642822</accesibility>
              </RawResource>
              <RawResource>
                <rawResourceType>Silvite</rawResourceType>
                <amount>827226</amount>
                <accesibility>0.55859917402267456</accesibility>
              </RawResource>
              <RawResource>
                <rawResourceType>Horizorium</rawResourceType>
                <amount>2707932</amount>
                <accesibility>0.83290863037109375</accesibility>
              </RawResource>
              <RawResource>
                <rawResourceType>Dodite</rawResourceType>
                <amount>881441</amount>
                <accesibility>0.88501930236816406</accesibility>
              </RawResource>
            </rawResources>
          </PlanetTile>
          <PlanetTile>
            <planetTileType>Volcanic</planetTileType>
            <rawResources>
              <RawResource>
                <rawResourceType>Uronimum</rawResourceType>
                <amount>59452</amount>
                <accesibility>0.6978422999382019</accesibility>
              </RawResource>
              <RawResource>
                <rawResourceType>Doronimum</rawResourceType>
                <amount>65102</amount>
                <accesibility>0.96704220771789551</accesibility>
              </RawResource>
            </rawResources>
          </PlanetTile>
        </planetTiles>
        <population>0</population>
        <color>
          <r>0.5</r>
          <g>0.5</g>
          <b>0.5</b>
          <a>1</a>
        </color>
        <satelites />
        <solarType>DwarfPlanet</solarType>
        <solarSubType>Rocky</solarSubType>
        <mass>1.9E+22</mass>
        <bodyRadius>1017896.7862432037</bodyRadius>
        <lastKnownPosition>
          <x>0</x>
          <y>0</y>
        </lastKnownPosition>
        <surfaceTemp>7751.35903981299</surfaceTemp>
        <surfacePressure>0.95753377676010132</surfacePressure>
        <luminosity>0</luminosity>
        <bondAlebo>0.41259866952896118</bondAlebo>
        <greenhouse>0.10702960169782831</greenhouse>
        <surfaceGravity>0.12468176487704036</surfaceGravity>
        <solarIndex>
          <int>184</int>
          <int>3</int>
        </solarIndex>
      </SolarBody>
      <SolarBody>
        <name>Blara 8 185 Planet 5</name>
        <orbit>
          <sma>6254351613952</sma>
          <ecc>0.000329500442603603</ecc>
          <inc>0</inc>
          <lpe>1.693785548210144</lpe>
          <lan>0</lan>
          <mna>1.693785548210144</mna>
          <eph>0</eph>
        </orbit>
        <planetTiles>
          <PlanetTile>
            <planetTileType>Rocky</planetTileType>
            <rawResources>
              <RawResource>
                <rawResourceType>Horizorium</rawResourceType>
                <amount>1254083</amount>
                <accesibility>0.97163784503936768</accesibility>
              </RawResource>
              <RawResource>
                <rawResourceType>Dodite</rawResourceType>
                <amount>902783</amount>
                <accesibility>0.95048224925994873</accesibility>
              </RawResource>
            </rawResources>
          </PlanetTile>
          <PlanetTile>
            <planetTileType>Rocky</planetTileType>
            <rawResources>
              <RawResource>
                <rawResourceType>Horizorium</rawResourceType>
                <amount>3411513</amount>
                <accesibility>0.8358079195022583</accesibility>
              </RawResource>
              <RawResource>
                <rawResourceType>Dodite</rawResourceType>
                <amount>365512</amount>
                <accesibility>0.74070578813552856</accesibility>
              </RawResource>
              <RawResource>
                <rawResourceType>Astodium</rawResourceType>
                <amount>79371</amount>
                <accesibility>0.95830774307250977</accesibility>
              </RawResource>
              <RawResource>
                <rawResourceType>Galiditum</rawResourceType>
                <amount>588673</amount>
                <accesibility>0.26613190770149231</accesibility>
              </RawResource>
            </rawResources>
          </PlanetTile>
          <PlanetTile>
            <planetTileType>Rocky</planetTileType>
            <rawResources>
              <RawResource>
                <rawResourceType>Horizorium</rawResourceType>
                <amount>764441</amount>
                <accesibility>0.8428114652633667</accesibility>
              </RawResource>
            </rawResources>
          </PlanetTile>
          <PlanetTile>
            <planetTileType>Rocky</planetTileType>
            <rawResources>
              <RawResource>
                <rawResourceType>Horizorium</rawResourceType>
                <amount>9253769</amount>
                <accesibility>0.65808457136154175</accesibility>
              </RawResource>
              <RawResource>
                <rawResourceType>Uronimum</rawResourceType>
                <amount>6522</amount>
                <accesibility>0.9704582691192627</accesibility>
              </RawResource>
            </rawResources>
          </PlanetTile>
          <PlanetTile>
            <planetTileType>Rocky</planetTileType>
            <rawResources>
              <RawResource>
                <rawResourceType>Horizorium</rawResourceType>
                <amount>5722302</amount>
                <accesibility>0.67472118139266968</accesibility>
              </RawResource>
              <RawResource>
                <rawResourceType>Dodite</rawResourceType>
                <amount>425221</amount>
                <accesibility>0.66297179460525513</accesibility>
              </RawResource>
            </rawResources>
          </PlanetTile>
          <PlanetTile>
            <planetTileType>Rocky</planetTileType>
            <rawResources>
              <RawResource>
                <rawResourceType>Horizorium</rawResourceType>
                <amount>3695090</amount>
                <accesibility>0.29764106869697571</accesibility>
              </RawResource>
              <RawResource>
                <rawResourceType>Galiditum</rawResourceType>
                <amount>293054</amount>
                <accesibility>0.763236403465271</accesibility>
              </RawResource>
            </rawResources>
          </PlanetTile>
          <PlanetTile>
            <planetTileType>Rocky</planetTileType>
            <rawResources>
              <RawResource>
                <rawResourceType>Horizorium</rawResourceType>
                <amount>3703609</amount>
                <accesibility>0.43223005533218384</accesibility>
              </RawResource>
              <RawResource>
                <rawResourceType>Dodite</rawResourceType>
                <amount>854641</amount>
                <accesibility>0.73825579881668091</accesibility>
              </RawResource>
              <RawResource>
                <rawResourceType>Uronimum</rawResourceType>
                <amount>6757</amount>
                <accesibility>0.81786978244781494</accesibility>
              </RawResource>
              <RawResource>
                <rawResourceType>Astodium</rawResourceType>
                <amount>19299</amount>
                <accesibility>0.12904776632785797</accesibility>
              </RawResource>
              <RawResource>
                <rawResourceType>Galiditum</rawResourceType>
                <amount>261871</amount>
                <accesibility>0.33834376931190491</accesibility>
              </RawResource>
            </rawResources>
          </PlanetTile>
          <PlanetTile>
            <planetTileType>Rocky</planetTileType>
            <rawResources>
              <RawResource>
                <rawResourceType>Horizorium</rawResourceType>
                <amount>8991041</amount>
                <accesibility>0.57286924123764038</accesibility>
              </RawResource>
            </rawResources>
          </PlanetTile>
          <PlanetTile>
            <planetTileType>Rocky</planetTileType>
            <rawResources>
              <RawResource>
                <rawResourceType>Horizorium</rawResourceType>
                <amount>5094424</amount>
                <accesibility>0.61681205034255981</accesibility>
              </RawResource>
              <RawResource>
                <rawResourceType>Dodite</rawResourceType>
                <amount>335164</amount>
                <accesibility>0.87953686714172363</accesibility>
              </RawResource>
              <RawResource>
                <rawResourceType>Doronimum</rawResourceType>
                <amount>3862</amount>
                <accesibility>0.11031140387058258</accesibility>
              </RawResource>
            </rawResources>
          </PlanetTile>
          <PlanetTile>
            <planetTileType>Rocky</planetTileType>
            <rawResources>
              <RawResource>
                <rawResourceType>Goldium</rawResourceType>
                <amount>345436</amount>
                <accesibility>0.054652102291584015</accesibility>
              </RawResource>
              <RawResource>
                <rawResourceType>Horizorium</rawResourceType>
                <amount>4911875</amount>
                <accesibility>0.01247263140976429</accesibility>
              </RawResource>
              <RawResource>
                <rawResourceType>Dodite</rawResourceType>
                <amount>29780</amount>
                <accesibility>0.68943923711776733</accesibility>
              </RawResource>
            </rawResources>
          </PlanetTile>
          <PlanetTile>
            <planetTileType>Rocky</planetTileType>
            <rawResources>
              <RawResource>
                <rawResourceType>Horizorium</rawResourceType>
                <amount>6601608</amount>
                <accesibility>0.998090386390686</accesibility>
              </RawResource>
              <RawResource>
                <rawResourceType>Dodite</rawResourceType>
                <amount>788631</amount>
                <accesibility>0.908139705657959</accesibility>
              </RawResource>
              <RawResource>
                <rawResourceType>Galiditum</rawResourceType>
                <amount>867340</amount>
                <accesibility>0.84805548191070557</accesibility>
              </RawResource>
            </rawResources>
          </PlanetTile>
          <PlanetTile>
            <planetTileType>Rocky</planetTileType>
            <rawResources>
              <RawResource>
                <rawResourceType>Horizorium</rawResourceType>
                <amount>2800559</amount>
                <accesibility>0.38200098276138306</accesibility>
              </RawResource>
              <RawResource>
                <rawResourceType>Dodite</rawResourceType>
                <amount>205437</amount>
                <accesibility>0.51194983720779419</accesibility>
              </RawResource>
              <RawResource>
                <rawResourceType>Uronimum</rawResourceType>
                <amount>9542</amount>
                <accesibility>0.57233363389968872</accesibility>
              </RawResource>
            </rawResources>
          </PlanetTile>
          <PlanetTile>
            <planetTileType>Rocky</planetTileType>
            <rawResources>
              <RawResource>
                <rawResourceType>Horizorium</rawResourceType>
                <amount>4676147</amount>
                <accesibility>0.2960527241230011</accesibility>
              </RawResource>
            </rawResources>
          </PlanetTile>
          <PlanetTile>
            <planetTileType>Rocky</planetTileType>
            <rawResources>
              <RawResource>
                <rawResourceType>Horizorium</rawResourceType>
                <amount>4004576</amount>
                <accesibility>0.54608196020126343</accesibility>
              </RawResource>
              <RawResource>
                <rawResourceType>Dodite</rawResourceType>
                <amount>662893</amount>
                <accesibility>0.764756441116333</accesibility>
              </RawResource>
              <RawResource>
                <rawResourceType>Doronimum</rawResourceType>
                <amount>7165</amount>
                <accesibility>0.12330831587314606</accesibility>
              </RawResource>
            </rawResources>
          </PlanetTile>
          <PlanetTile>
            <planetTileType>Rocky</planetTileType>
            <rawResources>
              <RawResource>
                <rawResourceType>Horizorium</rawResourceType>
                <amount>3746331</amount>
                <accesibility>0.89892792701721191</accesibility>
              </RawResource>
              <RawResource>
                <rawResourceType>Dodite</rawResourceType>
                <amount>528134</amount>
                <accesibility>0.67997962236404419</accesibility>
              </RawResource>
            </rawResources>
          </PlanetTile>
          <PlanetTile>
            <planetTileType>Rocky</planetTileType>
            <rawResources>
              <RawResource>
                <rawResourceType>Horizorium</rawResourceType>
                <amount>4873267</amount>
                <accesibility>0.53014642000198364</accesibility>
              </RawResource>
              <RawResource>
                <rawResourceType>Dodite</rawResourceType>
                <amount>691003</amount>
                <accesibility>0.6989101767539978</accesibility>
              </RawResource>
            </rawResources>
          </PlanetTile>
        </planetTiles>
        <population>0</population>
        <color>
          <r>0.5</r>
          <g>0.5</g>
          <b>0.5</b>
          <a>1</a>
        </color>
        <satelites />
        <solarType>Planet</solarType>
        <solarSubType>Rocky</solarSubType>
        <mass>4.5438781738281248E+24</mass>
        <bodyRadius>6630266.8227666374</bodyRadius>
        <lastKnownPosition>
          <x>0</x>
          <y>0</y>
        </lastKnownPosition>
        <surfaceTemp>2313.4531433657839</surfaceTemp>
        <surfacePressure>0.52415245771408081</surfacePressure>
        <luminosity>0</luminosity>
        <bondAlebo>0.76739335060119629</bondAlebo>
        <greenhouse>0.055468318980743808</greenhouse>
        <surfaceGravity>0.70278339755639307</surfaceGravity>
        <solarIndex>
          <int>184</int>
          <int>4</int>
        </solarIndex>
      </SolarBody>
      <SolarBody>
        <name>Blara 8 185 Comet 6</name>
        <orbit>
          <sma>5412705796096</sma>
          <ecc>0.55240142345428467</ecc>
          <inc>0</inc>
          <lpe>5.7652716636657715</lpe>
          <lan>0</lan>
          <mna>5.7652716636657715</mna>
          <eph>0</eph>
        </orbit>
        <planetTiles>
          <PlanetTile>
            <planetTileType>Rocky</planetTileType>
            <rawResources>
              <RawResource>
                <rawResourceType>Horizorium</rawResourceType>
                <amount>5104958</amount>
                <accesibility>0.020720960572361946</accesibility>
              </RawResource>
              <RawResource>
                <rawResourceType>Dodite</rawResourceType>
                <amount>583167</amount>
                <accesibility>0.77924740314483643</accesibility>
              </RawResource>
            </rawResources>
          </PlanetTile>
        </planetTiles>
        <population>0</population>
        <color>
          <r>0.5</r>
          <g>0.5</g>
          <b>0.5</b>
          <a>1</a>
        </color>
        <satelites>
          <SolarBody>
            <name>Blara 8 185Moon 6</name>
            <orbit>
              <sma>134059.375</sma>
              <ecc>0.0075411307625472546</ecc>
              <inc>0</inc>
              <lpe>1.1555968523025513</lpe>
              <lan>0</lan>
              <mna>1.1555968523025513</mna>
              <eph>0</eph>
            </orbit>
            <planetTiles>
              <PlanetTile>
                <planetTileType>Rocky</planetTileType>
                <rawResources>
                  <RawResource>
                    <rawResourceType>Goldium</rawResourceType>
                    <amount>48626</amount>
                    <accesibility>0.26967766880989075</accesibility>
                  </RawResource>
                  <RawResource>
                    <rawResourceType>Horizorium</rawResourceType>
                    <amount>5574823</amount>
                    <accesibility>0.59468692541122437</accesibility>
                  </RawResource>
                  <RawResource>
                    <rawResourceType>Dodite</rawResourceType>
                    <amount>456147</amount>
                    <accesibility>0.96663177013397217</accesibility>
                  </RawResource>
                </rawResources>
              </PlanetTile>
              <PlanetTile>
                <planetTileType>Rocky</planetTileType>
                <rawResources>
                  <RawResource>
                    <rawResourceType>Horizorium</rawResourceType>
                    <amount>1616061</amount>
                    <accesibility>0.25568583607673645</accesibility>
                  </RawResource>
                  <RawResource>
                    <rawResourceType>Astodium</rawResourceType>
                    <amount>65673</amount>
                    <accesibility>0.038685325533151627</accesibility>
                  </RawResource>
                </rawResources>
              </PlanetTile>
              <PlanetTile>
                <planetTileType>Volcanic</planetTileType>
                <rawResources>
                  <RawResource>
                    <rawResourceType>Horizorium</rawResourceType>
                    <amount>888342</amount>
                    <accesibility>0.66402477025985718</accesibility>
                  </RawResource>
                  <RawResource>
                    <rawResourceType>Doronimum</rawResourceType>
                    <amount>49294</amount>
                    <accesibility>0.17612697184085846</accesibility>
                  </RawResource>
                  <RawResource>
                    <rawResourceType>Astodium</rawResourceType>
                    <amount>560682</amount>
                    <accesibility>0.8464362621307373</accesibility>
                  </RawResource>
                </rawResources>
              </PlanetTile>
              <PlanetTile>
                <planetTileType>Volcanic</planetTileType>
                <rawResources>
                  <RawResource>
                    <rawResourceType>Doronimum</rawResourceType>
                    <amount>79486</amount>
                    <accesibility>0.28524127602577209</accesibility>
                  </RawResource>
                </rawResources>
              </PlanetTile>
              <PlanetTile>
                <planetTileType>Volcanic</planetTileType>
                <rawResources>
                  <RawResource>
                    <rawResourceType>Doronimum</rawResourceType>
                    <amount>5106</amount>
                    <accesibility>0.40291446447372437</accesibility>
                  </RawResource>
                  <RawResource>
                    <rawResourceType>Astodium</rawResourceType>
                    <amount>273034</amount>
                    <accesibility>0.0519869402050972</accesibility>
                  </RawResource>
                </rawResources>
              </PlanetTile>
              <PlanetTile>
                <planetTileType>Volcanic</planetTileType>
                <rawResources>
                  <RawResource>
                    <rawResourceType>Horizorium</rawResourceType>
                    <amount>6476144</amount>
                    <accesibility>0.87473762035369873</accesibility>
                  </RawResource>
                  <RawResource>
                    <rawResourceType>Doronimum</rawResourceType>
                    <amount>50913</amount>
                    <accesibility>0.49979716539382935</accesibility>
                  </RawResource>
                  <RawResource>
                    <rawResourceType>Astodium</rawResourceType>
                    <amount>152109</amount>
                    <accesibility>0.76580905914306641</accesibility>
                  </RawResource>
                </rawResources>
              </PlanetTile>
            </planetTiles>
            <population>0</population>
            <color>
              <r>1</r>
              <g>0</g>
              <b>0</b>
              <a>1</a>
            </color>
            <satelites />
            <solarType>Moon</solarType>
            <solarSubType>Volcanic</solarSubType>
            <mass>2.1252031326293947E+23</mass>
            <bodyRadius>2353018.2743801987</bodyRadius>
            <lastKnownPosition>
              <x>0</x>
              <y>0</y>
            </lastKnownPosition>
            <surfaceTemp>2088.3452683541445</surfaceTemp>
            <surfacePressure>0.31429937481880188</surfacePressure>
            <luminosity>0</luminosity>
            <bondAlebo>0.88328075408935547</bondAlebo>
            <greenhouse>0.032354892397880912</greenhouse>
            <surfaceGravity>0.26097966768568309</surfaceGravity>
            <solarIndex>
              <int>184</int>
              <int>5</int>
              <int>0</int>
            </solarIndex>
          </SolarBody>
          <SolarBody>
            <name>Blara 8 185Moon 6</name>
            <orbit>
              <sma>319954.46875</sma>
              <ecc>0.006798385176807642</ecc>
              <inc>0</inc>
              <lpe>4.0688967704772949</lpe>
              <lan>0</lan>
              <mna>4.0688967704772949</mna>
              <eph>0</eph>
            </orbit>
            <planetTiles>
              <PlanetTile>
                <planetTileType>Volcanic</planetTileType>
                <rawResources>
                  <RawResource>
                    <rawResourceType>Doronimum</rawResourceType>
                    <amount>76764</amount>
                    <accesibility>0.77255260944366455</accesibility>
                  </RawResource>
                  <RawResource>
                    <rawResourceType>Astodium</rawResourceType>
                    <amount>543315</amount>
                    <accesibility>0.27505365014076233</accesibility>
                  </RawResource>
                  <RawResource>
                    <rawResourceType>Galiditum</rawResourceType>
                    <amount>403606</amount>
                    <accesibility>0.36183097958564758</accesibility>
                  </RawResource>
                </rawResources>
              </PlanetTile>
              <PlanetTile>
                <planetTileType>Rocky</planetTileType>
                <rawResources>
                  <RawResource>
                    <rawResourceType>Horizorium</rawResourceType>
                    <amount>169751</amount>
                    <accesibility>0.0737307146191597</accesibility>
                  </RawResource>
                  <RawResource>
                    <rawResourceType>Dodite</rawResourceType>
                    <amount>929046</amount>
                    <accesibility>0.57213026285171509</accesibility>
                  </RawResource>
                </rawResources>
              </PlanetTile>
              <PlanetTile>
                <planetTileType>Rocky</planetTileType>
                <rawResources>
                  <RawResource>
                    <rawResourceType>Horizorium</rawResourceType>
                    <amount>6745401</amount>
                    <accesibility>0.86472570896148682</accesibility>
                  </RawResource>
                </rawResources>
              </PlanetTile>
              <PlanetTile>
                <planetTileType>Volcanic</planetTileType>
                <rawResources>
                  <RawResource>
                    <rawResourceType>Silvite</rawResourceType>
                    <amount>39461</amount>
                    <accesibility>0.68205279111862183</accesibility>
                  </RawResource>
                  <RawResource>
                    <rawResourceType>Dodite</rawResourceType>
                    <amount>498471</amount>
                    <accesibility>0.6683841347694397</accesibility>
                  </RawResource>
                  <RawResource>
                    <rawResourceType>Astodium</rawResourceType>
                    <amount>767962</amount>
                    <accesibility>0.50274425745010376</accesibility>
                  </RawResource>
                </rawResources>
              </PlanetTile>
              <PlanetTile>
                <planetTileType>Volcanic</planetTileType>
                <rawResources>
                  <RawResource>
                    <rawResourceType>Quananoid</rawResourceType>
                    <amount>72024</amount>
                    <accesibility>0.019912483170628548</accesibility>
                  </RawResource>
                  <RawResource>
                    <rawResourceType>Horizorium</rawResourceType>
                    <amount>5802866</amount>
                    <accesibility>0.81871283054351807</accesibility>
                  </RawResource>
                  <RawResource>
                    <rawResourceType>Uronimum</rawResourceType>
                    <amount>14780</amount>
                    <accesibility>0.651907742023468</accesibility>
                  </RawResource>
                  <RawResource>
                    <rawResourceType>Astodium</rawResourceType>
                    <amount>495889</amount>
                    <accesibility>0.875319242477417</accesibility>
                  </RawResource>
                  <RawResource>
                    <rawResourceType>Limoite</rawResourceType>
                    <amount>70858</amount>
                    <accesibility>0.82524287700653076</accesibility>
                  </RawResource>
                </rawResources>
              </PlanetTile>
              <PlanetTile>
                <planetTileType>Volcanic</planetTileType>
                <rawResources>
                  <RawResource>
                    <rawResourceType>Quananoid</rawResourceType>
                    <amount>62122</amount>
                    <accesibility>0.69726043939590454</accesibility>
                  </RawResource>
                  <RawResource>
                    <rawResourceType>Doronimum</rawResourceType>
                    <amount>82196</amount>
                    <accesibility>0.37847334146499634</accesibility>
                  </RawResource>
                  <RawResource>
                    <rawResourceType>Galiditum</rawResourceType>
                    <amount>172223</amount>
                    <accesibility>0.88277161121368408</accesibility>
                  </RawResource>
                </rawResources>
              </PlanetTile>
            </planetTiles>
            <population>0</population>
            <color>
              <r>1</r>
              <g>0</g>
              <b>0</b>
              <a>1</a>
            </color>
            <satelites />
            <solarType>Moon</solarType>
            <solarSubType>Volcanic</solarSubType>
            <mass>1.9870458602905275E+23</mass>
            <bodyRadius>2365852.6471369998</bodyRadius>
            <lastKnownPosition>
              <x>0</x>
              <y>0</y>
            </lastKnownPosition>
            <surfaceTemp>3213.1228749918591</surfaceTemp>
            <surfacePressure>0.1797979474067688</surfacePressure>
            <luminosity>0</luminosity>
            <bondAlebo>0.34227254986763</bondAlebo>
            <greenhouse>0.018176822590921324</greenhouse>
            <surfaceGravity>0.24137335852355454</surfaceGravity>
            <solarIndex>
              <int>184</int>
              <int>5</int>
              <int>1</int>
            </solarIndex>
          </SolarBody>
          <SolarBody>
            <name>Blara 8 185Moon 6</name>
            <orbit>
              <sma>888055.3125</sma>
              <ecc>0.0051220450550317764</ecc>
              <inc>0</inc>
              <lpe>1.5837786197662354</lpe>
              <lan>0</lan>
              <mna>1.5837786197662354</mna>
              <eph>0</eph>
            </orbit>
            <planetTiles>
              <PlanetTile>
                <planetTileType>Rocky</planetTileType>
                <rawResources>
                  <RawResource>
                    <rawResourceType>Horizorium</rawResourceType>
                    <amount>1381569</amount>
                    <accesibility>0.16199053823947906</accesibility>
                  </RawResource>
                  <RawResource>
                    <rawResourceType>Dodite</rawResourceType>
                    <amount>190555</amount>
                    <accesibility>0.49851638078689575</accesibility>
                  </RawResource>
                </rawResources>
              </PlanetTile>
              <PlanetTile>
                <planetTileType>Rocky</planetTileType>
                <rawResources>
                  <RawResource>
                    <rawResourceType>Horizorium</rawResourceType>
                    <amount>503524</amount>
                    <accesibility>0.21511676907539368</accesibility>
                  </RawResource>
                </rawResources>
              </PlanetTile>
              <PlanetTile>
                <planetTileType>Rocky</planetTileType>
                <rawResources>
                  <RawResource>
                    <rawResourceType>Horizorium</rawResourceType>
                    <amount>630389</amount>
                    <accesibility>0.66845124959945679</accesibility>
                  </RawResource>
                  <RawResource>
                    <rawResourceType>Dodite</rawResourceType>
                    <amount>315098</amount>
                    <accesibility>0.65882974863052368</accesibility>
                  </RawResource>
                  <RawResource>
                    <rawResourceType>Galiditum</rawResourceType>
                    <amount>653909</amount>
                    <accesibility>0.2685258686542511</accesibility>
                  </RawResource>
                </rawResources>
              </PlanetTile>
              <PlanetTile>
                <planetTileType>Desert</planetTileType>
                <rawResources>
                  <RawResource>
                    <rawResourceType>Dodite</rawResourceType>
                    <amount>337300</amount>
                    <accesibility>0.65063470602035522</accesibility>
                  </RawResource>
                  <RawResource>
                    <rawResourceType>Doronimum</rawResourceType>
                    <amount>4986</amount>
                    <accesibility>0.37320128083229065</accesibility>
                  </RawResource>
                  <RawResource>
                    <rawResourceType>Galiditum</rawResourceType>
                    <amount>282979</amount>
                    <accesibility>0.8874356746673584</accesibility>
                  </RawResource>
                </rawResources>
              </PlanetTile>
              <PlanetTile>
                <planetTileType>Rocky</planetTileType>
                <rawResources>
                  <RawResource>
                    <rawResourceType>Silvite</rawResourceType>
                    <amount>576315</amount>
                    <accesibility>0.37773603200912476</accesibility>
                  </RawResource>
                  <RawResource>
                    <rawResourceType>Horizorium</rawResourceType>
                    <amount>6486313</amount>
                    <accesibility>0.69630998373031616</accesibility>
                  </RawResource>
                  <RawResource>
                    <rawResourceType>Dodite</rawResourceType>
                    <amount>613559</amount>
                    <accesibility>0.53574877977371216</accesibility>
                  </RawResource>
                  <RawResource>
                    <rawResourceType>Galiditum</rawResourceType>
                    <amount>107765</amount>
                    <accesibility>0.220804363489151</accesibility>
                  </RawResource>
                </rawResources>
              </PlanetTile>
            </planetTiles>
            <population>0</population>
            <color>
              <r>0.5</r>
              <g>0.5</g>
              <b>0.5</b>
              <a>1</a>
            </color>
            <satelites />
            <solarType>Moon</solarType>
            <solarSubType>Rocky</solarSubType>
            <mass>2.5749584197998046E+23</mass>
            <bodyRadius>2118765.1944557843</bodyRadius>
            <lastKnownPosition>
              <x>0</x>
              <y>0</y>
            </lastKnownPosition>
            <surfaceTemp>2059.8049770780972</surfaceTemp>
            <surfacePressure>0.14766411483287811</surfacePressure>
            <luminosity>0</luminosity>
            <bondAlebo>0.88877439498901367</bondAlebo>
            <greenhouse>0.014863063812334838</greenhouse>
            <surfaceGravity>0.38999710833720819</surfaceGravity>
            <solarIndex>
              <int>184</int>
              <int>5</int>
              <int>2</int>
            </solarIndex>
          </SolarBody>
        </satelites>
        <solarType>Comet</solarType>
        <solarSubType>Rocky</solarSubType>
        <mass>100000000000000</mass>
        <bodyRadius>1556.373803479561</bodyRadius>
        <lastKnownPosition>
          <x>0</x>
          <y>0</y>
        </lastKnownPosition>
        <surfaceTemp>0</surfaceTemp>
        <surfacePressure>0</surfacePressure>
        <luminosity>0</luminosity>
        <bondAlebo>0.56961148977279663</bondAlebo>
        <greenhouse>0</greenhouse>
        <surfaceGravity>0.00028069133238665722</surfaceGravity>
        <solarIndex>
          <int>184</int>
          <int>5</int>
        </solarIndex>
      </SolarBody>
      <SolarBody>
        <name>Blara 8 185 Comet 7</name>
        <orbit>
          <sma>5923322462208</sma>
          <ecc>0.65916752815246582</ecc>
          <inc>0</inc>
          <lpe>0.098295360803604126</lpe>
          <lan>0</lan>
          <mna>0.098295360803604126</mna>
          <eph>0</eph>
        </orbit>
        <planetTiles>
          <PlanetTile>
            <planetTileType>Rocky</planetTileType>
            <rawResources>
              <RawResource>
                <rawResourceType>Horizorium</rawResourceType>
                <amount>2250678</amount>
                <accesibility>0.38662225008010864</accesibility>
              </RawResource>
              <RawResource>
                <rawResourceType>Dodite</rawResourceType>
                <amount>403371</amount>
                <accesibility>0.10482849180698395</accesibility>
              </RawResource>
              <RawResource>
                <rawResourceType>Uronimum</rawResourceType>
                <amount>897</amount>
                <accesibility>0.93858122825622559</accesibility>
              </RawResource>
            </rawResources>
          </PlanetTile>
        </planetTiles>
        <population>0</population>
        <color>
          <r>0.5</r>
          <g>0.5</g>
          <b>0.5</b>
          <a>1</a>
        </color>
        <satelites />
        <solarType>Comet</solarType>
        <solarSubType>Rocky</solarSubType>
        <mass>40000000000000</mass>
        <bodyRadius>1237.1635181409154</bodyRadius>
        <lastKnownPosition>
          <x>0</x>
          <y>0</y>
        </lastKnownPosition>
        <surfaceTemp>0</surfaceTemp>
        <surfacePressure>0</surfacePressure>
        <luminosity>0</luminosity>
        <bondAlebo>0.291882187128067</bondAlebo>
        <greenhouse>0</greenhouse>
        <surfaceGravity>0.0001776898448039353</surfaceGravity>
        <solarIndex>
          <int>184</int>
          <int>6</int>
        </solarIndex>
      </SolarBody>
    </satelites>
    <solarType>Star</solarType>
    <solarSubType>WhiteDwarf</solarSubType>
    <mass>1.3180710875988005E+30</mass>
    <bodyRadius>85710416.904662564</bodyRadius>
    <lastKnownPosition>
      <x>0</x>
      <y>0</y>
    </lastKnownPosition>
    <surfaceTemp>7877</surfaceTemp>
    <surfacePressure>1</surfacePressure>
    <luminosity>1.3436395095834816E+34</luminosity>
    <bondAlebo>0.5</bondAlebo>
    <greenhouse>0.1123595</greenhouse>
    <surfaceGravity>1219.9118363599102</surfaceGravity>
    <solarIndex>
      <int>184</int>
    </solarIndex>
  </solar>
  <stations />
  <ships />
  <nearStars>
    <Id>f78b0134-c17f-4642-87e1-92c02a9c3c1b</Id>
    <Id>f78b0134-c17f-4642-87e1-92c02a9c3c1b</Id>
    <Id>c8485459-9524-4c07-9379-e001532e6574</Id>
    <Id>2c88c0da-ef34-4686-9544-06ab0abb3f20</Id>
  </nearStars>
  <government />
  <governmentInfluence>0</governmentInfluence>
  <isCapital>false</isCapital>
  <index>184</index>
</SolarModel>