<?xml version="1.0" encoding="Windows-1252"?>
<SolarModel xmlns:xsi="http://www.w3.org/2001/XMLSchema-instance" xmlns:xsd="http://www.w3.org/2001/XMLSchema">
  <Id>76f2b892-114c-4b99-8a9a-d1ae3689ba8c</Id>
  <name>Wiunov 267</name>
  <isActive>false</isActive>
  <galacticPosition>
    <x>-69.996969347502755</x>
    <y>-1200.475943794323</y>
  </galacticPosition>
  <color>
    <r>0.5</r>
    <g>0.5</g>
    <b>0.5</b>
    <a>1</a>
  </color>
  <solar>
    <name>Wiunov 267 WhiteDwarf</name>
    <orbit>
      <sma>0</sma>
      <ecc>0</ecc>
      <inc>0</inc>
      <lpe>0</lpe>
      <lan>0</lan>
      <mna>0</mna>
      <eph>0</eph>
    </orbit>
    <population>0</population>
    <color>
      <r>0.741964042</r>
      <g>0.824710548</g>
      <b>1</b>
      <a>1</a>
    </color>
    <satelites>
      <SolarBody>
        <name>Wiunov 267 Comet 1</name>
        <orbit>
          <sma>5297818566656</sma>
          <ecc>0.80576741695404053</ecc>
          <inc>0</inc>
          <lpe>1.4113335609436035</lpe>
          <lan>0</lan>
          <mna>1.4113335609436035</mna>
          <eph>0</eph>
        </orbit>
        <planetTiles>
          <PlanetTile>
            <planetTileType>Rocky</planetTileType>
            <rawResources>
              <RawResource>
                <rawResourceType>Horizorium</rawResourceType>
                <amount>508231</amount>
                <accesibility>0.28244867920875549</accesibility>
              </RawResource>
              <RawResource>
                <rawResourceType>Dodite</rawResourceType>
                <amount>317342</amount>
                <accesibility>0.38216108083724976</accesibility>
              </RawResource>
            </rawResources>
          </PlanetTile>
        </planetTiles>
        <population>0</population>
        <color>
          <r>0.5</r>
          <g>0.5</g>
          <b>0.5</b>
          <a>1</a>
        </color>
        <satelites>
          <SolarBody>
            <name>Wiunov 267Moon 1</name>
            <orbit>
              <sma>1759419.5</sma>
              <ecc>0.019771324470639229</ecc>
              <inc>0</inc>
              <lpe>0.53712248802185059</lpe>
              <lan>0</lan>
              <mna>0.53712248802185059</mna>
              <eph>0</eph>
            </orbit>
            <planetTiles>
              <PlanetTile>
                <planetTileType>Volcanic</planetTileType>
                <rawResources>
                  <RawResource>
                    <rawResourceType>Horizorium</rawResourceType>
                    <amount>7567652</amount>
                    <accesibility>0.51344758272171021</accesibility>
                  </RawResource>
                  <RawResource>
                    <rawResourceType>Astodium</rawResourceType>
                    <amount>729254</amount>
                    <accesibility>0.54567974805831909</accesibility>
                  </RawResource>
                  <RawResource>
                    <rawResourceType>Galiditum</rawResourceType>
                    <amount>218334</amount>
                    <accesibility>0.18292869627475739</accesibility>
                  </RawResource>
                </rawResources>
              </PlanetTile>
              <PlanetTile>
                <planetTileType>Volcanic</planetTileType>
                <rawResources />
              </PlanetTile>
              <PlanetTile>
                <planetTileType>Desert</planetTileType>
                <rawResources />
              </PlanetTile>
              <PlanetTile>
                <planetTileType>Volcanic</planetTileType>
                <rawResources>
                  <RawResource>
                    <rawResourceType>Horizorium</rawResourceType>
                    <amount>5159404</amount>
                    <accesibility>0.41150873899459839</accesibility>
                  </RawResource>
                  <RawResource>
                    <rawResourceType>Doronimum</rawResourceType>
                    <amount>8604</amount>
                    <accesibility>0.36701610684394836</accesibility>
                  </RawResource>
                  <RawResource>
                    <rawResourceType>Astodium</rawResourceType>
                    <amount>409760</amount>
                    <accesibility>0.74912840127944946</accesibility>
                  </RawResource>
                  <RawResource>
                    <rawResourceType>Galiditum</rawResourceType>
                    <amount>7735</amount>
                    <accesibility>0.8484654426574707</accesibility>
                  </RawResource>
                </rawResources>
              </PlanetTile>
              <PlanetTile>
                <planetTileType>Volcanic</planetTileType>
                <rawResources>
                  <RawResource>
                    <rawResourceType>Galiditum</rawResourceType>
                    <amount>59968</amount>
                    <accesibility>0.1687939316034317</accesibility>
                  </RawResource>
                </rawResources>
              </PlanetTile>
            </planetTiles>
            <population>0</population>
            <color>
              <r>1</r>
              <g>0</g>
              <b>0</b>
              <a>1</a>
            </color>
            <satelites />
            <solarType>Moon</solarType>
            <solarSubType>Volcanic</solarSubType>
            <mass>1.341081714630127E+23</mass>
            <bodyRadius>2068703.8572158634</bodyRadius>
            <lastKnownPosition>
              <x>0</x>
              <y>0</y>
            </lastKnownPosition>
            <surfaceTemp>3169.3707979768087</surfaceTemp>
            <surfacePressure>0.83377891778945923</surfacePressure>
            <luminosity>0</luminosity>
            <bondAlebo>0.8597264289855957</bondAlebo>
            <greenhouse>0.091779731121429883</greenhouse>
            <surfaceGravity>0.21306662131193585</surfaceGravity>
            <solarIndex>
              <int>266</int>
              <int>0</int>
              <int>0</int>
            </solarIndex>
          </SolarBody>
        </satelites>
        <solarType>Comet</solarType>
        <solarSubType>Rocky</solarSubType>
        <mass>810000000000000</mass>
        <bodyRadius>3368.9092415945115</bodyRadius>
        <lastKnownPosition>
          <x>0</x>
          <y>0</y>
        </lastKnownPosition>
        <surfaceTemp>0</surfaceTemp>
        <surfacePressure>0</surfacePressure>
        <luminosity>0</luminosity>
        <bondAlebo>0.21270158886909485</bondAlebo>
        <greenhouse>0</greenhouse>
        <surfaceGravity>0.00048524740653078458</surfaceGravity>
        <solarIndex>
          <int>266</int>
          <int>0</int>
        </solarIndex>
      </SolarBody>
      <SolarBody>
        <name>Wiunov 267 Planet 2</name>
        <orbit>
          <sma>3981435731968</sma>
          <ecc>0.0063346098177134991</ecc>
          <inc>0</inc>
          <lpe>0.080236636102199554</lpe>
          <lan>0</lan>
          <mna>0.080236636102199554</mna>
          <eph>0</eph>
        </orbit>
        <planetTiles>
          <PlanetTile>
            <planetTileType>Desert</planetTileType>
            <rawResources>
              <RawResource>
                <rawResourceType>Galiditum</rawResourceType>
                <amount>30321</amount>
                <accesibility>0.69044095277786255</accesibility>
              </RawResource>
            </rawResources>
          </PlanetTile>
          <PlanetTile>
            <planetTileType>Desert</planetTileType>
            <rawResources>
              <RawResource>
                <rawResourceType>Horizorium</rawResourceType>
                <amount>9415232</amount>
                <accesibility>0.76206886768341064</accesibility>
              </RawResource>
              <RawResource>
                <rawResourceType>Galiditum</rawResourceType>
                <amount>423691</amount>
                <accesibility>0.77111876010894775</accesibility>
              </RawResource>
            </rawResources>
          </PlanetTile>
          <PlanetTile>
            <planetTileType>Desert</planetTileType>
            <rawResources>
              <RawResource>
                <rawResourceType>Horizorium</rawResourceType>
                <amount>5887090</amount>
                <accesibility>0.61736172437667847</accesibility>
              </RawResource>
              <RawResource>
                <rawResourceType>Astodium</rawResourceType>
                <amount>82232</amount>
                <accesibility>0.832755446434021</accesibility>
              </RawResource>
              <RawResource>
                <rawResourceType>Galiditum</rawResourceType>
                <amount>657490</amount>
                <accesibility>0.12597967684268951</accesibility>
              </RawResource>
            </rawResources>
          </PlanetTile>
          <PlanetTile>
            <planetTileType>Rocky</planetTileType>
            <rawResources>
              <RawResource>
                <rawResourceType>Horizorium</rawResourceType>
                <amount>3946092</amount>
                <accesibility>0.57849830389022827</accesibility>
              </RawResource>
            </rawResources>
          </PlanetTile>
          <PlanetTile>
            <planetTileType>Desert</planetTileType>
            <rawResources>
              <RawResource>
                <rawResourceType>Horizorium</rawResourceType>
                <amount>3785915</amount>
                <accesibility>0.46225696802139282</accesibility>
              </RawResource>
              <RawResource>
                <rawResourceType>Dodite</rawResourceType>
                <amount>167120</amount>
                <accesibility>0.40932303667068481</accesibility>
              </RawResource>
              <RawResource>
                <rawResourceType>Galiditum</rawResourceType>
                <amount>536311</amount>
                <accesibility>0.42215973138809204</accesibility>
              </RawResource>
            </rawResources>
          </PlanetTile>
          <PlanetTile>
            <planetTileType>Volcanic</planetTileType>
            <rawResources>
              <RawResource>
                <rawResourceType>Horizorium</rawResourceType>
                <amount>406751</amount>
                <accesibility>0.16441656649112701</accesibility>
              </RawResource>
            </rawResources>
          </PlanetTile>
          <PlanetTile>
            <planetTileType>Desert</planetTileType>
            <rawResources>
              <RawResource>
                <rawResourceType>Goldium</rawResourceType>
                <amount>91758</amount>
                <accesibility>0.40501683950424194</accesibility>
              </RawResource>
              <RawResource>
                <rawResourceType>Galiditum</rawResourceType>
                <amount>147007</amount>
                <accesibility>0.72216314077377319</accesibility>
              </RawResource>
            </rawResources>
          </PlanetTile>
        </planetTiles>
        <population>0</population>
        <color>
          <r>1</r>
          <g>0.921568632</g>
          <b>0.0156862754</b>
          <a>1</a>
        </color>
        <satelites />
        <solarType>Planet</solarType>
        <solarSubType>Desert</solarSubType>
        <mass>3.2918586730957032E+23</mass>
        <bodyRadius>2685873.8908482669</bodyRadius>
        <lastKnownPosition>
          <x>0</x>
          <y>0</y>
        </lastKnownPosition>
        <surfaceTemp>5580.3634089424431</surfaceTemp>
        <surfacePressure>1.5613971948623657</surfacePressure>
        <luminosity>0</luminosity>
        <bondAlebo>0.2653363049030304</bondAlebo>
        <greenhouse>0.18747548628759583</greenhouse>
        <surfaceGravity>0.3102607037525234</surfaceGravity>
        <solarIndex>
          <int>266</int>
          <int>1</int>
        </solarIndex>
      </SolarBody>
    </satelites>
    <solarType>Star</solarType>
    <solarSubType>WhiteDwarf</solarSubType>
    <mass>8.21316868841648E+29</mass>
    <bodyRadius>46618811.019897416</bodyRadius>
    <lastKnownPosition>
      <x>0</x>
      <y>0</y>
    </lastKnownPosition>
    <surfaceTemp>12467</surfaceTemp>
    <surfacePressure>1</surfacePressure>
    <luminosity>5.5535033542049919E+34</luminosity>
    <bondAlebo>0.5</bondAlebo>
    <greenhouse>0.1123595</greenhouse>
    <surfaceGravity>2569.4796556993683</surfaceGravity>
    <solarIndex>
      <int>266</int>
    </solarIndex>
  </solar>
  <stations />
  <ships />
  <nearStars>
    <Id>fd9b6abf-a6db-4d60-b972-aaddf7a8e4fd</Id>
    <Id>fd9b6abf-a6db-4d60-b972-aaddf7a8e4fd</Id>
    <Id>b37cf454-dfa4-4a9a-a85c-6c58ec5abee5</Id>
    <Id>69e63008-f334-4cb2-9f2a-747af28789c8</Id>
  </nearStars>
  <government />
  <governmentInfluence>0</governmentInfluence>
  <isCapital>false</isCapital>
  <index>266</index>
</SolarModel>