<?xml version="1.0" encoding="Windows-1252"?>
<SolarModel xmlns:xsi="http://www.w3.org/2001/XMLSchema-instance" xmlns:xsd="http://www.w3.org/2001/XMLSchema">
  <Id>886148c9-2306-4ae4-b2df-694ff2352e62</Id>
  <name>Swinda 69 32</name>
  <isActive>false</isActive>
  <galacticPosition>
    <x>686.5250183211308</x>
    <y>-734.66545148813225</y>
  </galacticPosition>
  <color>
    <r>0</r>
    <g>0</g>
    <b>0</b>
    <a>0</a>
  </color>
  <solar>
    <name>Swinda 69 32 MainSequence</name>
    <orbit>
      <sma>0</sma>
      <ecc>0</ecc>
      <inc>0</inc>
      <lpe>0</lpe>
      <lan>0</lan>
      <mna>0</mna>
      <eph>0</eph>
    </orbit>
    <groundStructures />
    <spaceStructures />
    <color>
      <r>0.961472</r>
      <g>0.9552327</g>
      <b>1</b>
      <a>1</a>
    </color>
    <satelites>
      <SolarBody>
        <name>Swinda 69 32 DwarfPlanet 1</name>
        <orbit>
          <sma>8414376448</sma>
          <ecc>0.10860149562358856</ecc>
          <inc>0</inc>
          <lpe>1.8108826875686646</lpe>
          <lan>0</lan>
          <mna>1.8108826875686646</mna>
          <eph>0</eph>
        </orbit>
        <groundStructures />
        <spaceStructures />
        <color>
          <r>1</r>
          <g>1</g>
          <b>1</b>
          <a>1</a>
        </color>
        <satelites />
        <totalPopulation>0</totalPopulation>
        <solarType>DwarfPlanet</solarType>
        <solarSubType>Ice</solarSubType>
        <mass>3E+22</mass>
        <bodyRadius>1212.4149997313116</bodyRadius>
        <lastKnownPosition>
          <x>0</x>
          <y>0</y>
        </lastKnownPosition>
        <surfaceTemp>102.1349227939002</surfaceTemp>
        <surfacePressure>0.90504688024520874</surfacePressure>
        <luminosity>0</luminosity>
        <bondAlebo>0.03055906668305397</bondAlebo>
        <greenhouse>0.10051045896668832</greenhouse>
        <surfaceGravity>0.13876357489070362</surfaceGravity>
        <planetTiles>
          <PlanetTile>
            <planetTileType>Ice</planetTileType>
            <count>3</count>
          </PlanetTile>
        </planetTiles>
        <rawResources />
        <population>0</population>
        <solarIndex>
          <int>31</int>
          <int>0</int>
        </solarIndex>
      </SolarBody>
      <SolarBody>
        <name>Swinda 69 32 Comet 2</name>
        <orbit>
          <sma>15260307456</sma>
          <ecc>0.79879486560821533</ecc>
          <inc>0</inc>
          <lpe>0.76572906970977783</lpe>
          <lan>0</lan>
          <mna>0.76572906970977783</mna>
          <eph>0</eph>
        </orbit>
        <groundStructures />
        <spaceStructures />
        <color>
          <r>0.5</r>
          <g>0.5</g>
          <b>0.5</b>
          <a>1</a>
        </color>
        <satelites />
        <totalPopulation>0</totalPopulation>
        <solarType>Comet</solarType>
        <solarSubType>Rocky</solarSubType>
        <mass>560000000000000</mass>
        <bodyRadius>3.1697127342206</bodyRadius>
        <lastKnownPosition>
          <x>0</x>
          <y>0</y>
        </lastKnownPosition>
        <surfaceTemp>0</surfaceTemp>
        <surfacePressure>0</surfacePressure>
        <luminosity>0</luminosity>
        <bondAlebo>0.89439451694488525</bondAlebo>
        <greenhouse>0</greenhouse>
        <surfaceGravity>0.00037897018549463019</surfaceGravity>
        <planetTiles>
          <PlanetTile>
            <planetTileType>Rocky</planetTileType>
            <count>1</count>
          </PlanetTile>
        </planetTiles>
        <rawResources>
          <RawResource>
            <name>Armoroid</name>
            <id>1</id>
            <amount>953416</amount>
            <accessibility>0.55643802881240845</accessibility>
          </RawResource>
        </rawResources>
        <population>0</population>
        <solarIndex>
          <int>31</int>
          <int>1</int>
        </solarIndex>
      </SolarBody>
      <SolarBody>
        <name>Swinda 69 32 Comet 3</name>
        <orbit>
          <sma>12157034496</sma>
          <ecc>0.537213146686554</ecc>
          <inc>0</inc>
          <lpe>2.1845629215240479</lpe>
          <lan>0</lan>
          <mna>2.1845629215240479</mna>
          <eph>0</eph>
        </orbit>
        <groundStructures />
        <spaceStructures />
        <color>
          <r>0.5</r>
          <g>0.5</g>
          <b>0.5</b>
          <a>1</a>
        </color>
        <satelites />
        <totalPopulation>0</totalPopulation>
        <solarType>Comet</solarType>
        <solarSubType>Rocky</solarSubType>
        <mass>750000000000000</mass>
        <bodyRadius>3.3157025289896302</bodyRadius>
        <lastKnownPosition>
          <x>0</x>
          <y>0</y>
        </lastKnownPosition>
        <surfaceTemp>0</surfaceTemp>
        <surfacePressure>0</surfacePressure>
        <luminosity>0</luminosity>
        <bondAlebo>0.84314644336700439</bondAlebo>
        <greenhouse>0</greenhouse>
        <surfaceGravity>0.00046383868722814109</surfaceGravity>
        <planetTiles>
          <PlanetTile>
            <planetTileType>Rocky</planetTileType>
            <count>1</count>
          </PlanetTile>
        </planetTiles>
        <rawResources>
          <RawResource>
            <name>Armoroid</name>
            <id>1</id>
            <amount>953416</amount>
            <accessibility>0.066107273101806641</accessibility>
          </RawResource>
        </rawResources>
        <population>0</population>
        <solarIndex>
          <int>31</int>
          <int>2</int>
        </solarIndex>
      </SolarBody>
      <SolarBody>
        <name>Swinda 69 32 Comet 4</name>
        <orbit>
          <sma>12197387264</sma>
          <ecc>0.67714500427246094</ecc>
          <inc>0</inc>
          <lpe>3.5639958381652832</lpe>
          <lan>0</lan>
          <mna>3.5639958381652832</mna>
          <eph>0</eph>
        </orbit>
        <groundStructures />
        <spaceStructures />
        <color>
          <r>0.5</r>
          <g>0.5</g>
          <b>0.5</b>
          <a>1</a>
        </color>
        <satelites>
          <SolarBody>
            <name>Swinda 69 32Moon 4</name>
            <orbit>
              <sma>1017.9447631835938</sma>
              <ecc>0.002935316413640976</ecc>
              <inc>0</inc>
              <lpe>0.91212612390518188</lpe>
              <lan>0</lan>
              <mna>0.91212612390518188</mna>
              <eph>0</eph>
            </orbit>
            <groundStructures />
            <spaceStructures />
            <color>
              <r>0.5</r>
              <g>0.5</g>
              <b>0.5</b>
              <a>1</a>
            </color>
            <satelites />
            <totalPopulation>0</totalPopulation>
            <solarType>Moon</solarType>
            <solarSubType>Rocky</solarSubType>
            <mass>2.8493253707885741E+23</mass>
            <bodyRadius>2311.6056430983522</bodyRadius>
            <lastKnownPosition>
              <x>0</x>
              <y>0</y>
            </lastKnownPosition>
            <surfaceTemp>82.099014680400714</surfaceTemp>
            <surfacePressure>0.24727262556552887</surfacePressure>
            <luminosity>0</luminosity>
            <bondAlebo>0.12452556192874908</bondAlebo>
            <greenhouse>0.025227357968458923</greenhouse>
            <surfaceGravity>0.36255289694412673</surfaceGravity>
            <planetTiles>
              <PlanetTile>
                <planetTileType>Rocky</planetTileType>
                <count>6</count>
              </PlanetTile>
            </planetTiles>
            <rawResources>
              <RawResource>
                <name>Armoroid</name>
                <id>1</id>
                <amount>953416</amount>
                <accessibility>0.16939008235931396</accessibility>
              </RawResource>
              <RawResource>
                <name>Coppode</name>
                <id>2</id>
                <amount>25411</amount>
                <accessibility>0.72604787349700928</accessibility>
              </RawResource>
              <RawResource>
                <name>Warium</name>
                <id>4</id>
                <amount>38199</amount>
                <accessibility>0.69977343082427979</accessibility>
              </RawResource>
              <RawResource>
                <name>Fuelodite</name>
                <id>3</id>
                <amount>4961</amount>
                <accessibility>0.8792043924331665</accessibility>
              </RawResource>
            </rawResources>
            <population>0</population>
            <solarIndex>
              <int>31</int>
              <int>3</int>
              <int>0</int>
            </solarIndex>
          </SolarBody>
          <SolarBody>
            <name>Swinda 69 32Moon 4</name>
            <orbit>
              <sma>1169.9981689453125</sma>
              <ecc>0.016843389719724655</ecc>
              <inc>0</inc>
              <lpe>5.1192588806152344</lpe>
              <lan>0</lan>
              <mna>5.1192588806152344</mna>
              <eph>0</eph>
            </orbit>
            <groundStructures />
            <spaceStructures />
            <color>
              <r>0.5</r>
              <g>0.5</g>
              <b>0.5</b>
              <a>1</a>
            </color>
            <satelites />
            <totalPopulation>0</totalPopulation>
            <solarType>Moon</solarType>
            <solarSubType>Rocky</solarSubType>
            <mass>3.4687061309814454E+23</mass>
            <bodyRadius>2721.3367048913315</bodyRadius>
            <lastKnownPosition>
              <x>0</x>
              <y>0</y>
            </lastKnownPosition>
            <surfaceTemp>81.840044024025957</surfaceTemp>
            <surfacePressure>0.950812816619873</surfacePressure>
            <luminosity>0</luminosity>
            <bondAlebo>0.16200162470340729</bondAlebo>
            <greenhouse>0.10619059976513104</greenhouse>
            <surfaceGravity>0.31846358205278669</surfaceGravity>
            <planetTiles>
              <PlanetTile>
                <planetTileType>Rocky</planetTileType>
                <count>7</count>
              </PlanetTile>
            </planetTiles>
            <rawResources>
              <RawResource>
                <name>Armoroid</name>
                <id>1</id>
                <amount>953416</amount>
                <accessibility>0.73115479946136475</accessibility>
              </RawResource>
              <RawResource>
                <name>Coppode</name>
                <id>2</id>
                <amount>25411</amount>
                <accessibility>0.47886365652084351</accessibility>
              </RawResource>
              <RawResource>
                <name>Warium</name>
                <id>4</id>
                <amount>38199</amount>
                <accessibility>0.88132143020629883</accessibility>
              </RawResource>
              <RawResource>
                <name>Fuelodite</name>
                <id>3</id>
                <amount>4961</amount>
                <accessibility>0.75174796581268311</accessibility>
              </RawResource>
            </rawResources>
            <population>0</population>
            <solarIndex>
              <int>31</int>
              <int>3</int>
              <int>1</int>
            </solarIndex>
          </SolarBody>
          <SolarBody>
            <name>Swinda 69 32Moon 4</name>
            <orbit>
              <sma>135.8099365234375</sma>
              <ecc>0.0078861704096198082</ecc>
              <inc>0</inc>
              <lpe>4.25984001159668</lpe>
              <lan>0</lan>
              <mna>4.25984001159668</mna>
              <eph>0</eph>
            </orbit>
            <groundStructures />
            <spaceStructures />
            <color>
              <r>1</r>
              <g>1</g>
              <b>1</b>
              <a>1</a>
            </color>
            <satelites />
            <totalPopulation>0</totalPopulation>
            <solarType>Moon</solarType>
            <solarSubType>Ice</solarSubType>
            <mass>2.442592144012451E+22</mass>
            <bodyRadius>1051.6976545627147</bodyRadius>
            <lastKnownPosition>
              <x>0</x>
              <y>0</y>
            </lastKnownPosition>
            <surfaceTemp>71.075089799859711</surfaceTemp>
            <surfacePressure>0.56155651807785034</surfacePressure>
            <luminosity>0</luminosity>
            <bondAlebo>0.51476269960403442</bondAlebo>
            <greenhouse>0.059715045986264335</greenhouse>
            <surfaceGravity>0.15015021961169392</surfaceGravity>
            <planetTiles>
              <PlanetTile>
                <planetTileType>Rocky</planetTileType>
                <count>1</count>
              </PlanetTile>
              <PlanetTile>
                <planetTileType>Ocean</planetTileType>
                <count>1</count>
              </PlanetTile>
              <PlanetTile>
                <planetTileType>Ice</planetTileType>
                <count>1</count>
              </PlanetTile>
            </planetTiles>
            <rawResources>
              <RawResource>
                <name>Armoroid</name>
                <id>1</id>
                <amount>953416</amount>
                <accessibility>0.47947198152542114</accessibility>
              </RawResource>
              <RawResource>
                <name>Fuelodite</name>
                <id>3</id>
                <amount>858551</amount>
                <accessibility>0.6142461895942688</accessibility>
              </RawResource>
            </rawResources>
            <population>0</population>
            <solarIndex>
              <int>31</int>
              <int>3</int>
              <int>2</int>
            </solarIndex>
          </SolarBody>
        </satelites>
        <totalPopulation>0</totalPopulation>
        <solarType>Comet</solarType>
        <solarSubType>Rocky</solarSubType>
        <mass>890000000000000</mass>
        <bodyRadius>3.5047144166819124</bodyRadius>
        <lastKnownPosition>
          <x>0</x>
          <y>0</y>
        </lastKnownPosition>
        <surfaceTemp>0</surfaceTemp>
        <surfacePressure>0</surfacePressure>
        <luminosity>0</luminosity>
        <bondAlebo>0.093220360577106476</bondAlebo>
        <greenhouse>0</greenhouse>
        <surfaceGravity>0.00049265348927439521</surfaceGravity>
        <planetTiles>
          <PlanetTile>
            <planetTileType>Rocky</planetTileType>
            <count>1</count>
          </PlanetTile>
        </planetTiles>
        <rawResources>
          <RawResource>
            <name>Armoroid</name>
            <id>1</id>
            <amount>953416</amount>
            <accessibility>0.031339645385742188</accessibility>
          </RawResource>
        </rawResources>
        <population>0</population>
        <solarIndex>
          <int>31</int>
          <int>3</int>
        </solarIndex>
      </SolarBody>
      <SolarBody>
        <name>Swinda 69 32 Comet 5</name>
        <orbit>
          <sma>11711450112</sma>
          <ecc>0.98758053779602051</ecc>
          <inc>0</inc>
          <lpe>2.3559155464172363</lpe>
          <lan>0</lan>
          <mna>2.3559155464172363</mna>
          <eph>0</eph>
        </orbit>
        <groundStructures />
        <spaceStructures />
        <color>
          <r>0.5</r>
          <g>0.5</g>
          <b>0.5</b>
          <a>1</a>
        </color>
        <satelites />
        <totalPopulation>0</totalPopulation>
        <solarType>Comet</solarType>
        <solarSubType>Rocky</solarSubType>
        <mass>580000000000000</mass>
        <bodyRadius>2.9130960482426671</bodyRadius>
        <lastKnownPosition>
          <x>0</x>
          <y>0</y>
        </lastKnownPosition>
        <surfaceTemp>0</surfaceTemp>
        <surfacePressure>0</surfacePressure>
        <luminosity>0</luminosity>
        <bondAlebo>0.799345850944519</bondAlebo>
        <greenhouse>0</greenhouse>
        <surfaceGravity>0.000464702717281969</surfaceGravity>
        <planetTiles>
          <PlanetTile>
            <planetTileType>Rocky</planetTileType>
            <count>1</count>
          </PlanetTile>
        </planetTiles>
        <rawResources>
          <RawResource>
            <name>Armoroid</name>
            <id>1</id>
            <amount>953416</amount>
            <accessibility>0.85728240013122559</accessibility>
          </RawResource>
        </rawResources>
        <population>0</population>
        <solarIndex>
          <int>31</int>
          <int>4</int>
        </solarIndex>
      </SolarBody>
      <SolarBody>
        <name>Swinda 69 32 Planet 6</name>
        <orbit>
          <sma>27068418048</sma>
          <ecc>0.0051268916577100754</ecc>
          <inc>0</inc>
          <lpe>5.8820719718933105</lpe>
          <lan>0</lan>
          <mna>5.8820719718933105</mna>
          <eph>0</eph>
        </orbit>
        <groundStructures />
        <spaceStructures />
        <color>
          <r>1</r>
          <g>1</g>
          <b>1</b>
          <a>1</a>
        </color>
        <satelites />
        <totalPopulation>0</totalPopulation>
        <solarType>Planet</solarType>
        <solarSubType>Ice</solarSubType>
        <mass>9.7723815917968752E+24</mass>
        <bodyRadius>7007.52424021034</bodyRadius>
        <lastKnownPosition>
          <x>0</x>
          <y>0</y>
        </lastKnownPosition>
        <surfaceTemp>43.020217117665439</surfaceTemp>
        <surfacePressure>0.55102807283401489</surfacePressure>
        <luminosity>0</luminosity>
        <bondAlebo>0.67910152673721313</bondAlebo>
        <greenhouse>0.058515797096114819</greenhouse>
        <surfaceGravity>1.3530941799707215</surfaceGravity>
        <planetTiles>
          <PlanetTile>
            <planetTileType>Ocean</planetTileType>
            <count>2</count>
          </PlanetTile>
          <PlanetTile>
            <planetTileType>Ice</planetTileType>
            <count>15</count>
          </PlanetTile>
        </planetTiles>
        <rawResources>
          <RawResource>
            <name>Warium</name>
            <id>4</id>
            <amount>20793</amount>
            <accessibility>0.62723708152771</accessibility>
          </RawResource>
          <RawResource>
            <name>Fuelodite</name>
            <id>3</id>
            <amount>907432</amount>
            <accessibility>0.98602628707885742</accessibility>
          </RawResource>
          <RawResource>
            <name>Armoroid</name>
            <id>1</id>
            <amount>38199</amount>
            <accessibility>0.035635828971862793</accessibility>
          </RawResource>
          <RawResource>
            <name>Glassitum</name>
            <id>6</id>
            <amount>505972</amount>
            <accessibility>0.91860461235046387</accessibility>
          </RawResource>
        </rawResources>
        <population>0</population>
        <solarIndex>
          <int>31</int>
          <int>5</int>
        </solarIndex>
      </SolarBody>
      <SolarBody>
        <name>Swinda 69 32 DwarfPlanet 7</name>
        <orbit>
          <sma>29320531968</sma>
          <ecc>0.3458937406539917</ecc>
          <inc>0</inc>
          <lpe>4.622136116027832</lpe>
          <lan>0</lan>
          <mna>4.622136116027832</mna>
          <eph>0</eph>
        </orbit>
        <groundStructures />
        <spaceStructures />
        <color>
          <r>0.5</r>
          <g>0.5</g>
          <b>0.5</b>
          <a>1</a>
        </color>
        <satelites />
        <totalPopulation>0</totalPopulation>
        <solarType>DwarfPlanet</solarType>
        <solarSubType>Rocky</solarSubType>
        <mass>3E+21</mass>
        <bodyRadius>500.27914582270932</bodyRadius>
        <lastKnownPosition>
          <x>0</x>
          <y>0</y>
        </lastKnownPosition>
        <surfaceTemp>45.70704494127623</surfaceTemp>
        <surfacePressure>0.97263866662979126</surfacePressure>
        <luminosity>0</luminosity>
        <bondAlebo>0.52937597036361694</bondAlebo>
        <greenhouse>0.10891972750288371</greenhouse>
        <surfaceGravity>0.081499188033257383</surfaceGravity>
        <planetTiles>
          <PlanetTile>
            <planetTileType>Rocky</planetTileType>
            <count>2</count>
          </PlanetTile>
        </planetTiles>
        <rawResources>
          <RawResource>
            <name>Armoroid</name>
            <id>1</id>
            <amount>953416</amount>
            <accessibility>0.43699449300765991</accessibility>
          </RawResource>
        </rawResources>
        <population>0</population>
        <solarIndex>
          <int>31</int>
          <int>6</int>
        </solarIndex>
      </SolarBody>
      <SolarBody>
        <name>Swinda 69 32 DwarfPlanet 8</name>
        <orbit>
          <sma>3265952256</sma>
          <ecc>0.39825177192687988</ecc>
          <inc>0</inc>
          <lpe>0.43274962902069092</lpe>
          <lan>0</lan>
          <mna>0.43274962902069092</mna>
          <eph>0</eph>
        </orbit>
        <groundStructures />
        <spaceStructures />
        <color>
          <r>1</r>
          <g>0</g>
          <b>0</b>
          <a>1</a>
        </color>
        <satelites />
        <totalPopulation>0</totalPopulation>
        <solarType>DwarfPlanet</solarType>
        <solarSubType>Volcanic</solarSubType>
        <mass>1.6E+22</mass>
        <bodyRadius>937.76416906748716</bodyRadius>
        <lastKnownPosition>
          <x>0</x>
          <y>0</y>
        </lastKnownPosition>
        <surfaceTemp>159.81888255368514</surfaceTemp>
        <surfacePressure>0.057324778288602829</surfacePressure>
        <luminosity>0</luminosity>
        <bondAlebo>0.091734059154987335</bondAlebo>
        <greenhouse>0.0056988814797272695</greenhouse>
        <surfaceGravity>0.12370565113705166</surfaceGravity>
        <planetTiles>
          <PlanetTile>
            <planetTileType>Volcanic</planetTileType>
            <count>2</count>
          </PlanetTile>
          <PlanetTile>
            <planetTileType>Rocky</planetTileType>
            <count>1</count>
          </PlanetTile>
        </planetTiles>
        <rawResources>
          <RawResource>
            <name>Warium</name>
            <id>4</id>
            <amount>20793</amount>
            <accessibility>0.89215385913848877</accessibility>
          </RawResource>
          <RawResource>
            <name>Fuelodite</name>
            <id>3</id>
            <amount>90743</amount>
            <accessibility>0.59304243326187134</accessibility>
          </RawResource>
          <RawResource>
            <name>Coppode</name>
            <id>2</id>
            <amount>83867</amount>
            <accessibility>0.21770787239074707</accessibility>
          </RawResource>
        </rawResources>
        <population>0</population>
        <solarIndex>
          <int>31</int>
          <int>7</int>
        </solarIndex>
      </SolarBody>
      <SolarBody>
        <name>Swinda 69 32 Comet 9</name>
        <orbit>
          <sma>29690798080</sma>
          <ecc>0.70570743083953857</ecc>
          <inc>0</inc>
          <lpe>5.3682870864868164</lpe>
          <lan>0</lan>
          <mna>5.3682870864868164</mna>
          <eph>0</eph>
        </orbit>
        <groundStructures />
        <spaceStructures />
        <color>
          <r>0.5</r>
          <g>0.5</g>
          <b>0.5</b>
          <a>1</a>
        </color>
        <satelites />
        <totalPopulation>0</totalPopulation>
        <solarType>Comet</solarType>
        <solarSubType>Rocky</solarSubType>
        <mass>770000000000000</mass>
        <bodyRadius>3.0769103162003333</bodyRadius>
        <lastKnownPosition>
          <x>0</x>
          <y>0</y>
        </lastKnownPosition>
        <surfaceTemp>0</surfaceTemp>
        <surfacePressure>0</surfacePressure>
        <luminosity>0</luminosity>
        <bondAlebo>0.52601486444473267</bondAlebo>
        <greenhouse>0</greenhouse>
        <surfaceGravity>0.0005529907615772616</surfaceGravity>
        <planetTiles>
          <PlanetTile>
            <planetTileType>Rocky</planetTileType>
            <count>1</count>
          </PlanetTile>
        </planetTiles>
        <rawResources>
          <RawResource>
            <name>Armoroid</name>
            <id>1</id>
            <amount>953416</amount>
            <accessibility>0.24695718288421631</accessibility>
          </RawResource>
        </rawResources>
        <population>0</population>
        <solarIndex>
          <int>31</int>
          <int>8</int>
        </solarIndex>
      </SolarBody>
      <SolarBody>
        <name>Swinda 69 32 Planet 10</name>
        <orbit>
          <sma>26257342464</sma>
          <ecc>0.0026876956690102816</ecc>
          <inc>0</inc>
          <lpe>4.9082789421081543</lpe>
          <lan>0</lan>
          <mna>4.9082789421081543</mna>
          <eph>0</eph>
        </orbit>
        <groundStructures />
        <spaceStructures />
        <color>
          <r>0.5</r>
          <g>0.5</g>
          <b>0.5</b>
          <a>1</a>
        </color>
        <satelites>
          <SolarBody>
            <name>Swinda 69 32Moon 10</name>
            <orbit>
              <sma>7350504</sma>
              <ecc>0.00061051844386383891</ecc>
              <inc>0</inc>
              <lpe>5.4291167259216309</lpe>
              <lan>0</lan>
              <mna>5.4291167259216309</mna>
              <eph>0</eph>
            </orbit>
            <groundStructures />
            <spaceStructures />
            <color>
              <r>0.5</r>
              <g>0.5</g>
              <b>0.5</b>
              <a>1</a>
            </color>
            <satelites />
            <totalPopulation>0</totalPopulation>
            <solarType>Moon</solarType>
            <solarSubType>Rocky</solarSubType>
            <mass>3.4269935607910156E+23</mass>
            <bodyRadius>2285.4862231296688</bodyRadius>
            <lastKnownPosition>
              <x>0</x>
              <y>0</y>
            </lastKnownPosition>
            <surfaceTemp>47.284660967328662</surfaceTemp>
            <surfacePressure>0.36312779784202576</surfacePressure>
            <luminosity>0</luminosity>
            <bondAlebo>0.5554841160774231</bondAlebo>
            <greenhouse>0.037624928073034976</greenhouse>
            <surfaceGravity>0.44608015143347068</surfaceGravity>
            <planetTiles>
              <PlanetTile>
                <planetTileType>Rocky</planetTileType>
                <count>4</count>
              </PlanetTile>
              <PlanetTile>
                <planetTileType>Ice</planetTileType>
                <count>2</count>
              </PlanetTile>
            </planetTiles>
            <rawResources>
              <RawResource>
                <name>Armoroid</name>
                <id>1</id>
                <amount>953416</amount>
                <accessibility>0.728736400604248</accessibility>
              </RawResource>
              <RawResource>
                <name>Coppode</name>
                <id>2</id>
                <amount>25411</amount>
                <accessibility>0.28069764375686646</accessibility>
              </RawResource>
              <RawResource>
                <name>Warium</name>
                <id>4</id>
                <amount>38199</amount>
                <accessibility>0.623460590839386</accessibility>
              </RawResource>
              <RawResource>
                <name>Glassitum</name>
                <id>6</id>
                <amount>496178</amount>
                <accessibility>0.097519755363464355</accessibility>
              </RawResource>
            </rawResources>
            <population>0</population>
            <solarIndex>
              <int>31</int>
              <int>9</int>
              <int>0</int>
            </solarIndex>
          </SolarBody>
          <SolarBody>
            <name>Swinda 69 32Moon 10</name>
            <orbit>
              <sma>854372.625</sma>
              <ecc>0.0050176940858364105</ecc>
              <inc>0</inc>
              <lpe>4.29591703414917</lpe>
              <lan>0</lan>
              <mna>4.29591703414917</mna>
              <eph>0</eph>
            </orbit>
            <groundStructures />
            <spaceStructures />
            <color>
              <r>0.5</r>
              <g>0.5</g>
              <b>0.5</b>
              <a>1</a>
            </color>
            <satelites />
            <totalPopulation>0</totalPopulation>
            <solarType>Moon</solarType>
            <solarSubType>Rocky</solarSubType>
            <mass>3.8839427947998047E+23</mass>
            <bodyRadius>2738.9183431611696</bodyRadius>
            <lastKnownPosition>
              <x>0</x>
              <y>0</y>
            </lastKnownPosition>
            <surfaceTemp>32.3433964925379</surfaceTemp>
            <surfacePressure>0.77088010311126709</surfacePressure>
            <luminosity>0</luminosity>
            <bondAlebo>0.90446805953979492</bondAlebo>
            <greenhouse>0.08419016129390651</greenhouse>
            <surfaceGravity>0.35202335852718458</surfaceGravity>
            <planetTiles>
              <PlanetTile>
                <planetTileType>Rocky</planetTileType>
                <count>7</count>
              </PlanetTile>
            </planetTiles>
            <rawResources>
              <RawResource>
                <name>Armoroid</name>
                <id>1</id>
                <amount>953416</amount>
                <accessibility>0.30281323194503784</accessibility>
              </RawResource>
              <RawResource>
                <name>Coppode</name>
                <id>2</id>
                <amount>25411</amount>
                <accessibility>0.71694684028625488</accessibility>
              </RawResource>
              <RawResource>
                <name>Warium</name>
                <id>4</id>
                <amount>38199</amount>
                <accessibility>0.634857177734375</accessibility>
              </RawResource>
              <RawResource>
                <name>Fuelodite</name>
                <id>3</id>
                <amount>4961</amount>
                <accessibility>0.454495370388031</accessibility>
              </RawResource>
            </rawResources>
            <population>0</population>
            <solarIndex>
              <int>31</int>
              <int>9</int>
              <int>1</int>
            </solarIndex>
          </SolarBody>
          <SolarBody>
            <name>Swinda 69 32Moon 10</name>
            <orbit>
              <sma>11903392</sma>
              <ecc>0.00805907603353262</ecc>
              <inc>0</inc>
              <lpe>2.1711351871490479</lpe>
              <lan>0</lan>
              <mna>2.1711351871490479</mna>
              <eph>0</eph>
            </orbit>
            <groundStructures />
            <spaceStructures />
            <color>
              <r>0.5</r>
              <g>0.5</g>
              <b>0.5</b>
              <a>1</a>
            </color>
            <satelites />
            <totalPopulation>0</totalPopulation>
            <solarType>Moon</solarType>
            <solarSubType>Rocky</solarSubType>
            <mass>2.3306713104248048E+23</mass>
            <bodyRadius>2346.8392952271079</bodyRadius>
            <lastKnownPosition>
              <x>0</x>
              <y>0</y>
            </lastKnownPosition>
            <surfaceTemp>40.466102219280963</surfaceTemp>
            <surfacePressure>0.19359652698040009</surfacePressure>
            <luminosity>0</luminosity>
            <bondAlebo>0.75980043411254883</bondAlebo>
            <greenhouse>0.019608486647964874</greenhouse>
            <surfaceGravity>0.28772073031172291</surfaceGravity>
            <planetTiles>
              <PlanetTile>
                <planetTileType>Rocky</planetTileType>
                <count>5</count>
              </PlanetTile>
              <PlanetTile>
                <planetTileType>Desert</planetTileType>
                <count>1</count>
              </PlanetTile>
            </planetTiles>
            <rawResources>
              <RawResource>
                <name>Armoroid</name>
                <id>1</id>
                <amount>953416</amount>
                <accessibility>0.61708694696426392</accessibility>
              </RawResource>
              <RawResource>
                <name>Glassitum</name>
                <id>6</id>
                <amount>548445</amount>
                <accessibility>0.84924471378326416</accessibility>
              </RawResource>
              <RawResource>
                <name>Coppode</name>
                <id>2</id>
                <amount>25411</amount>
                <accessibility>0.90678918361663818</accessibility>
              </RawResource>
              <RawResource>
                <name>Warium</name>
                <id>4</id>
                <amount>38199</amount>
                <accessibility>0.074090123176574707</accessibility>
              </RawResource>
              <RawResource>
                <name>Fuelodite</name>
                <id>3</id>
                <amount>4961</amount>
                <accessibility>0.075186014175415039</accessibility>
              </RawResource>
            </rawResources>
            <population>0</population>
            <solarIndex>
              <int>31</int>
              <int>9</int>
              <int>2</int>
            </solarIndex>
          </SolarBody>
        </satelites>
        <totalPopulation>0</totalPopulation>
        <solarType>Planet</solarType>
        <solarSubType>Rocky</solarSubType>
        <mass>5.7092952728271477E+24</mass>
        <bodyRadius>5856.1346051559149</bodyRadius>
        <lastKnownPosition>
          <x>0</x>
          <y>0</y>
        </lastKnownPosition>
        <surfaceTemp>42.056606408472952</surfaceTemp>
        <surfacePressure>0.48779264092445374</surfacePressure>
        <luminosity>0</luminosity>
        <bondAlebo>0.723442018032074</bondAlebo>
        <greenhouse>0.051376983694528262</greenhouse>
        <surfaceGravity>1.131923899667804</surfaceGravity>
        <planetTiles>
          <PlanetTile>
            <planetTileType>Ice</planetTileType>
            <count>2</count>
          </PlanetTile>
          <PlanetTile>
            <planetTileType>Rocky</planetTileType>
            <count>11</count>
          </PlanetTile>
          <PlanetTile>
            <planetTileType>Volcanic</planetTileType>
            <count>1</count>
          </PlanetTile>
        </planetTiles>
        <rawResources>
          <RawResource>
            <name>Warium</name>
            <id>4</id>
            <amount>51972</amount>
            <accessibility>0.096331119537353516</accessibility>
          </RawResource>
          <RawResource>
            <name>Armoroid</name>
            <id>1</id>
            <amount>834920</amount>
            <accessibility>0.54551476240158081</accessibility>
          </RawResource>
          <RawResource>
            <name>Coppode</name>
            <id>2</id>
            <amount>25411</amount>
            <accessibility>0.667396068572998</accessibility>
          </RawResource>
          <RawResource>
            <name>Fuelodite</name>
            <id>3</id>
            <amount>4961</amount>
            <accessibility>0.980951189994812</accessibility>
          </RawResource>
          <RawResource>
            <name>Glassitum</name>
            <id>6</id>
            <amount>40703</amount>
            <accessibility>0.27876991033554077</accessibility>
          </RawResource>
        </rawResources>
        <population>0</population>
        <solarIndex>
          <int>31</int>
          <int>9</int>
        </solarIndex>
      </SolarBody>
      <SolarBody>
        <name>Swinda 69 32 DwarfPlanet 11</name>
        <orbit>
          <sma>675892736</sma>
          <ecc>0.20401012897491455</ecc>
          <inc>0</inc>
          <lpe>0.54747986793518066</lpe>
          <lan>0</lan>
          <mna>0.54747986793518066</mna>
          <eph>0</eph>
        </orbit>
        <groundStructures />
        <spaceStructures />
        <color>
          <r>0</r>
          <g>1</g>
          <b>0</b>
          <a>1</a>
        </color>
        <satelites>
          <SolarBody>
            <name>Swinda 69 32Moon 11</name>
            <orbit>
              <sma>28781.14453125</sma>
              <ecc>0.0032080053351819515</ecc>
              <inc>0</inc>
              <lpe>0.76693499088287354</lpe>
              <lan>0</lan>
              <mna>0.76693499088287354</mna>
              <eph>0</eph>
            </orbit>
            <groundStructures />
            <spaceStructures />
            <color>
              <r>0</r>
              <g>0</g>
              <b>1</b>
              <a>1</a>
            </color>
            <satelites />
            <totalPopulation>0</totalPopulation>
            <solarType>Moon</solarType>
            <solarSubType>Ocean</solarSubType>
            <mass>4.85234375E+23</mass>
            <bodyRadius>2827.3514912356313</bodyRadius>
            <lastKnownPosition>
              <x>0</x>
              <y>0</y>
            </lastKnownPosition>
            <surfaceTemp>329.30874152558653</surfaceTemp>
            <surfacePressure>0.71976226568222046</surfacePressure>
            <luminosity>0</luminosity>
            <bondAlebo>0.31814530491828918</bondAlebo>
            <greenhouse>0.078102160093617173</greenhouse>
            <surfaceGravity>0.41271360073162322</surfaceGravity>
            <planetTiles>
              <PlanetTile>
                <planetTileType>Ocean</planetTileType>
                <count>7</count>
              </PlanetTile>
            </planetTiles>
            <rawResources>
              <RawResource>
                <name>Warium</name>
                <id>4</id>
                <amount>20793</amount>
                <accessibility>0.097679853439331055</accessibility>
              </RawResource>
              <RawResource>
                <name>Fuelodite</name>
                <id>3</id>
                <amount>907432</amount>
                <accessibility>0.46032208204269409</accessibility>
              </RawResource>
              <RawResource>
                <name>Goldium</name>
                <id>0</id>
                <amount>381</amount>
                <accessibility>0.69019198417663574</accessibility>
              </RawResource>
              <RawResource>
                <name>Coppode</name>
                <id>2</id>
                <amount>5059</amount>
                <accessibility>0.74326002597808838</accessibility>
              </RawResource>
            </rawResources>
            <population>0</population>
            <solarIndex>
              <int>31</int>
              <int>10</int>
              <int>0</int>
            </solarIndex>
          </SolarBody>
        </satelites>
        <totalPopulation>0</totalPopulation>
        <solarType>DwarfPlanet</solarType>
        <solarSubType>EarthLike</solarSubType>
        <mass>2.5E+22</mass>
        <bodyRadius>1149.03652207026</bodyRadius>
        <lastKnownPosition>
          <x>0</x>
          <y>0</y>
        </lastKnownPosition>
        <surfaceTemp>343.64395161657592</surfaceTemp>
        <surfacePressure>0.32998505234718323</surfacePressure>
        <luminosity>0</luminosity>
        <bondAlebo>0.17764951288700104</bondAlebo>
        <greenhouse>0.034040703205134727</greenhouse>
        <surfaceGravity>0.12874464359924234</surfaceGravity>
        <planetTiles>
          <PlanetTile>
            <planetTileType>Ocean</planetTileType>
            <count>3</count>
          </PlanetTile>
        </planetTiles>
        <rawResources>
          <RawResource>
            <name>Warium</name>
            <id>4</id>
            <amount>20793</amount>
            <accessibility>0.17137706279754639</accessibility>
          </RawResource>
          <RawResource>
            <name>Fuelodite</name>
            <id>3</id>
            <amount>907432</amount>
            <accessibility>0.84383153915405273</accessibility>
          </RawResource>
        </rawResources>
        <population>0</population>
        <solarIndex>
          <int>31</int>
          <int>10</int>
        </solarIndex>
      </SolarBody>
      <SolarBody>
        <name>Swinda 69 32 Planet 12</name>
        <orbit>
          <sma>16250024960</sma>
          <ecc>0.0076897703111171722</ecc>
          <inc>0</inc>
          <lpe>0.2305045872926712</lpe>
          <lan>0</lan>
          <mna>0.2305045872926712</mna>
          <eph>0</eph>
        </orbit>
        <groundStructures />
        <spaceStructures />
        <color>
          <r>0.5</r>
          <g>0.5</g>
          <b>0.5</b>
          <a>1</a>
        </color>
        <satelites />
        <totalPopulation>0</totalPopulation>
        <solarType>Planet</solarType>
        <solarSubType>Rocky</solarSubType>
        <mass>4.7573843002319332E+23</mass>
        <bodyRadius>2596.0456979196674</bodyRadius>
        <lastKnownPosition>
          <x>0</x>
          <y>0</y>
        </lastKnownPosition>
        <surfaceTemp>161.30780164025145</surfaceTemp>
        <surfacePressure>90.179237365722656</surfacePressure>
        <luminosity>0</luminosity>
        <bondAlebo>0.518079936504364</bondAlebo>
        <greenhouse>120.57325933156693</greenhouse>
        <surfaceGravity>0.47995486200696114</surfaceGravity>
        <planetTiles>
          <PlanetTile>
            <planetTileType>Rocky</planetTileType>
            <count>6</count>
          </PlanetTile>
          <PlanetTile>
            <planetTileType>Ice</planetTileType>
            <count>1</count>
          </PlanetTile>
        </planetTiles>
        <rawResources>
          <RawResource>
            <name>Armoroid</name>
            <id>1</id>
            <amount>953416</amount>
            <accessibility>0.76479101181030273</accessibility>
          </RawResource>
          <RawResource>
            <name>Coppode</name>
            <id>2</id>
            <amount>25411</amount>
            <accessibility>0.055098056793212891</accessibility>
          </RawResource>
          <RawResource>
            <name>Warium</name>
            <id>4</id>
            <amount>38199</amount>
            <accessibility>0.43175238370895386</accessibility>
          </RawResource>
          <RawResource>
            <name>Glassitum</name>
            <id>6</id>
            <amount>496178</amount>
            <accessibility>0.85676431655883789</accessibility>
          </RawResource>
        </rawResources>
        <population>0</population>
        <solarIndex>
          <int>31</int>
          <int>11</int>
        </solarIndex>
      </SolarBody>
      <SolarBody>
        <name>Swinda 69 32 Planet 13</name>
        <orbit>
          <sma>18345515008</sma>
          <ecc>0.0015874052187427878</ecc>
          <inc>0</inc>
          <lpe>4.0895309448242188</lpe>
          <lan>0</lan>
          <mna>4.0895309448242188</mna>
          <eph>0</eph>
        </orbit>
        <groundStructures />
        <spaceStructures />
        <color>
          <r>0.5</r>
          <g>0.5</g>
          <b>0.5</b>
          <a>1</a>
        </color>
        <satelites>
          <SolarBody>
            <name>Swinda 69 32Moon 13</name>
            <orbit>
              <sma>5899045</sma>
              <ecc>0.019490038976073265</ecc>
              <inc>0</inc>
              <lpe>4.4975967407226563</lpe>
              <lan>0</lan>
              <mna>4.4975967407226563</mna>
              <eph>0</eph>
            </orbit>
            <groundStructures />
            <spaceStructures />
            <color>
              <r>0.5</r>
              <g>0.5</g>
              <b>0.5</b>
              <a>1</a>
            </color>
            <satelites />
            <totalPopulation>0</totalPopulation>
            <solarType>Moon</solarType>
            <solarSubType>Rocky</solarSubType>
            <mass>3.7252685546875E+23</mass>
            <bodyRadius>2779.5736580454377</bodyRadius>
            <lastKnownPosition>
              <x>0</x>
              <y>0</y>
            </lastKnownPosition>
            <surfaceTemp>54.999062333221175</surfaceTemp>
            <surfacePressure>0.32341253757476807</surfacePressure>
            <luminosity>0</luminosity>
            <bondAlebo>0.602125346660614</bondAlebo>
            <greenhouse>0.033333502729193228</greenhouse>
            <surfaceGravity>0.32783705412169911</surfaceGravity>
            <planetTiles>
              <PlanetTile>
                <planetTileType>Rocky</planetTileType>
                <count>7</count>
              </PlanetTile>
            </planetTiles>
            <rawResources>
              <RawResource>
                <name>Armoroid</name>
                <id>1</id>
                <amount>953416</amount>
                <accessibility>0.36987167596817017</accessibility>
              </RawResource>
              <RawResource>
                <name>Coppode</name>
                <id>2</id>
                <amount>25411</amount>
                <accessibility>0.21810078620910645</accessibility>
              </RawResource>
              <RawResource>
                <name>Warium</name>
                <id>4</id>
                <amount>38199</amount>
                <accessibility>0.82015132904052734</accessibility>
              </RawResource>
              <RawResource>
                <name>Fuelodite</name>
                <id>3</id>
                <amount>4961</amount>
                <accessibility>0.26335030794143677</accessibility>
              </RawResource>
            </rawResources>
            <population>0</population>
            <solarIndex>
              <int>31</int>
              <int>12</int>
              <int>0</int>
            </solarIndex>
          </SolarBody>
          <SolarBody>
            <name>Swinda 69 32Moon 13</name>
            <orbit>
              <sma>1294570.875</sma>
              <ecc>0.0085706077516078949</ecc>
              <inc>0</inc>
              <lpe>1.6710777282714844</lpe>
              <lan>0</lan>
              <mna>1.6710777282714844</mna>
              <eph>0</eph>
            </orbit>
            <groundStructures />
            <spaceStructures />
            <color>
              <r>0.5</r>
              <g>0.5</g>
              <b>0.5</b>
              <a>1</a>
            </color>
            <satelites />
            <totalPopulation>0</totalPopulation>
            <solarType>Moon</solarType>
            <solarSubType>Rocky</solarSubType>
            <mass>2.8856503963470457E+22</mass>
            <bodyRadius>1107.870732418241</bodyRadius>
            <lastKnownPosition>
              <x>0</x>
              <y>0</y>
            </lastKnownPosition>
            <surfaceTemp>12.433275060762332</surfaceTemp>
            <surfacePressure>0.80759960412979126</surfacePressure>
            <luminosity>0</luminosity>
            <bondAlebo>0.99898326396942139</bondAlebo>
            <greenhouse>0.0886076511502742</greenhouse>
            <surfaceGravity>0.15985357812353687</surfaceGravity>
            <planetTiles>
              <PlanetTile>
                <planetTileType>Rocky</planetTileType>
                <count>2</count>
              </PlanetTile>
              <PlanetTile>
                <planetTileType>Volcanic</planetTileType>
                <count>1</count>
              </PlanetTile>
            </planetTiles>
            <rawResources>
              <RawResource>
                <name>Armoroid</name>
                <id>1</id>
                <amount>953416</amount>
                <accessibility>0.89904475212097168</accessibility>
              </RawResource>
              <RawResource>
                <name>Warium</name>
                <id>4</id>
                <amount>83867</amount>
                <accessibility>0.762458324432373</accessibility>
              </RawResource>
            </rawResources>
            <population>0</population>
            <solarIndex>
              <int>31</int>
              <int>12</int>
              <int>1</int>
            </solarIndex>
          </SolarBody>
          <SolarBody>
            <name>Swinda 69 32Moon 13</name>
            <orbit>
              <sma>79715.640625</sma>
              <ecc>0.0035424232482910156</ecc>
              <inc>0</inc>
              <lpe>1.8875367641448975</lpe>
              <lan>0</lan>
              <mna>1.8875367641448975</mna>
              <eph>0</eph>
            </orbit>
            <groundStructures />
            <spaceStructures />
            <color>
              <r>0.5</r>
              <g>0.5</g>
              <b>0.5</b>
              <a>1</a>
            </color>
            <satelites />
            <totalPopulation>0</totalPopulation>
            <solarType>Moon</solarType>
            <solarSubType>Rocky</solarSubType>
            <mass>2.959271812438965E+23</mass>
            <bodyRadius>2353.1495325157257</bodyRadius>
            <lastKnownPosition>
              <x>0</x>
              <y>0</y>
            </lastKnownPosition>
            <surfaceTemp>60.535971779896364</surfaceTemp>
            <surfacePressure>0.54374414682388306</surfacePressure>
            <luminosity>0</luminosity>
            <bondAlebo>0.4218936562538147</bondAlebo>
            <greenhouse>0.057687898869735084</greenhouse>
            <surfaceGravity>0.36336461499990524</surfaceGravity>
            <planetTiles>
              <PlanetTile>
                <planetTileType>Rocky</planetTileType>
                <count>4</count>
              </PlanetTile>
              <PlanetTile>
                <planetTileType>Desert</planetTileType>
                <count>1</count>
              </PlanetTile>
              <PlanetTile>
                <planetTileType>Volcanic</planetTileType>
                <count>1</count>
              </PlanetTile>
            </planetTiles>
            <rawResources>
              <RawResource>
                <name>Armoroid</name>
                <id>1</id>
                <amount>953416</amount>
                <accessibility>0.24885463714599609</accessibility>
              </RawResource>
              <RawResource>
                <name>Glassitum</name>
                <id>6</id>
                <amount>500020</amount>
                <accessibility>0.27977591753005981</accessibility>
              </RawResource>
              <RawResource>
                <name>Warium</name>
                <id>4</id>
                <amount>98142</amount>
                <accessibility>0.48230332136154175</accessibility>
              </RawResource>
              <RawResource>
                <name>Fuelodite</name>
                <id>3</id>
                <amount>58722</amount>
                <accessibility>0.7875676155090332</accessibility>
              </RawResource>
              <RawResource>
                <name>Goldium</name>
                <id>0</id>
                <amount>381</amount>
                <accessibility>0.95181787014007568</accessibility>
              </RawResource>
              <RawResource>
                <name>Coppode</name>
                <id>2</id>
                <amount>67617</amount>
                <accessibility>0.43573516607284546</accessibility>
              </RawResource>
            </rawResources>
            <population>0</population>
            <solarIndex>
              <int>31</int>
              <int>12</int>
              <int>2</int>
            </solarIndex>
          </SolarBody>
        </satelites>
        <totalPopulation>0</totalPopulation>
        <solarType>Planet</solarType>
        <solarSubType>Rocky</solarSubType>
        <mass>4.7010059356689451E+24</mass>
        <bodyRadius>5929.3572376778684</bodyRadius>
        <lastKnownPosition>
          <x>0</x>
          <y>0</y>
        </lastKnownPosition>
        <surfaceTemp>55.086996762198012</surfaceTemp>
        <surfacePressure>1.0700054168701172</surfacePressure>
        <luminosity>0</luminosity>
        <bondAlebo>0.61306852102279663</bondAlebo>
        <greenhouse>0.12125394516044598</greenhouse>
        <surfaceGravity>0.90914340406561622</surfaceGravity>
        <planetTiles>
          <PlanetTile>
            <planetTileType>Ice</planetTileType>
            <count>2</count>
          </PlanetTile>
          <PlanetTile>
            <planetTileType>Rocky</planetTileType>
            <count>11</count>
          </PlanetTile>
          <PlanetTile>
            <planetTileType>Volcanic</planetTileType>
            <count>1</count>
          </PlanetTile>
        </planetTiles>
        <rawResources>
          <RawResource>
            <name>Coppode</name>
            <id>2</id>
            <amount>58722</amount>
            <accessibility>0.14658129215240479</accessibility>
          </RawResource>
          <RawResource>
            <name>Armoroid</name>
            <id>1</id>
            <amount>1913</amount>
            <accessibility>0.24759364128112793</accessibility>
          </RawResource>
          <RawResource>
            <name>Fuelodite</name>
            <id>3</id>
            <amount>1384</amount>
            <accessibility>0.51121634244918823</accessibility>
          </RawResource>
          <RawResource>
            <name>Warium</name>
            <id>4</id>
            <amount>95382</amount>
            <accessibility>0.86967325210571289</accessibility>
          </RawResource>
          <RawResource>
            <name>Glassitum</name>
            <id>6</id>
            <amount>40703</amount>
            <accessibility>0.33118301630020142</accessibility>
          </RawResource>
        </rawResources>
        <population>0</population>
        <solarIndex>
          <int>31</int>
          <int>12</int>
        </solarIndex>
      </SolarBody>
      <SolarBody>
        <name>Swinda 69 32 Comet 14</name>
        <orbit>
          <sma>7807440896</sma>
          <ecc>0.56016331911087036</ecc>
          <inc>0</inc>
          <lpe>4.8742456436157227</lpe>
          <lan>0</lan>
          <mna>4.8742456436157227</mna>
          <eph>0</eph>
        </orbit>
        <groundStructures />
        <spaceStructures />
        <color>
          <r>0.5</r>
          <g>0.5</g>
          <b>0.5</b>
          <a>1</a>
        </color>
        <satelites>
          <SolarBody>
            <name>Swinda 69 32Moon 14</name>
            <orbit>
              <sma>544.29461669921875</sma>
              <ecc>0.0068854414857923985</ecc>
              <inc>0</inc>
              <lpe>3.1452932357788086</lpe>
              <lan>0</lan>
              <mna>3.1452932357788086</mna>
              <eph>0</eph>
            </orbit>
            <groundStructures />
            <spaceStructures />
            <color>
              <r>0.5</r>
              <g>0.5</g>
              <b>0.5</b>
              <a>1</a>
            </color>
            <satelites />
            <totalPopulation>0</totalPopulation>
            <solarType>Moon</solarType>
            <solarSubType>Rocky</solarSubType>
            <mass>2.7035945892333984E+23</mass>
            <bodyRadius>2273.507978613563</bodyRadius>
            <lastKnownPosition>
              <x>0</x>
              <y>0</y>
            </lastKnownPosition>
            <surfaceTemp>84.253356447900018</surfaceTemp>
            <surfacePressure>0.69155913591384888</surfacePressure>
            <luminosity>0</luminosity>
            <bondAlebo>0.60969358682632446</bondAlebo>
            <greenhouse>0.07477396248947904</greenhouse>
            <surfaceGravity>0.35563576494148164</surfaceGravity>
            <planetTiles>
              <PlanetTile>
                <planetTileType>Rocky</planetTileType>
                <count>5</count>
              </PlanetTile>
              <PlanetTile>
                <planetTileType>Volcanic</planetTileType>
                <count>1</count>
              </PlanetTile>
            </planetTiles>
            <rawResources>
              <RawResource>
                <name>Armoroid</name>
                <id>1</id>
                <amount>953416</amount>
                <accessibility>0.051280975341796875</accessibility>
              </RawResource>
              <RawResource>
                <name>Warium</name>
                <id>4</id>
                <amount>98142</amount>
                <accessibility>0.4480864405632019</accessibility>
              </RawResource>
              <RawResource>
                <name>Fuelodite</name>
                <id>3</id>
                <amount>58722</amount>
                <accessibility>0.611613929271698</accessibility>
              </RawResource>
              <RawResource>
                <name>Glassitum</name>
                <id>6</id>
                <amount>25411</amount>
                <accessibility>0.36550050973892212</accessibility>
              </RawResource>
              <RawResource>
                <name>Goldium</name>
                <id>0</id>
                <amount>381</amount>
                <accessibility>0.67659580707550049</accessibility>
              </RawResource>
              <RawResource>
                <name>Coppode</name>
                <id>2</id>
                <amount>67617</amount>
                <accessibility>0.28937274217605591</accessibility>
              </RawResource>
            </rawResources>
            <population>0</population>
            <solarIndex>
              <int>31</int>
              <int>13</int>
              <int>0</int>
            </solarIndex>
          </SolarBody>
          <SolarBody>
            <name>Swinda 69 32Moon 14</name>
            <orbit>
              <sma>22.236858367919922</sma>
              <ecc>0.0089375507086515427</ecc>
              <inc>0</inc>
              <lpe>2.6064226627349854</lpe>
              <lan>0</lan>
              <mna>2.6064226627349854</mna>
              <eph>0</eph>
            </orbit>
            <groundStructures />
            <spaceStructures />
            <color>
              <r>0.5</r>
              <g>0.5</g>
              <b>0.5</b>
              <a>1</a>
            </color>
            <satelites />
            <totalPopulation>0</totalPopulation>
            <solarType>Moon</solarType>
            <solarSubType>Rocky</solarSubType>
            <mass>2.4835502624511719E+23</mass>
            <bodyRadius>2498.5111223346667</bodyRadius>
            <lastKnownPosition>
              <x>0</x>
              <y>0</y>
            </lastKnownPosition>
            <surfaceTemp>88.257413257888771</surfaceTemp>
            <surfacePressure>0.0643695741891861</surfacePressure>
            <luminosity>0</luminosity>
            <bondAlebo>0.51740533113479614</bondAlebo>
            <greenhouse>0.0064054597440986374</greenhouse>
            <surfaceGravity>0.27049996055222414</surfaceGravity>
            <planetTiles>
              <PlanetTile>
                <planetTileType>Rocky</planetTileType>
                <count>6</count>
              </PlanetTile>
            </planetTiles>
            <rawResources>
              <RawResource>
                <name>Armoroid</name>
                <id>1</id>
                <amount>953416</amount>
                <accessibility>0.88467955589294434</accessibility>
              </RawResource>
              <RawResource>
                <name>Coppode</name>
                <id>2</id>
                <amount>25411</amount>
                <accessibility>0.66637003421783447</accessibility>
              </RawResource>
              <RawResource>
                <name>Warium</name>
                <id>4</id>
                <amount>38199</amount>
                <accessibility>0.824142336845398</accessibility>
              </RawResource>
              <RawResource>
                <name>Fuelodite</name>
                <id>3</id>
                <amount>4961</amount>
                <accessibility>0.5060238242149353</accessibility>
              </RawResource>
            </rawResources>
            <population>0</population>
            <solarIndex>
              <int>31</int>
              <int>13</int>
              <int>1</int>
            </solarIndex>
          </SolarBody>
        </satelites>
        <totalPopulation>0</totalPopulation>
        <solarType>Comet</solarType>
        <solarSubType>Rocky</solarSubType>
        <mass>460000000000000</mass>
        <bodyRadius>2.5160632155160427</bodyRadius>
        <lastKnownPosition>
          <x>0</x>
          <y>0</y>
        </lastKnownPosition>
        <surfaceTemp>0</surfaceTemp>
        <surfacePressure>0</surfacePressure>
        <luminosity>0</luminosity>
        <bondAlebo>0.36595550179481506</bondAlebo>
        <greenhouse>0</greenhouse>
        <surfaceGravity>0.00049405074815712946</surfaceGravity>
        <planetTiles>
          <PlanetTile>
            <planetTileType>Rocky</planetTileType>
            <count>1</count>
          </PlanetTile>
        </planetTiles>
        <rawResources>
          <RawResource>
            <name>Armoroid</name>
            <id>1</id>
            <amount>953416</amount>
            <accessibility>0.74723565578460693</accessibility>
          </RawResource>
        </rawResources>
        <population>0</population>
        <solarIndex>
          <int>31</int>
          <int>13</int>
        </solarIndex>
      </SolarBody>
      <SolarBody>
        <name>Swinda 69 32 Planet 15</name>
        <orbit>
          <sma>18848483328</sma>
          <ecc>0.0007279121782630682</ecc>
          <inc>0</inc>
          <lpe>4.2155289649963379</lpe>
          <lan>0</lan>
          <mna>4.2155289649963379</mna>
          <eph>0</eph>
        </orbit>
        <groundStructures />
        <spaceStructures />
        <color>
          <r>0.5</r>
          <g>0.5</g>
          <b>0.5</b>
          <a>1</a>
        </color>
        <satelites />
        <totalPopulation>0</totalPopulation>
        <solarType>Planet</solarType>
        <solarSubType>Rocky</solarSubType>
        <mass>8.2857460021972648E+24</mass>
        <bodyRadius>7863.4616551000754</bodyRadius>
        <lastKnownPosition>
          <x>0</x>
          <y>0</y>
        </lastKnownPosition>
        <surfaceTemp>52.356311066321346</surfaceTemp>
        <surfacePressure>1.1634175777435303</surfacePressure>
        <luminosity>0</luminosity>
        <bondAlebo>0.66822940111160278</bondAlebo>
        <greenhouse>0.13333193684670841</greenhouse>
        <surfaceGravity>0.91108919414248546</surfaceGravity>
        <planetTiles>
          <PlanetTile>
            <planetTileType>Rocky</planetTileType>
            <count>17</count>
          </PlanetTile>
          <PlanetTile>
            <planetTileType>Desert</planetTileType>
            <count>2</count>
          </PlanetTile>
        </planetTiles>
        <rawResources>
          <RawResource>
            <name>Armoroid</name>
            <id>1</id>
            <amount>953416</amount>
            <accessibility>0.00081694126129150391</accessibility>
          </RawResource>
          <RawResource>
            <name>Coppode</name>
            <id>2</id>
            <amount>25411</amount>
            <accessibility>0.1567913293838501</accessibility>
          </RawResource>
          <RawResource>
            <name>Warium</name>
            <id>4</id>
            <amount>38199</amount>
            <accessibility>0.033444881439208984</accessibility>
          </RawResource>
          <RawResource>
            <name>Fuelodite</name>
            <id>3</id>
            <amount>4961</amount>
            <accessibility>0.71921145915985107</accessibility>
          </RawResource>
          <RawResource>
            <name>Glassitum</name>
            <id>6</id>
            <amount>40703</amount>
            <accessibility>0.97901642322540283</accessibility>
          </RawResource>
          <RawResource>
            <name>Goldium</name>
            <id>0</id>
            <amount>441</amount>
            <accessibility>0.731560468673706</accessibility>
          </RawResource>
        </rawResources>
        <population>0</population>
        <solarIndex>
          <int>31</int>
          <int>14</int>
        </solarIndex>
      </SolarBody>
      <SolarBody>
        <name>Swinda 69 32 Comet 16</name>
        <orbit>
          <sma>6197264896</sma>
          <ecc>0.95705199241638184</ecc>
          <inc>0</inc>
          <lpe>1.9503670930862427</lpe>
          <lan>0</lan>
          <mna>1.9503670930862427</mna>
          <eph>0</eph>
        </orbit>
        <groundStructures />
        <spaceStructures />
        <color>
          <r>0.5</r>
          <g>0.5</g>
          <b>0.5</b>
          <a>1</a>
        </color>
        <satelites />
        <totalPopulation>0</totalPopulation>
        <solarType>Comet</solarType>
        <solarSubType>Rocky</solarSubType>
        <mass>500000000000000</mass>
        <bodyRadius>2.7700711837067944</bodyRadius>
        <lastKnownPosition>
          <x>0</x>
          <y>0</y>
        </lastKnownPosition>
        <surfaceTemp>0</surfaceTemp>
        <surfacePressure>0</surfacePressure>
        <luminosity>0</luminosity>
        <bondAlebo>0.69683557748794556</bondAlebo>
        <greenhouse>0</greenhouse>
        <surfaceGravity>0.00044304207450755485</surfaceGravity>
        <planetTiles>
          <PlanetTile>
            <planetTileType>Rocky</planetTileType>
            <count>1</count>
          </PlanetTile>
        </planetTiles>
        <rawResources>
          <RawResource>
            <name>Armoroid</name>
            <id>1</id>
            <amount>953416</amount>
            <accessibility>0.58847254514694214</accessibility>
          </RawResource>
        </rawResources>
        <population>0</population>
        <solarIndex>
          <int>31</int>
          <int>15</int>
        </solarIndex>
      </SolarBody>
      <SolarBody>
        <name>Swinda 69 32 Comet 17</name>
        <orbit>
          <sma>550639616</sma>
          <ecc>0.73056364059448242</ecc>
          <inc>0</inc>
          <lpe>1.8732284307479858</lpe>
          <lan>0</lan>
          <mna>1.8732284307479858</mna>
          <eph>0</eph>
        </orbit>
        <groundStructures />
        <spaceStructures />
        <color>
          <r>0.5</r>
          <g>0.5</g>
          <b>0.5</b>
          <a>1</a>
        </color>
        <satelites />
        <totalPopulation>0</totalPopulation>
        <solarType>Comet</solarType>
        <solarSubType>Rocky</solarSubType>
        <mass>210000000000000</mass>
        <bodyRadius>2.3046793855873737</bodyRadius>
        <lastKnownPosition>
          <x>0</x>
          <y>0</y>
        </lastKnownPosition>
        <surfaceTemp>0</surfaceTemp>
        <surfacePressure>0</surfacePressure>
        <luminosity>0</luminosity>
        <bondAlebo>0.59201043844223022</bondAlebo>
        <greenhouse>0</greenhouse>
        <surfaceGravity>0.00026881598285128429</surfaceGravity>
        <planetTiles>
          <PlanetTile>
            <planetTileType>Rocky</planetTileType>
            <count>1</count>
          </PlanetTile>
        </planetTiles>
        <rawResources>
          <RawResource>
            <name>Armoroid</name>
            <id>1</id>
            <amount>953416</amount>
            <accessibility>0.55283445119857788</accessibility>
          </RawResource>
        </rawResources>
        <population>0</population>
        <solarIndex>
          <int>31</int>
          <int>16</int>
        </solarIndex>
      </SolarBody>
    </satelites>
    <totalPopulation>0</totalPopulation>
    <solarType>Star</solarType>
    <solarSubType>MainSequence</solarSubType>
    <mass>1.1219009637451171E+32</mass>
    <bodyRadius>26756643.341342043</bodyRadius>
    <lastKnownPosition>
      <x>0</x>
      <y>0</y>
    </lastKnownPosition>
    <surfaceTemp>6924.1332869235175</surfaceTemp>
    <surfacePressure>1</surfacePressure>
    <luminosity>2.1788919963937092E+28</luminosity>
    <bondAlebo>0.5</bondAlebo>
    <greenhouse>0.1123595</greenhouse>
    <surfaceGravity>1.0654868357635048</surfaceGravity>
    <planetTiles />
    <rawResources />
    <population>0</population>
    <solarIndex>
      <int>31</int>
    </solarIndex>
  </solar>
  <nearStars>
    <Id>3820144d-b382-4e96-85c0-8725e0567d58</Id>
    <Id>4b7cd1af-806c-47ff-8b93-f4606b255585</Id>
    <Id>3820144d-b382-4e96-85c0-8725e0567d58</Id>
    <Id>462b9312-9241-430a-a5a7-9661d538f7fe</Id>
  </nearStars>
  <government />
  <governmentInfluence>0</governmentInfluence>
  <isCapital>false</isCapital>
  <index>31</index>
</SolarModel>