<?xml version="1.0" encoding="Windows-1252"?>
<SolarModel xmlns:xsi="http://www.w3.org/2001/XMLSchema-instance" xmlns:xsd="http://www.w3.org/2001/XMLSchema">
  <Id>d37d2c80-6c33-4e83-b4a9-eac6f72e7fbb</Id>
  <name>Deskuerili 326</name>
  <isActive>false</isActive>
  <galacticPosition>
    <x>1105.0396677239321</x>
    <y>867.25240629361724</y>
  </galacticPosition>
  <color>
    <r>0</r>
    <g>0</g>
    <b>0</b>
    <a>0</a>
  </color>
  <solar>
    <name>Deskuerili 326 GasGiant</name>
    <orbit>
      <sma>0</sma>
      <ecc>0</ecc>
      <inc>0</inc>
      <lpe>0</lpe>
      <lan>0</lan>
      <mna>0</mna>
      <eph>0</eph>
    </orbit>
    <groundStructures />
    <spaceStructures />
    <color>
      <r>0.6024377</r>
      <g>0.732846439</g>
      <b>1</b>
      <a>1</a>
    </color>
    <satelites>
      <SolarBody>
        <name>Deskuerili 326 Comet 1</name>
        <orbit>
          <sma>19809431552</sma>
          <ecc>0.77485001087188721</ecc>
          <inc>0</inc>
          <lpe>2.9616463184356689</lpe>
          <lan>0</lan>
          <mna>2.9616463184356689</mna>
          <eph>0</eph>
        </orbit>
        <groundStructures />
        <spaceStructures />
        <color>
          <r>0.5</r>
          <g>0.5</g>
          <b>0.5</b>
          <a>1</a>
        </color>
        <satelites />
        <totalPopulation>0</totalPopulation>
        <solarType>Comet</solarType>
        <solarSubType>Rocky</solarSubType>
        <mass>760000000000000</mass>
        <bodyRadius>3.3363303783671032</bodyRadius>
        <lastKnownPosition>
          <x>0</x>
          <y>0</y>
        </lastKnownPosition>
        <surfaceTemp>0</surfaceTemp>
        <surfacePressure>0</surfacePressure>
        <luminosity>0</luminosity>
        <bondAlebo>0.090021617710590363</bondAlebo>
        <greenhouse>0</greenhouse>
        <surfaceGravity>0.00046422905566685733</surfaceGravity>
        <planetTiles>
          <PlanetTile>
            <planetTileType>Rocky</planetTileType>
            <count>1</count>
          </PlanetTile>
        </planetTiles>
        <rawResources>
          <RawResource>
            <name>Armoroid</name>
            <id>1</id>
            <amount>953416</amount>
            <accessibility>0.94994258880615234</accessibility>
          </RawResource>
        </rawResources>
        <population>0</population>
        <solarIndex>
          <int>325</int>
          <int>0</int>
        </solarIndex>
      </SolarBody>
      <SolarBody>
        <name>Deskuerili 326 Comet 2</name>
        <orbit>
          <sma>10824204288</sma>
          <ecc>0.51585566997528076</ecc>
          <inc>0</inc>
          <lpe>3.3187806606292725</lpe>
          <lan>0</lan>
          <mna>3.3187806606292725</mna>
          <eph>0</eph>
        </orbit>
        <groundStructures />
        <spaceStructures />
        <color>
          <r>0.5</r>
          <g>0.5</g>
          <b>0.5</b>
          <a>1</a>
        </color>
        <satelites>
          <SolarBody>
            <name>Deskuerili 326Moon 2</name>
            <orbit>
              <sma>519.40924072265625</sma>
              <ecc>0.015693522989749908</ecc>
              <inc>0</inc>
              <lpe>3.169912576675415</lpe>
              <lan>0</lan>
              <mna>3.169912576675415</mna>
              <eph>0</eph>
            </orbit>
            <groundStructures />
            <spaceStructures />
            <color>
              <r>1</r>
              <g>1</g>
              <b>1</b>
              <a>1</a>
            </color>
            <satelites />
            <totalPopulation>0</totalPopulation>
            <solarType>Moon</solarType>
            <solarSubType>Ice</solarSubType>
            <mass>2.6054265975952149E+23</mass>
            <bodyRadius>2335.0163818591127</bodyRadius>
            <lastKnownPosition>
              <x>0</x>
              <y>0</y>
            </lastKnownPosition>
            <surfaceTemp>51.811688505296623</surfaceTemp>
            <surfacePressure>0.10640907287597656</surfacePressure>
            <luminosity>0</luminosity>
            <bondAlebo>0.57390290498733521</bondAlebo>
            <greenhouse>0.010650270702462451</greenhouse>
            <surfaceGravity>0.32490455895238052</surfaceGravity>
            <planetTiles>
              <PlanetTile>
                <planetTileType>Ice</planetTileType>
                <count>5</count>
              </PlanetTile>
              <PlanetTile>
                <planetTileType>Rocky</planetTileType>
                <count>1</count>
              </PlanetTile>
            </planetTiles>
            <rawResources>
              <RawResource>
                <name>Glassitum</name>
                <id>6</id>
                <amount>381993</amount>
                <accessibility>0.21090400218963623</accessibility>
              </RawResource>
            </rawResources>
            <population>0</population>
            <solarIndex>
              <int>325</int>
              <int>1</int>
              <int>0</int>
            </solarIndex>
          </SolarBody>
          <SolarBody>
            <name>Deskuerili 326Moon 2</name>
            <orbit>
              <sma>438.19281005859375</sma>
              <ecc>0.00016679763211868703</ecc>
              <inc>0</inc>
              <lpe>4.6457343101501465</lpe>
              <lan>0</lan>
              <mna>4.6457343101501465</mna>
              <eph>0</eph>
            </orbit>
            <groundStructures />
            <spaceStructures />
            <color>
              <r>1</r>
              <g>1</g>
              <b>1</b>
              <a>1</a>
            </color>
            <satelites />
            <totalPopulation>0</totalPopulation>
            <solarType>Moon</solarType>
            <solarSubType>Ice</solarSubType>
            <mass>1.5491694450378419E+23</mass>
            <bodyRadius>1902.7406400058285</bodyRadius>
            <lastKnownPosition>
              <x>0</x>
              <y>0</y>
            </lastKnownPosition>
            <surfaceTemp>47.0946551721254</surfaceTemp>
            <surfacePressure>0.66014516353607178</surfacePressure>
            <luminosity>0</luminosity>
            <bondAlebo>0.71588116884231567</bondAlebo>
            <greenhouse>0.071092578392293632</greenhouse>
            <surfaceGravity>0.29093539517536693</surfaceGravity>
            <planetTiles>
              <PlanetTile>
                <planetTileType>Ice</planetTileType>
                <count>4</count>
              </PlanetTile>
              <PlanetTile>
                <planetTileType>Rocky</planetTileType>
                <count>1</count>
              </PlanetTile>
            </planetTiles>
            <rawResources />
            <population>0</population>
            <solarIndex>
              <int>325</int>
              <int>1</int>
              <int>1</int>
            </solarIndex>
          </SolarBody>
          <SolarBody>
            <name>Deskuerili 326Moon 2</name>
            <orbit>
              <sma>520.5706787109375</sma>
              <ecc>0.010850499384105206</ecc>
              <inc>0</inc>
              <lpe>0.515630304813385</lpe>
              <lan>0</lan>
              <mna>0.515630304813385</mna>
              <eph>0</eph>
            </orbit>
            <groundStructures />
            <spaceStructures />
            <color>
              <r>0.5</r>
              <g>0.5</g>
              <b>0.5</b>
              <a>1</a>
            </color>
            <satelites />
            <totalPopulation>0</totalPopulation>
            <solarType>Moon</solarType>
            <solarSubType>Rocky</solarSubType>
            <mass>2.130398178100586E+23</mass>
            <bodyRadius>2416.9669009147556</bodyRadius>
            <lastKnownPosition>
              <x>0</x>
              <y>0</y>
            </lastKnownPosition>
            <surfaceTemp>29.953299361551021</surfaceTemp>
            <surfacePressure>0.62855815887451172</surfacePressure>
            <luminosity>0</luminosity>
            <bondAlebo>0.95344090461730957</bondAlebo>
            <greenhouse>0.06741824518714859</greenhouse>
            <surfaceGravity>0.24795690253728947</surfaceGravity>
            <planetTiles>
              <PlanetTile>
                <planetTileType>Rocky</planetTileType>
                <count>6</count>
              </PlanetTile>
            </planetTiles>
            <rawResources>
              <RawResource>
                <name>Armoroid</name>
                <id>1</id>
                <amount>953416</amount>
                <accessibility>0.62200528383255</accessibility>
              </RawResource>
              <RawResource>
                <name>Coppode</name>
                <id>2</id>
                <amount>25411</amount>
                <accessibility>0.29867762327194214</accessibility>
              </RawResource>
              <RawResource>
                <name>Warium</name>
                <id>4</id>
                <amount>38199</amount>
                <accessibility>0.97698593139648438</accessibility>
              </RawResource>
              <RawResource>
                <name>Fuelodite</name>
                <id>3</id>
                <amount>4961</amount>
                <accessibility>0.035961627960205078</accessibility>
              </RawResource>
            </rawResources>
            <population>0</population>
            <solarIndex>
              <int>325</int>
              <int>1</int>
              <int>2</int>
            </solarIndex>
          </SolarBody>
          <SolarBody>
            <name>Deskuerili 326Moon 2</name>
            <orbit>
              <sma>891.359375</sma>
              <ecc>0.014142643660306931</ecc>
              <inc>0</inc>
              <lpe>0.62713897228240967</lpe>
              <lan>0</lan>
              <mna>0.62713897228240967</mna>
              <eph>0</eph>
            </orbit>
            <groundStructures />
            <spaceStructures />
            <color>
              <r>0.5</r>
              <g>0.5</g>
              <b>0.5</b>
              <a>1</a>
            </color>
            <satelites />
            <totalPopulation>0</totalPopulation>
            <solarType>Moon</solarType>
            <solarSubType>Rocky</solarSubType>
            <mass>3.0035055160522462E+23</mass>
            <bodyRadius>2541.803903696496</bodyRadius>
            <lastKnownPosition>
              <x>0</x>
              <y>0</y>
            </lastKnownPosition>
            <surfaceTemp>62.09349399312233</surfaceTemp>
            <surfacePressure>0.72192895412445068</surfacePressure>
            <luminosity>0</luminosity>
            <bondAlebo>0.14377166330814362</bondAlebo>
            <greenhouse>0.078358750512955669</greenhouse>
            <surfaceGravity>0.31608302696970797</surfaceGravity>
            <planetTiles>
              <PlanetTile>
                <planetTileType>Desert</planetTileType>
                <count>1</count>
              </PlanetTile>
              <PlanetTile>
                <planetTileType>Rocky</planetTileType>
                <count>5</count>
              </PlanetTile>
            </planetTiles>
            <rawResources>
              <RawResource>
                <name>Glassitum</name>
                <id>6</id>
                <amount>907432</amount>
                <accessibility>0.032549619674682617</accessibility>
              </RawResource>
              <RawResource>
                <name>Armoroid</name>
                <id>1</id>
                <amount>834920</amount>
                <accessibility>0.43827694654464722</accessibility>
              </RawResource>
              <RawResource>
                <name>Coppode</name>
                <id>2</id>
                <amount>25411</amount>
                <accessibility>0.26854652166366577</accessibility>
              </RawResource>
              <RawResource>
                <name>Warium</name>
                <id>4</id>
                <amount>38199</amount>
                <accessibility>0.89134550094604492</accessibility>
              </RawResource>
              <RawResource>
                <name>Fuelodite</name>
                <id>3</id>
                <amount>4961</amount>
                <accessibility>0.86788201332092285</accessibility>
              </RawResource>
            </rawResources>
            <population>0</population>
            <solarIndex>
              <int>325</int>
              <int>1</int>
              <int>3</int>
            </solarIndex>
          </SolarBody>
        </satelites>
        <totalPopulation>0</totalPopulation>
        <solarType>Comet</solarType>
        <solarSubType>Rocky</solarSubType>
        <mass>840000000000000</mass>
        <bodyRadius>3.1685976050280775</bodyRadius>
        <lastKnownPosition>
          <x>0</x>
          <y>0</y>
        </lastKnownPosition>
        <surfaceTemp>0</surfaceTemp>
        <surfacePressure>0</surfacePressure>
        <luminosity>0</luminosity>
        <bondAlebo>0.56472641229629517</bondAlebo>
        <greenhouse>0</greenhouse>
        <surfaceGravity>0.00056885546324446606</surfaceGravity>
        <planetTiles>
          <PlanetTile>
            <planetTileType>Rocky</planetTileType>
            <count>1</count>
          </PlanetTile>
        </planetTiles>
        <rawResources>
          <RawResource>
            <name>Armoroid</name>
            <id>1</id>
            <amount>953416</amount>
            <accessibility>0.68965828418731689</accessibility>
          </RawResource>
        </rawResources>
        <population>0</population>
        <solarIndex>
          <int>325</int>
          <int>1</int>
        </solarIndex>
      </SolarBody>
      <SolarBody>
        <name>Deskuerili 326 Comet 3</name>
        <orbit>
          <sma>2604653568</sma>
          <ecc>0.96290212869644165</ecc>
          <inc>0</inc>
          <lpe>0.34376299381256104</lpe>
          <lan>0</lan>
          <mna>0.34376299381256104</mna>
          <eph>0</eph>
        </orbit>
        <groundStructures />
        <spaceStructures />
        <color>
          <r>0.5</r>
          <g>0.5</g>
          <b>0.5</b>
          <a>1</a>
        </color>
        <satelites>
          <SolarBody>
            <name>Deskuerili 326Moon 3</name>
            <orbit>
              <sma>20.605188369750977</sma>
              <ecc>0.013977291062474251</ecc>
              <inc>0</inc>
              <lpe>2.236302375793457</lpe>
              <lan>0</lan>
              <mna>2.236302375793457</mna>
              <eph>0</eph>
            </orbit>
            <groundStructures />
            <spaceStructures />
            <color>
              <r>1</r>
              <g>1</g>
              <b>1</b>
              <a>1</a>
            </color>
            <satelites />
            <totalPopulation>0</totalPopulation>
            <solarType>Moon</solarType>
            <solarSubType>Ice</solarSubType>
            <mass>4.0001518249511722E+23</mass>
            <bodyRadius>2684.1117451008922</bodyRadius>
            <lastKnownPosition>
              <x>0</x>
              <y>0</y>
            </lastKnownPosition>
            <surfaceTemp>103.19114524207423</surfaceTemp>
            <surfacePressure>0.31827819347381592</surfacePressure>
            <luminosity>0</luminosity>
            <bondAlebo>0.61512607336044312</bondAlebo>
            <greenhouse>0.03278187439300196</greenhouse>
            <surfaceGravity>0.37751317845633725</surfaceGravity>
            <planetTiles>
              <PlanetTile>
                <planetTileType>Rocky</planetTileType>
                <count>1</count>
              </PlanetTile>
              <PlanetTile>
                <planetTileType>Ice</planetTileType>
                <count>6</count>
              </PlanetTile>
            </planetTiles>
            <rawResources>
              <RawResource>
                <name>Armoroid</name>
                <id>1</id>
                <amount>953416</amount>
                <accessibility>0.27417701482772827</accessibility>
              </RawResource>
              <RawResource>
                <name>Fuelodite</name>
                <id>3</id>
                <amount>3819</amount>
                <accessibility>0.26267713308334351</accessibility>
              </RawResource>
              <RawResource>
                <name>Glassitum</name>
                <id>6</id>
                <amount>138450</amount>
                <accessibility>0.27209740877151489</accessibility>
              </RawResource>
            </rawResources>
            <population>0</population>
            <solarIndex>
              <int>325</int>
              <int>2</int>
              <int>0</int>
            </solarIndex>
          </SolarBody>
        </satelites>
        <totalPopulation>0</totalPopulation>
        <solarType>Comet</solarType>
        <solarSubType>Rocky</solarSubType>
        <mass>10000000000000</mass>
        <bodyRadius>0.877234530019772</bodyRadius>
        <lastKnownPosition>
          <x>0</x>
          <y>0</y>
        </lastKnownPosition>
        <surfaceTemp>0</surfaceTemp>
        <surfacePressure>0</surfacePressure>
        <luminosity>0</luminosity>
        <bondAlebo>0.75415241718292236</bondAlebo>
        <greenhouse>0</greenhouse>
        <surfaceGravity>8.8353832015528372E-05</surfaceGravity>
        <planetTiles>
          <PlanetTile>
            <planetTileType>Rocky</planetTileType>
            <count>1</count>
          </PlanetTile>
        </planetTiles>
        <rawResources>
          <RawResource>
            <name>Armoroid</name>
            <id>1</id>
            <amount>953416</amount>
            <accessibility>0.28141516447067261</accessibility>
          </RawResource>
        </rawResources>
        <population>0</population>
        <solarIndex>
          <int>325</int>
          <int>2</int>
        </solarIndex>
      </SolarBody>
      <SolarBody>
        <name>Deskuerili 326 Comet 4</name>
        <orbit>
          <sma>1564966016</sma>
          <ecc>0.59817427396774292</ecc>
          <inc>0</inc>
          <lpe>4.2365450859069824</lpe>
          <lan>0</lan>
          <mna>4.2365450859069824</mna>
          <eph>0</eph>
        </orbit>
        <groundStructures />
        <spaceStructures />
        <color>
          <r>0.5</r>
          <g>0.5</g>
          <b>0.5</b>
          <a>1</a>
        </color>
        <satelites>
          <SolarBody>
            <name>Deskuerili 326Moon 4</name>
            <orbit>
              <sma>50.834358215332031</sma>
              <ecc>0.003301308024674654</ecc>
              <inc>0</inc>
              <lpe>2.0819673538208008</lpe>
              <lan>0</lan>
              <mna>2.0819673538208008</mna>
              <eph>0</eph>
            </orbit>
            <groundStructures />
            <spaceStructures />
            <color>
              <r>1</r>
              <g>1</g>
              <b>1</b>
              <a>1</a>
            </color>
            <satelites />
            <totalPopulation>0</totalPopulation>
            <solarType>Moon</solarType>
            <solarSubType>Ice</solarSubType>
            <mass>4.6164043426513671E+23</mass>
            <bodyRadius>2922.4675171991184</bodyRadius>
            <lastKnownPosition>
              <x>0</x>
              <y>0</y>
            </lastKnownPosition>
            <surfaceTemp>155.55510239973947</surfaceTemp>
            <surfacePressure>0.052701808512210846</surfacePressure>
            <luminosity>0</luminosity>
            <bondAlebo>0.27476873993873596</bondAlebo>
            <greenhouse>0.0052359480434558871</greenhouse>
            <surfaceGravity>0.36750333279950359</surfaceGravity>
            <planetTiles>
              <PlanetTile>
                <planetTileType>Ice</planetTileType>
                <count>6</count>
              </PlanetTile>
              <PlanetTile>
                <planetTileType>Rocky</planetTileType>
                <count>1</count>
              </PlanetTile>
            </planetTiles>
            <rawResources>
              <RawResource>
                <name>Coppode</name>
                <id>2</id>
                <amount>58722</amount>
                <accessibility>0.16947126388549805</accessibility>
              </RawResource>
              <RawResource>
                <name>Fuelodite</name>
                <id>3</id>
                <amount>3819</amount>
                <accessibility>0.51866942644119263</accessibility>
              </RawResource>
              <RawResource>
                <name>Glassitum</name>
                <id>6</id>
                <amount>138450</amount>
                <accessibility>0.94604241847991943</accessibility>
              </RawResource>
            </rawResources>
            <population>0</population>
            <solarIndex>
              <int>325</int>
              <int>3</int>
              <int>0</int>
            </solarIndex>
          </SolarBody>
          <SolarBody>
            <name>Deskuerili 326Moon 4</name>
            <orbit>
              <sma>131.63124084472656</sma>
              <ecc>0.017826737836003304</ecc>
              <inc>0</inc>
              <lpe>0.16074590384960175</lpe>
              <lan>0</lan>
              <mna>0.16074590384960175</mna>
              <eph>0</eph>
            </orbit>
            <groundStructures />
            <spaceStructures />
            <color>
              <r>0.5</r>
              <g>0.5</g>
              <b>0.5</b>
              <a>1</a>
            </color>
            <satelites />
            <totalPopulation>0</totalPopulation>
            <solarType>Moon</solarType>
            <solarSubType>Rocky</solarSubType>
            <mass>1.650113868713379E+23</mass>
            <bodyRadius>1864.5394079655111</bodyRadius>
            <lastKnownPosition>
              <x>0</x>
              <y>0</y>
            </lastKnownPosition>
            <surfaceTemp>94.11454429854966</surfaceTemp>
            <surfacePressure>0.70616257190704346</surfacePressure>
            <luminosity>0</luminosity>
            <bondAlebo>0.90547215938568115</bondAlebo>
            <greenhouse>0.076494558779746036</greenhouse>
            <surfaceGravity>0.32272128290708246</surfaceGravity>
            <planetTiles>
              <PlanetTile>
                <planetTileType>Rocky</planetTileType>
                <count>5</count>
              </PlanetTile>
            </planetTiles>
            <rawResources>
              <RawResource>
                <name>Armoroid</name>
                <id>1</id>
                <amount>953416</amount>
                <accessibility>0.12764108180999756</accessibility>
              </RawResource>
              <RawResource>
                <name>Coppode</name>
                <id>2</id>
                <amount>25411</amount>
                <accessibility>0.14941036701202393</accessibility>
              </RawResource>
            </rawResources>
            <population>0</population>
            <solarIndex>
              <int>325</int>
              <int>3</int>
              <int>1</int>
            </solarIndex>
          </SolarBody>
          <SolarBody>
            <name>Deskuerili 326Moon 4</name>
            <orbit>
              <sma>20.345283508300781</sma>
              <ecc>0.0011407471029087901</ecc>
              <inc>0</inc>
              <lpe>0.94101035594940186</lpe>
              <lan>0</lan>
              <mna>0.94101035594940186</mna>
              <eph>0</eph>
            </orbit>
            <groundStructures />
            <spaceStructures />
            <color>
              <r>0.5</r>
              <g>0.5</g>
              <b>0.5</b>
              <a>1</a>
            </color>
            <satelites />
            <totalPopulation>0</totalPopulation>
            <solarType>Moon</solarType>
            <solarSubType>Rocky</solarSubType>
            <mass>1.4571895599365235E+23</mass>
            <bodyRadius>1770.9893657654927</bodyRadius>
            <lastKnownPosition>
              <x>0</x>
              <y>0</y>
            </lastKnownPosition>
            <surfaceTemp>134.11450334232885</surfaceTemp>
            <surfacePressure>0.34688675403594971</surfacePressure>
            <luminosity>0</luminosity>
            <bondAlebo>0.60404950380325317</bondAlebo>
            <greenhouse>0.035864769417778206</greenhouse>
            <surfaceGravity>0.31589370446522846</surfaceGravity>
            <planetTiles>
              <PlanetTile>
                <planetTileType>Rocky</planetTileType>
                <count>4</count>
              </PlanetTile>
              <PlanetTile>
                <planetTileType>Ice</planetTileType>
                <count>1</count>
              </PlanetTile>
            </planetTiles>
            <rawResources>
              <RawResource>
                <name>Armoroid</name>
                <id>1</id>
                <amount>953416</amount>
                <accessibility>0.96240663528442383</accessibility>
              </RawResource>
              <RawResource>
                <name>Coppode</name>
                <id>2</id>
                <amount>25411</amount>
                <accessibility>0.8361581563949585</accessibility>
              </RawResource>
            </rawResources>
            <population>0</population>
            <solarIndex>
              <int>325</int>
              <int>3</int>
              <int>2</int>
            </solarIndex>
          </SolarBody>
          <SolarBody>
            <name>Deskuerili 326Moon 4</name>
            <orbit>
              <sma>29.720302581787109</sma>
              <ecc>0.0036027359310537577</ecc>
              <inc>0</inc>
              <lpe>4.1241054534912109</lpe>
              <lan>0</lan>
              <mna>4.1241054534912109</mna>
              <eph>0</eph>
            </orbit>
            <groundStructures />
            <spaceStructures />
            <color>
              <r>0.5</r>
              <g>0.5</g>
              <b>0.5</b>
              <a>1</a>
            </color>
            <satelites />
            <totalPopulation>0</totalPopulation>
            <solarType>Moon</solarType>
            <solarSubType>Rocky</solarSubType>
            <mass>6.2433224916458128E+21</mass>
            <bodyRadius>702.2553930311841</bodyRadius>
            <lastKnownPosition>
              <x>0</x>
              <y>0</y>
            </lastKnownPosition>
            <surfaceTemp>125.33651780198628</surfaceTemp>
            <surfacePressure>0.81905025243759155</surfacePressure>
            <luminosity>0</luminosity>
            <bondAlebo>0.70419484376907349</bondAlebo>
            <greenhouse>0.089992780622299734</greenhouse>
            <surfaceGravity>0.086076069759398355</surfaceGravity>
            <planetTiles>
              <PlanetTile>
                <planetTileType>Rocky</planetTileType>
                <count>2</count>
              </PlanetTile>
            </planetTiles>
            <rawResources>
              <RawResource>
                <name>Armoroid</name>
                <id>1</id>
                <amount>953416</amount>
                <accessibility>0.970831036567688</accessibility>
              </RawResource>
            </rawResources>
            <population>0</population>
            <solarIndex>
              <int>325</int>
              <int>3</int>
              <int>3</int>
            </solarIndex>
          </SolarBody>
        </satelites>
        <totalPopulation>0</totalPopulation>
        <solarType>Comet</solarType>
        <solarSubType>Rocky</solarSubType>
        <mass>840000000000000</mass>
        <bodyRadius>3.6249316503523512</bodyRadius>
        <lastKnownPosition>
          <x>0</x>
          <y>0</y>
        </lastKnownPosition>
        <surfaceTemp>0</surfaceTemp>
        <surfacePressure>0</surfacePressure>
        <luminosity>0</luminosity>
        <bondAlebo>0.37057974934577942</bondAlebo>
        <greenhouse>0</greenhouse>
        <surfaceGravity>0.00043464678166740139</surfaceGravity>
        <planetTiles>
          <PlanetTile>
            <planetTileType>Rocky</planetTileType>
            <count>1</count>
          </PlanetTile>
        </planetTiles>
        <rawResources>
          <RawResource>
            <name>Armoroid</name>
            <id>1</id>
            <amount>953416</amount>
            <accessibility>0.83485257625579834</accessibility>
          </RawResource>
        </rawResources>
        <population>0</population>
        <solarIndex>
          <int>325</int>
          <int>3</int>
        </solarIndex>
      </SolarBody>
      <SolarBody>
        <name>Deskuerili 326 Comet 5</name>
        <orbit>
          <sma>2036110592</sma>
          <ecc>0.96773958206176758</ecc>
          <inc>0</inc>
          <lpe>3.5991344451904297</lpe>
          <lan>0</lan>
          <mna>3.5991344451904297</mna>
          <eph>0</eph>
        </orbit>
        <groundStructures />
        <spaceStructures />
        <color>
          <r>0.5</r>
          <g>0.5</g>
          <b>0.5</b>
          <a>1</a>
        </color>
        <satelites />
        <totalPopulation>0</totalPopulation>
        <solarType>Comet</solarType>
        <solarSubType>Rocky</solarSubType>
        <mass>750000000000000</mass>
        <bodyRadius>2.9504298855526683</bodyRadius>
        <lastKnownPosition>
          <x>0</x>
          <y>0</y>
        </lastKnownPosition>
        <surfaceTemp>0</surfaceTemp>
        <surfacePressure>0</surfacePressure>
        <luminosity>0</luminosity>
        <bondAlebo>0.62584501504898071</bondAlebo>
        <greenhouse>0</greenhouse>
        <surfaceGravity>0.00058579747179730987</surfaceGravity>
        <planetTiles>
          <PlanetTile>
            <planetTileType>Rocky</planetTileType>
            <count>1</count>
          </PlanetTile>
        </planetTiles>
        <rawResources>
          <RawResource>
            <name>Armoroid</name>
            <id>1</id>
            <amount>953416</amount>
            <accessibility>0.49279993772506714</accessibility>
          </RawResource>
        </rawResources>
        <population>0</population>
        <solarIndex>
          <int>325</int>
          <int>4</int>
        </solarIndex>
      </SolarBody>
      <SolarBody>
        <name>Deskuerili 326 Comet 6</name>
        <orbit>
          <sma>15402388480</sma>
          <ecc>0.56511068344116211</ecc>
          <inc>0</inc>
          <lpe>5.69375467300415</lpe>
          <lan>0</lan>
          <mna>5.69375467300415</mna>
          <eph>0</eph>
        </orbit>
        <groundStructures />
        <spaceStructures />
        <color>
          <r>0.5</r>
          <g>0.5</g>
          <b>0.5</b>
          <a>1</a>
        </color>
        <satelites />
        <totalPopulation>0</totalPopulation>
        <solarType>Comet</solarType>
        <solarSubType>Rocky</solarSubType>
        <mass>360000000000000</mass>
        <bodyRadius>2.7280537364666455</bodyRadius>
        <lastKnownPosition>
          <x>0</x>
          <y>0</y>
        </lastKnownPosition>
        <surfaceTemp>0</surfaceTemp>
        <surfacePressure>0</surfacePressure>
        <luminosity>0</luminosity>
        <bondAlebo>0.15352393686771393</bondAlebo>
        <greenhouse>0</greenhouse>
        <surfaceGravity>0.00032889213339431107</surfaceGravity>
        <planetTiles>
          <PlanetTile>
            <planetTileType>Rocky</planetTileType>
            <count>1</count>
          </PlanetTile>
        </planetTiles>
        <rawResources>
          <RawResource>
            <name>Armoroid</name>
            <id>1</id>
            <amount>953416</amount>
            <accessibility>0.44312018156051636</accessibility>
          </RawResource>
        </rawResources>
        <population>0</population>
        <solarIndex>
          <int>325</int>
          <int>5</int>
        </solarIndex>
      </SolarBody>
      <SolarBody>
        <name>Deskuerili 326 Planet 7</name>
        <orbit>
          <sma>7287126016</sma>
          <ecc>0.003228786401450634</ecc>
          <inc>0</inc>
          <lpe>4.8325910568237305</lpe>
          <lan>0</lan>
          <mna>4.8325910568237305</mna>
          <eph>0</eph>
        </orbit>
        <groundStructures />
        <spaceStructures />
        <color>
          <r>1</r>
          <g>1</g>
          <b>1</b>
          <a>1</a>
        </color>
        <satelites />
        <totalPopulation>0</totalPopulation>
        <solarType>Planet</solarType>
        <solarSubType>Ice</solarSubType>
        <mass>9.7395980834960934E+24</mass>
        <bodyRadius>8412.4357704657341</bodyRadius>
        <lastKnownPosition>
          <x>0</x>
          <y>0</y>
        </lastKnownPosition>
        <surfaceTemp>70.439975026956645</surfaceTemp>
        <surfacePressure>0.22473077476024628</surfacePressure>
        <luminosity>0</luminosity>
        <bondAlebo>0.34337309002876282</bondAlebo>
        <greenhouse>0.022858014951062725</greenhouse>
        <surfaceGravity>0.93573815718217057</surfaceGravity>
        <planetTiles>
          <PlanetTile>
            <planetTileType>Ice</planetTileType>
            <count>17</count>
          </PlanetTile>
          <PlanetTile>
            <planetTileType>Rocky</planetTileType>
            <count>2</count>
          </PlanetTile>
          <PlanetTile>
            <planetTileType>Ocean</planetTileType>
            <count>1</count>
          </PlanetTile>
        </planetTiles>
        <rawResources>
          <RawResource>
            <name>Glassitum</name>
            <id>6</id>
            <amount>381993</amount>
            <accessibility>0.2669481635093689</accessibility>
          </RawResource>
          <RawResource>
            <name>Warium</name>
            <id>4</id>
            <amount>49617</amount>
            <accessibility>0.9070897102355957</accessibility>
          </RawResource>
          <RawResource>
            <name>Armoroid</name>
            <id>1</id>
            <amount>407033</amount>
            <accessibility>0.96023261547088623</accessibility>
          </RawResource>
          <RawResource>
            <name>Coppode</name>
            <id>2</id>
            <amount>60457</amount>
            <accessibility>0.40067583322525024</accessibility>
          </RawResource>
          <RawResource>
            <name>Fuelodite</name>
            <id>3</id>
            <amount>859283</amount>
            <accessibility>0.092035055160522461</accessibility>
          </RawResource>
        </rawResources>
        <population>0</population>
        <solarIndex>
          <int>325</int>
          <int>6</int>
        </solarIndex>
      </SolarBody>
      <SolarBody>
        <name>Deskuerili 326 Planet 8</name>
        <orbit>
          <sma>11671153664</sma>
          <ecc>0.0087290676310658455</ecc>
          <inc>0</inc>
          <lpe>3.8641655445098877</lpe>
          <lan>0</lan>
          <mna>3.8641655445098877</mna>
          <eph>0</eph>
        </orbit>
        <groundStructures />
        <spaceStructures />
        <color>
          <r>1</r>
          <g>0.5</g>
          <b>0</b>
          <a>1</a>
        </color>
        <satelites>
          <SolarBody>
            <name>Deskuerili 326Moon 8</name>
            <orbit>
              <sma>9710193</sma>
              <ecc>0.0063076294027268887</ecc>
              <inc>0</inc>
              <lpe>5.5264744758605957</lpe>
              <lan>0</lan>
              <mna>5.5264744758605957</mna>
              <eph>0</eph>
            </orbit>
            <groundStructures />
            <spaceStructures />
            <color>
              <r>0.5</r>
              <g>0.5</g>
              <b>0.5</b>
              <a>1</a>
            </color>
            <satelites />
            <totalPopulation>0</totalPopulation>
            <solarType>Moon</solarType>
            <solarSubType>Rocky</solarSubType>
            <mass>2.4346590042114258E+23</mass>
            <bodyRadius>2325.9653844186541</bodyRadius>
            <lastKnownPosition>
              <x>0</x>
              <y>0</y>
            </lastKnownPosition>
            <surfaceTemp>55.37388255934345</surfaceTemp>
            <surfacePressure>0.03144136443734169</surfacePressure>
            <luminosity>0</luminosity>
            <bondAlebo>0.35067513585090637</bondAlebo>
            <greenhouse>0.0031145337064488513</greenhouse>
            <surfaceGravity>0.30597678369406878</surfaceGravity>
            <planetTiles>
              <PlanetTile>
                <planetTileType>Rocky</planetTileType>
                <count>6</count>
              </PlanetTile>
            </planetTiles>
            <rawResources>
              <RawResource>
                <name>Armoroid</name>
                <id>1</id>
                <amount>953416</amount>
                <accessibility>0.89477622509002686</accessibility>
              </RawResource>
              <RawResource>
                <name>Coppode</name>
                <id>2</id>
                <amount>25411</amount>
                <accessibility>0.28530365228652954</accessibility>
              </RawResource>
              <RawResource>
                <name>Warium</name>
                <id>4</id>
                <amount>38199</amount>
                <accessibility>0.77861130237579346</accessibility>
              </RawResource>
              <RawResource>
                <name>Fuelodite</name>
                <id>3</id>
                <amount>4961</amount>
                <accessibility>0.0063884258270263672</accessibility>
              </RawResource>
            </rawResources>
            <population>0</population>
            <solarIndex>
              <int>325</int>
              <int>7</int>
              <int>0</int>
            </solarIndex>
          </SolarBody>
          <SolarBody>
            <name>Deskuerili 326Moon 8</name>
            <orbit>
              <sma>37149120</sma>
              <ecc>0.01669984869658947</ecc>
              <inc>0</inc>
              <lpe>0.64666581153869629</lpe>
              <lan>0</lan>
              <mna>0.64666581153869629</mna>
              <eph>0</eph>
            </orbit>
            <groundStructures />
            <spaceStructures />
            <color>
              <r>1</r>
              <g>0</g>
              <b>0</b>
              <a>1</a>
            </color>
            <satelites />
            <totalPopulation>0</totalPopulation>
            <solarType>Moon</solarType>
            <solarSubType>Volcanic</solarSubType>
            <mass>4.6703132629394528E+23</mass>
            <bodyRadius>2782.5574366284359</bodyRadius>
            <lastKnownPosition>
              <x>0</x>
              <y>0</y>
            </lastKnownPosition>
            <surfaceTemp>31.4845302529434</surfaceTemp>
            <surfacePressure>0.92803502082824707</surfacePressure>
            <luminosity>0</luminosity>
            <bondAlebo>0.93440687656402588</bondAlebo>
            <greenhouse>0.10335639185432395</greenhouse>
            <surfaceGravity>0.41012341332883911</surfaceGravity>
            <planetTiles>
              <PlanetTile>
                <planetTileType>Volcanic</planetTileType>
                <count>7</count>
              </PlanetTile>
            </planetTiles>
            <rawResources>
              <RawResource>
                <name>Warium</name>
                <id>4</id>
                <amount>20793</amount>
                <accessibility>0.36978369951248169</accessibility>
              </RawResource>
              <RawResource>
                <name>Fuelodite</name>
                <id>3</id>
                <amount>90743</amount>
                <accessibility>0.899646520614624</accessibility>
              </RawResource>
              <RawResource>
                <name>Coppode</name>
                <id>2</id>
                <amount>83867</amount>
                <accessibility>0.00050485134124755859</accessibility>
              </RawResource>
              <RawResource>
                <name>Glassitum</name>
                <id>6</id>
                <amount>83492</amount>
                <accessibility>0.7190016508102417</accessibility>
              </RawResource>
              <RawResource>
                <name>Armoroid</name>
                <id>1</id>
                <amount>61494</amount>
                <accessibility>0.29949873685836792</accessibility>
              </RawResource>
            </rawResources>
            <population>0</population>
            <solarIndex>
              <int>325</int>
              <int>7</int>
              <int>1</int>
            </solarIndex>
          </SolarBody>
          <SolarBody>
            <name>Deskuerili 326Moon 8</name>
            <orbit>
              <sma>30202096</sma>
              <ecc>0.0096679171547293663</ecc>
              <inc>0</inc>
              <lpe>1.5318528413772583</lpe>
              <lan>0</lan>
              <mna>1.5318528413772583</mna>
              <eph>0</eph>
            </orbit>
            <groundStructures />
            <spaceStructures />
            <color>
              <r>0.5</r>
              <g>0.5</g>
              <b>0.5</b>
              <a>1</a>
            </color>
            <satelites />
            <totalPopulation>0</totalPopulation>
            <solarType>Moon</solarType>
            <solarSubType>Rocky</solarSubType>
            <mass>1.5923564910888673E+23</mass>
            <bodyRadius>1856.0854529713281</bodyRadius>
            <lastKnownPosition>
              <x>0</x>
              <y>0</y>
            </lastKnownPosition>
            <surfaceTemp>48.887055326876073</surfaceTemp>
            <surfacePressure>0.80360698699951172</surfacePressure>
            <luminosity>0</luminosity>
            <bondAlebo>0.6169617772102356</bondAlebo>
            <greenhouse>0.088125530343017858</greenhouse>
            <surfaceGravity>0.31426874784320147</surfaceGravity>
            <planetTiles>
              <PlanetTile>
                <planetTileType>Rocky</planetTileType>
                <count>5</count>
              </PlanetTile>
            </planetTiles>
            <rawResources>
              <RawResource>
                <name>Armoroid</name>
                <id>1</id>
                <amount>953416</amount>
                <accessibility>0.86585938930511475</accessibility>
              </RawResource>
              <RawResource>
                <name>Coppode</name>
                <id>2</id>
                <amount>25411</amount>
                <accessibility>0.04078364372253418</accessibility>
              </RawResource>
            </rawResources>
            <population>0</population>
            <solarIndex>
              <int>325</int>
              <int>7</int>
              <int>2</int>
            </solarIndex>
          </SolarBody>
          <SolarBody>
            <name>Deskuerili 326Moon 8</name>
            <orbit>
              <sma>313924.9375</sma>
              <ecc>0.00878231879323721</ecc>
              <inc>0</inc>
              <lpe>4.8024678230285645</lpe>
              <lan>0</lan>
              <mna>4.8024678230285645</mna>
              <eph>0</eph>
            </orbit>
            <groundStructures />
            <spaceStructures />
            <color>
              <r>0.5</r>
              <g>0.5</g>
              <b>0.5</b>
              <a>1</a>
            </color>
            <satelites />
            <totalPopulation>0</totalPopulation>
            <solarType>Moon</solarType>
            <solarSubType>Rocky</solarSubType>
            <mass>4.5921913146972653E+23</mass>
            <bodyRadius>2889.2688869539261</bodyRadius>
            <lastKnownPosition>
              <x>0</x>
              <y>0</y>
            </lastKnownPosition>
            <surfaceTemp>51.291822993881517</surfaceTemp>
            <surfacePressure>0.70241034030914307</surfacePressure>
            <luminosity>0</luminosity>
            <bondAlebo>0.5360834002494812</bondAlebo>
            <greenhouse>0.076051906704527161</greenhouse>
            <surfaceGravity>0.37402521182405252</surfaceGravity>
            <planetTiles>
              <PlanetTile>
                <planetTileType>Rocky</planetTileType>
                <count>6</count>
              </PlanetTile>
              <PlanetTile>
                <planetTileType>Desert</planetTileType>
                <count>1</count>
              </PlanetTile>
            </planetTiles>
            <rawResources>
              <RawResource>
                <name>Armoroid</name>
                <id>1</id>
                <amount>953416</amount>
                <accessibility>0.4556618332862854</accessibility>
              </RawResource>
              <RawResource>
                <name>Glassitum</name>
                <id>6</id>
                <amount>548445</amount>
                <accessibility>0.13462841510772705</accessibility>
              </RawResource>
              <RawResource>
                <name>Coppode</name>
                <id>2</id>
                <amount>25411</amount>
                <accessibility>0.27797573804855347</accessibility>
              </RawResource>
              <RawResource>
                <name>Warium</name>
                <id>4</id>
                <amount>38199</amount>
                <accessibility>0.87982463836669922</accessibility>
              </RawResource>
              <RawResource>
                <name>Fuelodite</name>
                <id>3</id>
                <amount>4961</amount>
                <accessibility>0.21333110332489014</accessibility>
              </RawResource>
            </rawResources>
            <population>0</population>
            <solarIndex>
              <int>325</int>
              <int>7</int>
              <int>3</int>
            </solarIndex>
          </SolarBody>
          <SolarBody>
            <name>Deskuerili 326Moon 8</name>
            <orbit>
              <sma>34795512</sma>
              <ecc>0.0007086610421538353</ecc>
              <inc>0</inc>
              <lpe>6.05313777923584</lpe>
              <lan>0</lan>
              <mna>6.05313777923584</mna>
              <eph>0</eph>
            </orbit>
            <groundStructures />
            <spaceStructures />
            <color>
              <r>1</r>
              <g>1</g>
              <b>1</b>
              <a>1</a>
            </color>
            <satelites />
            <totalPopulation>0</totalPopulation>
            <solarType>Moon</solarType>
            <solarSubType>Ice</solarSubType>
            <mass>4.1311862945556638E+23</mass>
            <bodyRadius>2459.4510690947377</bodyRadius>
            <lastKnownPosition>
              <x>0</x>
              <y>0</y>
            </lastKnownPosition>
            <surfaceTemp>30.029237916065494</surfaceTemp>
            <surfacePressure>0.63887315988540649</surfacePressure>
            <luminosity>0</luminosity>
            <bondAlebo>0.94501745700836182</bondAlebo>
            <greenhouse>0.068615116218043976</greenhouse>
            <surfaceGravity>0.46436046026549871</surfaceGravity>
            <planetTiles>
              <PlanetTile>
                <planetTileType>Ice</planetTileType>
                <count>5</count>
              </PlanetTile>
              <PlanetTile>
                <planetTileType>Rocky</planetTileType>
                <count>1</count>
              </PlanetTile>
            </planetTiles>
            <rawResources>
              <RawResource>
                <name>Glassitum</name>
                <id>6</id>
                <amount>381993</amount>
                <accessibility>0.88002204895019531</accessibility>
              </RawResource>
            </rawResources>
            <population>0</population>
            <solarIndex>
              <int>325</int>
              <int>7</int>
              <int>4</int>
            </solarIndex>
          </SolarBody>
          <SolarBody>
            <name>Deskuerili 326Moon 8</name>
            <orbit>
              <sma>39630888</sma>
              <ecc>0.0076588140800595284</ecc>
              <inc>0</inc>
              <lpe>3.2581801414489746</lpe>
              <lan>0</lan>
              <mna>3.2581801414489746</mna>
              <eph>0</eph>
            </orbit>
            <groundStructures />
            <spaceStructures />
            <color>
              <r>1</r>
              <g>1</g>
              <b>1</b>
              <a>1</a>
            </color>
            <satelites />
            <totalPopulation>0</totalPopulation>
            <solarType>Moon</solarType>
            <solarSubType>Ice</solarSubType>
            <mass>2.9478716850280761E+22</mass>
            <bodyRadius>1009.0094485999406</bodyRadius>
            <lastKnownPosition>
              <x>0</x>
              <y>0</y>
            </lastKnownPosition>
            <surfaceTemp>21.840082700557335</surfaceTemp>
            <surfacePressure>0.6881173849105835</surfacePressure>
            <luminosity>0</luminosity>
            <bondAlebo>0.98463737964630127</bondAlebo>
            <greenhouse>0.07436930370312396</greenhouse>
            <surfaceGravity>0.19686791237775214</surfaceGravity>
            <planetTiles>
              <PlanetTile>
                <planetTileType>Ice</planetTileType>
                <count>3</count>
              </PlanetTile>
            </planetTiles>
            <rawResources />
            <population>0</population>
            <solarIndex>
              <int>325</int>
              <int>7</int>
              <int>5</int>
            </solarIndex>
          </SolarBody>
          <SolarBody>
            <name>Deskuerili 326Moon 8</name>
            <orbit>
              <sma>41317832</sma>
              <ecc>0.0084987934678792953</ecc>
              <inc>0</inc>
              <lpe>0.84522420167922974</lpe>
              <lan>0</lan>
              <mna>0.84522420167922974</mna>
              <eph>0</eph>
            </orbit>
            <groundStructures />
            <spaceStructures />
            <color>
              <r>0.5</r>
              <g>0.5</g>
              <b>0.5</b>
              <a>1</a>
            </color>
            <satelites />
            <totalPopulation>0</totalPopulation>
            <solarType>Moon</solarType>
            <solarSubType>Rocky</solarSubType>
            <mass>1.2167040824890136E+23</mass>
            <bodyRadius>1702.0686579664427</bodyRadius>
            <lastKnownPosition>
              <x>0</x>
              <y>0</y>
            </lastKnownPosition>
            <surfaceTemp>32.422640086096848</surfaceTemp>
            <surfacePressure>0.670840859413147</surfacePressure>
            <luminosity>0</luminosity>
            <bondAlebo>0.92530286312103271</bondAlebo>
            <greenhouse>0.072342957273343528</greenhouse>
            <surfaceGravity>0.2855536018273504</surfaceGravity>
            <planetTiles>
              <PlanetTile>
                <planetTileType>Rocky</planetTileType>
                <count>4</count>
              </PlanetTile>
              <PlanetTile>
                <planetTileType>Ice</planetTileType>
                <count>1</count>
              </PlanetTile>
            </planetTiles>
            <rawResources>
              <RawResource>
                <name>Armoroid</name>
                <id>1</id>
                <amount>953416</amount>
                <accessibility>0.80710327625274658</accessibility>
              </RawResource>
              <RawResource>
                <name>Coppode</name>
                <id>2</id>
                <amount>25411</amount>
                <accessibility>0.3625836968421936</accessibility>
              </RawResource>
            </rawResources>
            <population>0</population>
            <solarIndex>
              <int>325</int>
              <int>7</int>
              <int>6</int>
            </solarIndex>
          </SolarBody>
          <SolarBody>
            <name>Deskuerili 326Moon 8</name>
            <orbit>
              <sma>33683728</sma>
              <ecc>0.0095974672585725784</ecc>
              <inc>0</inc>
              <lpe>0.1279083788394928</lpe>
              <lan>0</lan>
              <mna>0.1279083788394928</mna>
              <eph>0</eph>
            </orbit>
            <groundStructures />
            <spaceStructures />
            <color>
              <r>0.5</r>
              <g>0.5</g>
              <b>0.5</b>
              <a>1</a>
            </color>
            <satelites />
            <totalPopulation>0</totalPopulation>
            <solarType>Moon</solarType>
            <solarSubType>Rocky</solarSubType>
            <mass>4.9059520721435544E+23</mass>
            <bodyRadius>3170.7696504655114</bodyRadius>
            <lastKnownPosition>
              <x>0</x>
              <y>0</y>
            </lastKnownPosition>
            <surfaceTemp>37.155590803350179</surfaceTemp>
            <surfacePressure>0.71946394443511963</surfacePressure>
            <luminosity>0</luminosity>
            <bondAlebo>0.87162244319915771</bondAlebo>
            <greenhouse>0.078066841451655364</greenhouse>
            <surfaceGravity>0.33178041223494126</surfaceGravity>
            <planetTiles>
              <PlanetTile>
                <planetTileType>Rocky</planetTileType>
                <count>8</count>
              </PlanetTile>
            </planetTiles>
            <rawResources>
              <RawResource>
                <name>Armoroid</name>
                <id>1</id>
                <amount>953416</amount>
                <accessibility>0.16852223873138428</accessibility>
              </RawResource>
              <RawResource>
                <name>Coppode</name>
                <id>2</id>
                <amount>25411</amount>
                <accessibility>0.16675567626953125</accessibility>
              </RawResource>
              <RawResource>
                <name>Warium</name>
                <id>4</id>
                <amount>38199</amount>
                <accessibility>0.61460107564926147</accessibility>
              </RawResource>
              <RawResource>
                <name>Fuelodite</name>
                <id>3</id>
                <amount>4961</amount>
                <accessibility>0.13270878791809082</accessibility>
              </RawResource>
            </rawResources>
            <population>0</population>
            <solarIndex>
              <int>325</int>
              <int>7</int>
              <int>7</int>
            </solarIndex>
          </SolarBody>
          <SolarBody>
            <name>Deskuerili 326Moon 8</name>
            <orbit>
              <sma>28640056</sma>
              <ecc>0.0072432025335729122</ecc>
              <inc>0</inc>
              <lpe>1.8842486143112183</lpe>
              <lan>0</lan>
              <mna>1.8842486143112183</mna>
              <eph>0</eph>
            </orbit>
            <groundStructures />
            <spaceStructures />
            <color>
              <r>0.5</r>
              <g>0.5</g>
              <b>0.5</b>
              <a>1</a>
            </color>
            <satelites />
            <totalPopulation>0</totalPopulation>
            <solarType>Moon</solarType>
            <solarSubType>Rocky</solarSubType>
            <mass>4.7845439910888669E+23</mass>
            <bodyRadius>2665.6598378978288</bodyRadius>
            <lastKnownPosition>
              <x>0</x>
              <y>0</y>
            </lastKnownPosition>
            <surfaceTemp>41.565927485820978</surfaceTemp>
            <surfacePressure>0.38035088777542114</surfacePressure>
            <luminosity>0</luminosity>
            <bondAlebo>0.79609811305999756</bondAlebo>
            <greenhouse>0.03949943310462125</greenhouse>
            <surfaceGravity>0.4578127895773913</surfaceGravity>
            <planetTiles>
              <PlanetTile>
                <planetTileType>Rocky</planetTileType>
                <count>7</count>
              </PlanetTile>
            </planetTiles>
            <rawResources>
              <RawResource>
                <name>Armoroid</name>
                <id>1</id>
                <amount>953416</amount>
                <accessibility>0.37872117757797241</accessibility>
              </RawResource>
              <RawResource>
                <name>Coppode</name>
                <id>2</id>
                <amount>25411</amount>
                <accessibility>0.79362225532531738</accessibility>
              </RawResource>
              <RawResource>
                <name>Warium</name>
                <id>4</id>
                <amount>38199</amount>
                <accessibility>0.15070748329162598</accessibility>
              </RawResource>
              <RawResource>
                <name>Fuelodite</name>
                <id>3</id>
                <amount>4961</amount>
                <accessibility>0.53692585229873657</accessibility>
              </RawResource>
            </rawResources>
            <population>0</population>
            <solarIndex>
              <int>325</int>
              <int>7</int>
              <int>8</int>
            </solarIndex>
          </SolarBody>
          <SolarBody>
            <name>Deskuerili 326Moon 8</name>
            <orbit>
              <sma>12166283</sma>
              <ecc>0.0077217253856360912</ecc>
              <inc>0</inc>
              <lpe>3.0733983516693115</lpe>
              <lan>0</lan>
              <mna>3.0733983516693115</mna>
              <eph>0</eph>
            </orbit>
            <groundStructures />
            <spaceStructures />
            <color>
              <r>1</r>
              <g>1</g>
              <b>1</b>
              <a>1</a>
            </color>
            <satelites />
            <totalPopulation>0</totalPopulation>
            <solarType>Moon</solarType>
            <solarSubType>Ice</solarSubType>
            <mass>1.0830665826797485E+22</mass>
            <bodyRadius>775.94655356744613</bodyRadius>
            <lastKnownPosition>
              <x>0</x>
              <y>0</y>
            </lastKnownPosition>
            <surfaceTemp>56.038934711599573</surfaceTemp>
            <surfacePressure>0.62608230113983154</surfacePressure>
            <luminosity>0</luminosity>
            <bondAlebo>0.33537951111793518</bondAlebo>
            <greenhouse>0.067131401157463175</greenhouse>
            <surfaceGravity>0.12230616976324642</surfaceGravity>
            <planetTiles>
              <PlanetTile>
                <planetTileType>Rocky</planetTileType>
                <count>1</count>
              </PlanetTile>
              <PlanetTile>
                <planetTileType>Ice</planetTileType>
                <count>1</count>
              </PlanetTile>
            </planetTiles>
            <rawResources>
              <RawResource>
                <name>Armoroid</name>
                <id>1</id>
                <amount>953416</amount>
                <accessibility>0.26600569486618042</accessibility>
              </RawResource>
            </rawResources>
            <population>0</population>
            <solarIndex>
              <int>325</int>
              <int>7</int>
              <int>9</int>
            </solarIndex>
          </SolarBody>
          <SolarBody>
            <name>Deskuerili 326Moon 8</name>
            <orbit>
              <sma>33462816</sma>
              <ecc>0.0034224651753902435</ecc>
              <inc>0</inc>
              <lpe>2.8730497360229492</lpe>
              <lan>0</lan>
              <mna>2.8730497360229492</mna>
              <eph>0</eph>
            </orbit>
            <groundStructures />
            <spaceStructures />
            <color>
              <r>0.5</r>
              <g>0.5</g>
              <b>0.5</b>
              <a>1</a>
            </color>
            <satelites />
            <totalPopulation>0</totalPopulation>
            <solarType>Moon</solarType>
            <solarSubType>Rocky</solarSubType>
            <mass>4.5412506103515627E+23</mass>
            <bodyRadius>2822.9294981330227</bodyRadius>
            <lastKnownPosition>
              <x>0</x>
              <y>0</y>
            </lastKnownPosition>
            <surfaceTemp>38.401181131133704</surfaceTemp>
            <surfacePressure>0.5590863823890686</surfacePressure>
            <luminosity>0</luminosity>
            <bondAlebo>0.85247683525085449</bondAlebo>
            <greenhouse>0.05943341034142214</greenhouse>
            <surfaceGravity>0.38746478008370083</surfaceGravity>
            <planetTiles>
              <PlanetTile>
                <planetTileType>Rocky</planetTileType>
                <count>7</count>
              </PlanetTile>
            </planetTiles>
            <rawResources>
              <RawResource>
                <name>Armoroid</name>
                <id>1</id>
                <amount>953416</amount>
                <accessibility>0.832787275314331</accessibility>
              </RawResource>
              <RawResource>
                <name>Coppode</name>
                <id>2</id>
                <amount>25411</amount>
                <accessibility>0.63039553165435791</accessibility>
              </RawResource>
              <RawResource>
                <name>Warium</name>
                <id>4</id>
                <amount>38199</amount>
                <accessibility>0.11274158954620361</accessibility>
              </RawResource>
              <RawResource>
                <name>Fuelodite</name>
                <id>3</id>
                <amount>4961</amount>
                <accessibility>0.61115294694900513</accessibility>
              </RawResource>
            </rawResources>
            <population>0</population>
            <solarIndex>
              <int>325</int>
              <int>7</int>
              <int>10</int>
            </solarIndex>
          </SolarBody>
          <SolarBody>
            <name>Deskuerili 326Moon 8</name>
            <orbit>
              <sma>13507395</sma>
              <ecc>0.016354655846953392</ecc>
              <inc>0</inc>
              <lpe>2.7291357517242432</lpe>
              <lan>0</lan>
              <mna>2.7291357517242432</mna>
              <eph>0</eph>
            </orbit>
            <groundStructures />
            <spaceStructures />
            <color>
              <r>1</r>
              <g>1</g>
              <b>1</b>
              <a>1</a>
            </color>
            <satelites />
            <totalPopulation>0</totalPopulation>
            <solarType>Moon</solarType>
            <solarSubType>Ice</solarSubType>
            <mass>1.1965648651123047E+23</mass>
            <bodyRadius>1673.9103149233881</bodyRadius>
            <lastKnownPosition>
              <x>0</x>
              <y>0</y>
            </lastKnownPosition>
            <surfaceTemp>60.69895147879177</surfaceTemp>
            <surfacePressure>0.9174540638923645</surfacePressure>
            <luminosity>0</luminosity>
            <bondAlebo>0.0970693975687027</bondAlebo>
            <greenhouse>0.10204466604669066</greenhouse>
            <surfaceGravity>0.29035459399930957</surfaceGravity>
            <planetTiles>
              <PlanetTile>
                <planetTileType>Ice</planetTileType>
                <count>2</count>
              </PlanetTile>
              <PlanetTile>
                <planetTileType>Ocean</planetTileType>
                <count>1</count>
              </PlanetTile>
              <PlanetTile>
                <planetTileType>Rocky</planetTileType>
                <count>1</count>
              </PlanetTile>
            </planetTiles>
            <rawResources />
            <population>0</population>
            <solarIndex>
              <int>325</int>
              <int>7</int>
              <int>11</int>
            </solarIndex>
          </SolarBody>
          <SolarBody>
            <name>Deskuerili 326Moon 8</name>
            <orbit>
              <sma>37237772</sma>
              <ecc>0.019387586042284966</ecc>
              <inc>0</inc>
              <lpe>5.8301692008972168</lpe>
              <lan>0</lan>
              <mna>5.8301692008972168</mna>
              <eph>0</eph>
            </orbit>
            <groundStructures />
            <spaceStructures />
            <color>
              <r>1</r>
              <g>1</g>
              <b>1</b>
              <a>1</a>
            </color>
            <satelites />
            <totalPopulation>0</totalPopulation>
            <solarType>Moon</solarType>
            <solarSubType>Ice</solarSubType>
            <mass>4.9140520095825191E+22</mass>
            <bodyRadius>1222.9555542975338</bodyRadius>
            <lastKnownPosition>
              <x>0</x>
              <y>0</y>
            </lastKnownPosition>
            <surfaceTemp>26.535529019769555</surfaceTemp>
            <surfacePressure>0.22184287011623383</surfacePressure>
            <luminosity>0</luminosity>
            <bondAlebo>0.96585822105407715</bondAlebo>
            <greenhouse>0.022555479774381951</greenhouse>
            <surfaceGravity>0.22339591510042547</surfaceGravity>
            <planetTiles>
              <PlanetTile>
                <planetTileType>Ice</planetTileType>
                <count>3</count>
              </PlanetTile>
            </planetTiles>
            <rawResources />
            <population>0</population>
            <solarIndex>
              <int>325</int>
              <int>7</int>
              <int>12</int>
            </solarIndex>
          </SolarBody>
          <SolarBody>
            <name>Deskuerili 326Moon 8</name>
            <orbit>
              <sma>36862712</sma>
              <ecc>0.017216665670275688</ecc>
              <inc>0</inc>
              <lpe>0.040189098566770554</lpe>
              <lan>0</lan>
              <mna>0.040189098566770554</mna>
              <eph>0</eph>
            </orbit>
            <groundStructures />
            <spaceStructures />
            <color>
              <r>0.5</r>
              <g>0.5</g>
              <b>0.5</b>
              <a>1</a>
            </color>
            <satelites />
            <totalPopulation>0</totalPopulation>
            <solarType>Moon</solarType>
            <solarSubType>Rocky</solarSubType>
            <mass>2.3667922973632813E+23</mass>
            <bodyRadius>2110.0943081473461</bodyRadius>
            <lastKnownPosition>
              <x>0</x>
              <y>0</y>
            </lastKnownPosition>
            <surfaceTemp>58.143462649300659</surfaceTemp>
            <surfacePressure>0.931466817855835</surfacePressure>
            <luminosity>0</luminosity>
            <bondAlebo>0.23725095391273499</bondAlebo>
            <greenhouse>0.10378249361171753</greenhouse>
            <surfaceGravity>0.36142088227733488</surfaceGravity>
            <planetTiles>
              <PlanetTile>
                <planetTileType>Rocky</planetTileType>
                <count>4</count>
              </PlanetTile>
              <PlanetTile>
                <planetTileType>Volcanic</planetTileType>
                <count>1</count>
              </PlanetTile>
            </planetTiles>
            <rawResources>
              <RawResource>
                <name>Armoroid</name>
                <id>1</id>
                <amount>953416</amount>
                <accessibility>0.25714069604873657</accessibility>
              </RawResource>
              <RawResource>
                <name>Coppode</name>
                <id>2</id>
                <amount>51972</amount>
                <accessibility>0.24537551403045654</accessibility>
              </RawResource>
            </rawResources>
            <population>0</population>
            <solarIndex>
              <int>325</int>
              <int>7</int>
              <int>13</int>
            </solarIndex>
          </SolarBody>
        </satelites>
        <totalPopulation>0</totalPopulation>
        <solarType>Planet</solarType>
        <solarSubType>GasGiant</solarSubType>
        <mass>2.8000000000000003E+26</mass>
        <bodyRadius>44694.912689606</bodyRadius>
        <lastKnownPosition>
          <x>0</x>
          <y>0</y>
        </lastKnownPosition>
        <surfaceTemp>146.53383533799234</surfaceTemp>
        <surfacePressure>95</surfacePressure>
        <luminosity>0</luminosity>
        <bondAlebo>0.40564686059951782</bondAlebo>
        <greenhouse>133.3080565</greenhouse>
        <surfaceGravity>0.95301266326987388</surfaceGravity>
        <planetTiles />
        <rawResources />
        <population>0</population>
        <solarIndex>
          <int>325</int>
          <int>7</int>
        </solarIndex>
      </SolarBody>
      <SolarBody>
        <name>Deskuerili 326 DwarfPlanet 9</name>
        <orbit>
          <sma>10383037440</sma>
          <ecc>0.35339570045471191</ecc>
          <inc>0</inc>
          <lpe>0.49962759017944336</lpe>
          <lan>0</lan>
          <mna>0.49962759017944336</mna>
          <eph>0</eph>
        </orbit>
        <groundStructures />
        <spaceStructures />
        <color>
          <r>0.5</r>
          <g>0.5</g>
          <b>0.5</b>
          <a>1</a>
        </color>
        <satelites />
        <totalPopulation>0</totalPopulation>
        <solarType>DwarfPlanet</solarType>
        <solarSubType>Rocky</solarSubType>
        <mass>3E+22</mass>
        <bodyRadius>1017.7121971223174</bodyRadius>
        <lastKnownPosition>
          <x>0</x>
          <y>0</y>
        </lastKnownPosition>
        <surfaceTemp>64.940181599203967</surfaceTemp>
        <surfacePressure>0.64472562074661255</surfacePressure>
        <luminosity>0</luminosity>
        <bondAlebo>0.054146774113178253</bondAlebo>
        <greenhouse>0.069295488819469619</greenhouse>
        <surfaceGravity>0.19693736474830489</surfaceGravity>
        <planetTiles>
          <PlanetTile>
            <planetTileType>Rocky</planetTileType>
            <count>3</count>
          </PlanetTile>
        </planetTiles>
        <rawResources>
          <RawResource>
            <name>Armoroid</name>
            <id>1</id>
            <amount>953416</amount>
            <accessibility>0.15645384788513184</accessibility>
          </RawResource>
        </rawResources>
        <population>0</population>
        <solarIndex>
          <int>325</int>
          <int>8</int>
        </solarIndex>
      </SolarBody>
      <SolarBody>
        <name>Deskuerili 326 Comet 10</name>
        <orbit>
          <sma>5086866944</sma>
          <ecc>0.928261935710907</ecc>
          <inc>0</inc>
          <lpe>2.8373584747314453</lpe>
          <lan>0</lan>
          <mna>2.8373584747314453</mna>
          <eph>0</eph>
        </orbit>
        <groundStructures />
        <spaceStructures />
        <color>
          <r>0.5</r>
          <g>0.5</g>
          <b>0.5</b>
          <a>1</a>
        </color>
        <satelites>
          <SolarBody>
            <name>Deskuerili 326Moon 10</name>
            <orbit>
              <sma>310.40939331054688</sma>
              <ecc>0.0021728991996496916</ecc>
              <inc>0</inc>
              <lpe>2.4302747249603271</lpe>
              <lan>0</lan>
              <mna>2.4302747249603271</mna>
              <eph>0</eph>
            </orbit>
            <groundStructures />
            <spaceStructures />
            <color>
              <r>0.5</r>
              <g>0.5</g>
              <b>0.5</b>
              <a>1</a>
            </color>
            <satelites />
            <totalPopulation>0</totalPopulation>
            <solarType>Moon</solarType>
            <solarSubType>Rocky</solarSubType>
            <mass>4.805037307739258E+23</mass>
            <bodyRadius>2934.5527907338355</bodyRadius>
            <lastKnownPosition>
              <x>0</x>
              <y>0</y>
            </lastKnownPosition>
            <surfaceTemp>85.512554236154415</surfaceTemp>
            <surfacePressure>0.88079839944839478</surfacePressure>
            <luminosity>0</luminosity>
            <bondAlebo>0.32475355267524719</bondAlebo>
            <greenhouse>0.097524225674239129</greenhouse>
            <surfaceGravity>0.37937589881156947</surfaceGravity>
            <planetTiles>
              <PlanetTile>
                <planetTileType>Rocky</planetTileType>
                <count>5</count>
              </PlanetTile>
              <PlanetTile>
                <planetTileType>Ice</planetTileType>
                <count>1</count>
              </PlanetTile>
              <PlanetTile>
                <planetTileType>Desert</planetTileType>
                <count>1</count>
              </PlanetTile>
            </planetTiles>
            <rawResources>
              <RawResource>
                <name>Armoroid</name>
                <id>1</id>
                <amount>953416</amount>
                <accessibility>0.15683043003082275</accessibility>
              </RawResource>
              <RawResource>
                <name>Coppode</name>
                <id>2</id>
                <amount>25411</amount>
                <accessibility>0.24022138118743896</accessibility>
              </RawResource>
              <RawResource>
                <name>Warium</name>
                <id>4</id>
                <amount>38199</amount>
                <accessibility>0.47278517484664917</accessibility>
              </RawResource>
              <RawResource>
                <name>Fuelodite</name>
                <id>3</id>
                <amount>4961</amount>
                <accessibility>0.82705783843994141</accessibility>
              </RawResource>
            </rawResources>
            <population>0</population>
            <solarIndex>
              <int>325</int>
              <int>9</int>
              <int>0</int>
            </solarIndex>
          </SolarBody>
          <SolarBody>
            <name>Deskuerili 326Moon 10</name>
            <orbit>
              <sma>34.018669128417969</sma>
              <ecc>0.0018148755189031363</ecc>
              <inc>0</inc>
              <lpe>1.7529449462890625</lpe>
              <lan>0</lan>
              <mna>1.7529449462890625</mna>
              <eph>0</eph>
            </orbit>
            <groundStructures />
            <spaceStructures />
            <color>
              <r>0.5</r>
              <g>0.5</g>
              <b>0.5</b>
              <a>1</a>
            </color>
            <satelites />
            <totalPopulation>0</totalPopulation>
            <solarType>Moon</solarType>
            <solarSubType>Rocky</solarSubType>
            <mass>4.7842803955078123E+23</mass>
            <bodyRadius>2653.1566547790271</bodyRadius>
            <lastKnownPosition>
              <x>0</x>
              <y>0</y>
            </lastKnownPosition>
            <surfaceTemp>76.51117458579624</surfaceTemp>
            <surfacePressure>0.56819403171539307</surfacePressure>
            <luminosity>0</luminosity>
            <bondAlebo>0.56107133626937866</bondAlebo>
            <greenhouse>0.060472660676171165</greenhouse>
            <surfaceGravity>0.46211244467558843</surfaceGravity>
            <planetTiles>
              <PlanetTile>
                <planetTileType>Volcanic</planetTileType>
                <count>2</count>
              </PlanetTile>
              <PlanetTile>
                <planetTileType>Rocky</planetTileType>
                <count>5</count>
              </PlanetTile>
            </planetTiles>
            <rawResources>
              <RawResource>
                <name>Warium</name>
                <id>4</id>
                <amount>20793</amount>
                <accessibility>0.36576932668685913</accessibility>
              </RawResource>
              <RawResource>
                <name>Fuelodite</name>
                <id>3</id>
                <amount>90743</amount>
                <accessibility>0.66187751293182373</accessibility>
              </RawResource>
              <RawResource>
                <name>Coppode</name>
                <id>2</id>
                <amount>83867</amount>
                <accessibility>0.27406233549118042</accessibility>
              </RawResource>
              <RawResource>
                <name>Glassitum</name>
                <id>6</id>
                <amount>25411</amount>
                <accessibility>0.43468457460403442</accessibility>
              </RawResource>
              <RawResource>
                <name>Goldium</name>
                <id>0</id>
                <amount>381</amount>
                <accessibility>0.97690653800964355</accessibility>
              </RawResource>
              <RawResource>
                <name>Armoroid</name>
                <id>1</id>
                <amount>974890</amount>
                <accessibility>0.42490082979202271</accessibility>
              </RawResource>
            </rawResources>
            <population>0</population>
            <solarIndex>
              <int>325</int>
              <int>9</int>
              <int>1</int>
            </solarIndex>
          </SolarBody>
        </satelites>
        <totalPopulation>0</totalPopulation>
        <solarType>Comet</solarType>
        <solarSubType>Rocky</solarSubType>
        <mass>590000000000000</mass>
        <bodyRadius>2.8007426548392154</bodyRadius>
        <lastKnownPosition>
          <x>0</x>
          <y>0</y>
        </lastKnownPosition>
        <surfaceTemp>0</surfaceTemp>
        <surfacePressure>0</surfacePressure>
        <luminosity>0</luminosity>
        <bondAlebo>0.15311922132968903</bondAlebo>
        <greenhouse>0</greenhouse>
        <surfaceGravity>0.00051140200551985909</surfaceGravity>
        <planetTiles>
          <PlanetTile>
            <planetTileType>Rocky</planetTileType>
            <count>1</count>
          </PlanetTile>
        </planetTiles>
        <rawResources>
          <RawResource>
            <name>Armoroid</name>
            <id>1</id>
            <amount>953416</amount>
            <accessibility>0.16913032531738281</accessibility>
          </RawResource>
        </rawResources>
        <population>0</population>
        <solarIndex>
          <int>325</int>
          <int>9</int>
        </solarIndex>
      </SolarBody>
      <SolarBody>
        <name>Deskuerili 326 Comet 11</name>
        <orbit>
          <sma>15780802560</sma>
          <ecc>0.77246534824371338</ecc>
          <inc>0</inc>
          <lpe>1.8992348909378052</lpe>
          <lan>0</lan>
          <mna>1.8992348909378052</mna>
          <eph>0</eph>
        </orbit>
        <groundStructures />
        <spaceStructures />
        <color>
          <r>0.5</r>
          <g>0.5</g>
          <b>0.5</b>
          <a>1</a>
        </color>
        <satelites />
        <totalPopulation>0</totalPopulation>
        <solarType>Comet</solarType>
        <solarSubType>Rocky</solarSubType>
        <mass>890000000000000</mass>
        <bodyRadius>3.3767118178568256</bodyRadius>
        <lastKnownPosition>
          <x>0</x>
          <y>0</y>
        </lastKnownPosition>
        <surfaceTemp>0</surfaceTemp>
        <surfacePressure>0</surfacePressure>
        <luminosity>0</luminosity>
        <bondAlebo>0.11359359323978424</bondAlebo>
        <greenhouse>0</greenhouse>
        <surfaceGravity>0.00053071191444218875</surfaceGravity>
        <planetTiles>
          <PlanetTile>
            <planetTileType>Rocky</planetTileType>
            <count>1</count>
          </PlanetTile>
        </planetTiles>
        <rawResources>
          <RawResource>
            <name>Armoroid</name>
            <id>1</id>
            <amount>953416</amount>
            <accessibility>0.8351891040802002</accessibility>
          </RawResource>
        </rawResources>
        <population>0</population>
        <solarIndex>
          <int>325</int>
          <int>10</int>
        </solarIndex>
      </SolarBody>
      <SolarBody>
        <name>Deskuerili 326 DwarfPlanet 12</name>
        <orbit>
          <sma>23920123904</sma>
          <ecc>0.28977394104003906</ecc>
          <inc>0</inc>
          <lpe>3.0906128883361816</lpe>
          <lan>0</lan>
          <mna>3.0906128883361816</mna>
          <eph>0</eph>
        </orbit>
        <groundStructures />
        <spaceStructures />
        <color>
          <r>1</r>
          <g>1</g>
          <b>1</b>
          <a>1</a>
        </color>
        <satelites />
        <totalPopulation>0</totalPopulation>
        <solarType>DwarfPlanet</solarType>
        <solarSubType>Ice</solarSubType>
        <mass>1.7E+22</mass>
        <bodyRadius>936.589139549396</bodyRadius>
        <lastKnownPosition>
          <x>0</x>
          <y>0</y>
        </lastKnownPosition>
        <surfaceTemp>25.831197203882194</surfaceTemp>
        <surfacePressure>0.78213638067245483</surfacePressure>
        <luminosity>0</luminosity>
        <bondAlebo>0.87511014938354492</bondAlebo>
        <greenhouse>0.085540396415905745</greenhouse>
        <surfaceGravity>0.1317672593005349</surfaceGravity>
        <planetTiles>
          <PlanetTile>
            <planetTileType>Ice</planetTileType>
            <count>2</count>
          </PlanetTile>
          <PlanetTile>
            <planetTileType>Rocky</planetTileType>
            <count>1</count>
          </PlanetTile>
        </planetTiles>
        <rawResources />
        <population>0</population>
        <solarIndex>
          <int>325</int>
          <int>11</int>
        </solarIndex>
      </SolarBody>
    </satelites>
    <totalPopulation>0</totalPopulation>
    <solarType>Star</solarType>
    <solarSubType>GasGiant</solarSubType>
    <mass>1.7620208026885985E+32</mass>
    <bodyRadius>32733682.414188288</bodyRadius>
    <lastKnownPosition>
      <x>0</x>
      <y>0</y>
    </lastKnownPosition>
    <surfaceTemp>36895</surfaceTemp>
    <surfacePressure>1</surfacePressure>
    <luminosity>5.6242701447863387E+27</luminosity>
    <bondAlebo>0.5</bondAlebo>
    <greenhouse>0.1123595</greenhouse>
    <surfaceGravity>1.118093515998869</surfaceGravity>
    <planetTiles />
    <rawResources />
    <population>0</population>
    <solarIndex>
      <int>325</int>
    </solarIndex>
  </solar>
  <nearStars>
    <Id>54981114-70cc-4d95-875c-b217bee940c9</Id>
    <Id>54981114-70cc-4d95-875c-b217bee940c9</Id>
    <Id>32388dbe-daf3-43bf-8217-48652acb441a</Id>
  </nearStars>
  <government />
  <governmentInfluence>0</governmentInfluence>
  <isCapital>false</isCapital>
  <index>325</index>
</SolarModel>